Workbook
Name NativeTimeline_Date: #N/A
Name Slicer_Customer_Name: #N/A
Name Slicer_Months__Timestamp: #N/A
Name Slicer_Select__Set_Categories: #N/A
Name Slicer_Service_item_category: #N/A
Name Slicer_Unit_Price_per_crate: #N/A
Name Slicer_Years__Timestamp: #N/A

Sheet Egg sorting&grading
A1: Timestamp | B1: COLLECTION DATE | C1: Select SET | D1: Select Size | E1: Number of crates | F1: Number of singles(pcs) | G1: Do you still have some more data to record
A2: 46055.332 | B2: 46054 | C2: SET A | D2: S - (45 GHS) | E2: 0 | F2: 10
A3: 46055.332 | B3: 46054 | C3: SET A | D3: M - (50 GHS) | E3: 0 | F3: 17
A4: 46055.333 | B4: 46054 | C4: SET A | D4: L - (55 GHS) | E4: 0 | F4: 23
A5: 46055.333 | B5: 46054 | C5: SET A | D5: XL - (60 GHS) | E5: 0 | F5: 5
A6: 46055.333 | B6: 46054 | C6: SET B | D6: XS - (40 GHS) | E6: 0 | F6: 13
A7: 46055.334 | B7: 46054 | C7: SET B | D7: S - (45 GHS) | E7: 2 | F7: 29
A8: 46055.334 | B8: 46054 | C8: SET B | D8: M - (50 GHS) | E8: 6 | F8: 6
A9: 46055.334 | B9: 46054 | C9: SET B | D9: L - (55 GHS) | E9: 4 | F9: 17
A10: 46055.335 | B10: 46054 | C10: SET B | D10: XL - (60 GHS) | E10: 1 | F10: 1
A11: 46055.335 | B11: 46054 | C11: SET C | D11: XS - (40 GHS) | E11: 0 | F11: 24
A12: 46055.335 | B12: 46054 | C12: SET C | D12: S - (45 GHS) | E12: 4 | F12: 17
A13: 46055.336 | B13: 46054 | C13: SET C | D13: M - (50 GHS) | E13: 4 | F13: 9
... A15: 46055.339 | B15: 46054 | C15: SET C | D15: XL - (60 GHS) | E15: 0 | F15: 6

Sheet Sales by Month
A2: Month | B2: (All)
A4: Sum of Amount Paid | B4: Column Labels
A5: Row Labels | B5: 2026 | C5: Grand Total
A6: Jan | B6: 40940 | C6: 40940
A7: Feb | B7: 15750 | C7: 15750
A8: Grand Total | B8: 56690 | C8: 56690
A23: total sales | B23: =GETPIVOTDATA("Amount Paid",$A$4) -> 56690
A24: Profit | B24: =B23-'MOM Expenses'!B25 -> -104784
A30: Month | B30: (All)
A32: Average of Unit Price(per crate) | B32: Column Labels
A33: Row Labels | B33: 2026 | C33: Grand Total
A34: Jan | B34: 48.75 | C34: 48.75
A35: Feb | B35: 48.461538 | C35: 48.461538
A36: Grand Total | B36: 48.677419 | C36: 48.677419
A48: Average Price/crate | B48: =GETPIVOTDATA("Unit Price(per crate)",$A$32) -> 48.677419

Sheet Sales by Size
A1: Months (Date) | B1: (All)
A3: Sum of Amount Paid | B3: Column Labels
A4: Row Labels | B4: 2026 | C4: Grand Total
A5: 40 | B5: 4480 | C5: 4480
A6: 45 | B6: 14535 | C6: 14535
A7: 50 | B7: 20800 | C7: 20800
A8: 55 | B8: 13475 | C8: 13475
A9: 60 | B9: 2100 | C9: 2100
A10: 65 | B10: 1300 | C10: 1300
A11: Grand Total | B11: 56690 | C11: 56690

Sheet Sales by Customer
A1: Month | B1: (All)
A3: Row Labels | B3: Sum of Amount Paid
A4: AB Prime | B4: 150
A5: Aberkuma North K | B5: 3250
A6: Aberkuma North K | B6: 5950
A7: Afriyie Agric | B7: 950
A8: Agya Atta | B8: 50
A9: Amelia Adabraka | B9: 550
A10: Amelia Adabraka | B10: 500
A11: Amelia Kotoku | B11: 200
A12: Amelia Kotoku | B12: 100
A13: Ant Gina | B13: 80
A14: Ant Gina | B14: 120
A15: Ant Lydia | B15: 500
... A84: Grand Total | B84: 56690

Sheet Quantity Sold byMonth
A1: Month | B1: (All)
A3: Sum of Quantity | B3: Column Labels
A4: Row Labels | B4: 2026 | C4: Grand Total
A5: Jan | B5: 836 | C5: 836
A6: Feb | B6: 315 | C6: 315
A7: Grand Total | B7: 1151 | C7: 1151
A19: tootal quantity soldd | B19: =GETPIVOTDATA("Quantity",$A$3) -> 1151

Sheet Egg Sales
A1: Timestamp | B1: Date | C1: Customer Name | D1: Unit Price(per crate) | E1: Quantity | F1: Amount Paid | G1: Payment Channel | H1: Month | I1: Total | J1: Total Pieces | K1: Check | L1: Amount Banked
A2: 46358.229 | B2: 46064 | C2: Martha Akuorkor | D2: 40 | E2: 4 | F2: 160 | H2: 46054 | I2: 160 | J2: 120 | K2: TRUE
A3: 46358.228 | B3: 46064 | C3: Martha Akuorkor | D3: 45 | E3: 6 | F3: 270 | H3: 46054 | I3: 270 | J3: 180 | K3: TRUE
A4: 46297.671 | B4: 46063 | C4: Mummy | D4: 50 | E4: 2 | F4: 100 | H4: 46054 | I4: 100 | J4: 60 | K4: TRUE
A5: 46297.564 | B5: 46063 | C5: Tei | D5: 45 | E5: 4 | F5: 180 | H5: 46054 | I5: 180 | J5: 120 | K5: TRUE
A6: 46297.551 | B6: 46063 | C6: Thasha | D6: 45 | E6: 3 | F6: 135 | H6: 46054 | I6: 135 | J6: 90 | K6: TRUE
A7: 46297.55 | B7: 46063 | C7: Mama Becky | D7: 45 | E7: 2 | F7: 90 | H7: 46054 | I7: 90 | J7: 60 | K7: TRUE
A8: 46297.55 | B8: 46063 | C8: Sis Maggie | D8: 45 | E8: 10 | F8: 450 | H8: 46054 | I8: 450 | J8: 300 | K8: TRUE
A9: 46297.55 | B9: 46063 | C9: Aberkuma North K | D9: 55 | E9: 20 | F9: 1100 | H9: 46054 | I9: 1100 | J9: 600 | K9: TRUE
A10: 46297.548 | B10: 46063 | C10: Aberkuma North K | D10: 50 | E10: 20 | F10: 1000 | H10: 46054 | I10: 1000 | J10: 600 | K10: TRUE
A11: 46267.394 | B11: 46062 | C11: Ice Block Woman | D11: 45 | E11: 3 | F11: 135 | H11: 46054 | I11: 135 | J11: 90 | K11: TRUE
A12: 46267.393 | B12: 46062 | C12: Amelia Kotoku | D12: 50 | E12: 4 | F12: 200 | H12: 46054 | I12: 200 | J12: 120 | K12: TRUE | L12: 15360
A13: 46267.607 | B13: 46061 | C13: Rev Class Peters | D13: 65 | E13: 4 | F13: 260 | H13: 46054 | I13: 260 | J13: 120 | K13: TRUE
A14: 46267.393 | B14: 46061 | C14: Aberkuma North K | D14: 55 | E14: 10 | F14: 550 | H14: 46054 | I14: 550 | J14: 300 | K14: TRUE
A15: 46267.393 | B15: 46061 | C15: Aberkuma North K | D15: 60 | E15: 10 | F15: 600 | H15: 46054 | I15: 600 | J15: 300 | K15: TRUE
A16: 46267.388 | B16: 46061 | C16: Lady Tantra Hill | D16: 50 | E16: 10 | F16: 500 | H16: 46054 | I16: 500 | J16: 300 | K16: TRUE
A17: 46267.386 | B17: 46061 | C17: Moda | D17: 45 | E17: 3 | F17: 135 | H17: 46054 | I17: 135 | J17: 90 | K17: TRUE
A18: 46267.382 | B18: 46061 | C18: Moda's Tenant | D18: 40 | E18: 4 | F18: 160 | H18: 46054 | I18: 160 | J18: 120 | K18: TRUE
A19: 46267.381 | B19: 46061 | C19: Lady | D19: 40 | E19: 2 | F19: 80 | H19: 46054 | I19: 80 | J19: 60 | K19: TRUE
A20: 46267.381 | B20: 46061 | C20: Amelia Adabraka | D20: 55 | E20: 10 | F20: 550 | H20: 46054 | I20: 550 | J20: 300 | K20: TRUE
A21: 46236.345 | B21: 46061 | C21: Wele House | D21: 50 | E21: 10 | F21: 500 | H21: 46054 | I21: 500 | J21: 300 | K21: TRUE
A22: 46205.772 | B22: 46060 | C22: Vanessa | D22: 45 | E22: 3 | F22: 135 | H22: 46054 | I22: 135 | J22: 90 | K22: TRUE
A23: 46205.277 | B23: 46059 | C23: Sis Maggie | D23: 45 | E23: 7 | F23: 315 | H23: 46054 | I23: 315 | J23: 210 | K23: TRUE
A24: 46205.269 | B24: 46059 | C24: Bro DK | D24: 65 | E24: 2 | F24: 130 | H24: 46054 | I24: 130 | J24: 60 | K24: TRUE
... A37: 46055.737 | B37: 46055 | C37: Ice block Woman | D37: 45 | E37: 2 | F37: 90 | H37: 46054 | I37: 90 | J37: 60 | K37: TRUE
A38: 46054.769 | B38: 46054 | C38: Bro Kofi | D38: 50 | E38: 4 | F38: 200 | H38: =TEXT(B38, "MMMM YYYY") -> February 2026 | I38: =D38*E38 -> 200 | J38: =E38*30 -> 120 | K38: =IF(F38=I38,TRUE) -> TRUE
A39: 46055.322 | B39: 46054 | C39: Martha Akuokor | D39: 40 | E39: 4 | F39: 160 | H39: =TEXT(B39, "MMMM YYYY") -> February 2026 | I39: =D39*E39 -> 160 | J39: =E39*30 -> 120 | K39: =IF(F39=I39,TRUE) -> TRUE
A40: 46055.331 | B40: 46054 | C40: Martha Akuokor | D40: 45 | E40: 7 | F40: 315 | H40: =TEXT(B40, "MMMM YYYY") -> February 2026 | I40: =D40*E40 -> 315 | J40: =E40*30 -> 210 | K40: =IF(F40=I40,TRUE) -> TRUE
A41: 46054.455 | B41: 46053 | C41: Vanessa | D41: 50 | E41: 1 | F41: 50 | H41: =TEXT(B41, "MMMM YYYY") -> January 2026 | I41: =D41*E41 -> 50 | J41: =E41*30 -> 30 | K41: =IF(F41=I41,TRUE) -> TRUE
A42: 46054.042 | B42: 46053 | C42: Martha Akuokor | D42: 40 | E42: 3 | F42: 120 | H42: =TEXT(B42, "MMMM YYYY") -> January 2026 | I42: =D42*E42 -> 120 | J42: =E42*30 -> 90 | K42: =IF(F42=I42,TRUE) -> TRUE
A43: 46054.768 | B43: 46053 | C43: Phyllis Amartey | D43: 45 | E43: 10 | F43: 450 | H43: =TEXT(B43, "MMMM YYYY") -> January 2026 | I43: =D43*E43 -> 450 | J43: =E43*30 -> 300 | K43: =IF(F43=I43,TRUE) -> TRUE
A44: 46054.768 | B44: 46053 | C44: Ant Gina | D44: 60 | E44: 2 | F44: 120 | H44: =TEXT(B44, "MMMM YYYY") -> January 2026 | I44: =D44*E44 -> 120 | J44: =E44*30 -> 60 | K44: =IF(F44=I44,TRUE) -> TRUE
A45: 46052.763 | B45: 46052 | C45: Maa J | D45: 65 | E45: 2 | F45: 130 | H45: =TEXT(B45, "MMMM YYYY") -> January 2026 | I45: =D45*E45 -> 130 | J45: =E45*30 -> 60 | K45: =IF(F45=I45,TRUE) -> TRUE
A46: 46052.762 | B46: 46052 | C46: Bubiashie indomie | D46: 50 | E46: 20 | F46: 1000 | H46: =TEXT(B46, "MMMM YYYY") -> January 2026 | I46: =D46*E46 -> 1000 | J46: =E46*30 -> 600 | K46: =IF(F46=I46,TRUE) -> TRUE
A47: 46052.762 | B47: 46052 | C47: Bubiashie Kenkey | D47: 55 | E47: 20 | F47: 1100 | H47: =TEXT(B47, "MMMM YYYY") -> January 2026 | I47: =D47*E47 -> 1100 | J47: =E47*30 -> 600 | K47: =IF(F47=I47,TRUE) -> TRUE
A48: 46052.329 | B48: 46052 | C48: Moses | D48: 40 | E48: 2 | F48: 80 | H48: =TEXT(B48, "MMMM YYYY") -> January 2026 | I48: =D48*E48 -> 80 | J48: =E48*30 -> 60 | K48: =IF(F48=I48,TRUE) -> TRUE
A49: 46051.01 | B49: 46050 | C49: Haajii Anye | D49: 45 | E49: 20 | F49: 900 | H49: =TEXT(B49, "MMMM YYYY") -> January 2026 | I49: =D49*E49 -> 900 | J49: =E49*30 -> 600 | K49: =IF(F49=I49,TRUE) -> TRUE | L49: 7655
A50: 46050.515 | B50: 46050 | C50: Martha Akuokor | D50: 40 | E50: 3 | F50: 120 | H50: =TEXT(B50, "MMMM YYYY") -> January 2026 | I50: =D50*E50 -> 120 | J50: =E50*30 -> 90 | K50: =IF(F50=I50,TRUE) -> TRUE
A51: 46050.513 | B51: 46050 | C51: Deborah Kotoku | D51: 50 | E51: 2 | F51: 100 | H51: =TEXT(B51, "MMMM YYYY") -> January 2026 | I51: =D51*E51 -> 100 | J51: =E51*30 -> 60 | K51: =IF(F51=I51,TRUE) -> TRUE
A52: 46050.513 | B52: 46050 | C52: Deborah Kotoku | D52: 45 | E52: 5 | F52: 225 | H52: =TEXT(B52, "MMMM YYYY") -> January 2026 | I52: =D52*E52 -> 225 | J52: =E52*30 -> 150 | K52: =IF(F52=I52,TRUE) -> TRUE
A53: 46050.512 | B53: 46050 | C53: Afriyie Agric | D53: 50 | E53: 10 | F53: 500 | H53: =TEXT(B53, "MMMM YYYY") -> January 2026 | I53: =D53*E53 -> 500 | J53: =E53*30 -> 300 | K53: =IF(F53=I53,TRUE) -> TRUE
A54: 46050.512 | B54: 46050 | C54: Afriyie Agric | D54: 45 | E54: 10 | F54: 450 | H54: =TEXT(B54, "MMMM YYYY") -> January 2026 | I54: =D54*E54 -> 450 | J54: =E54*30 -> 300 | K54: =IF(F54=I54,TRUE) -> TRUE
A55: 46050.511 | B55: 46050 | C55: Vanessa | D55: 45 | E55: 4 | F55: 180 | H55: =TEXT(B55, "MMMM YYYY") -> January 2026 | I55: =D55*E55 -> 180 | J55: =E55*30 -> 120 | K55: =IF(F55=I55,TRUE) -> TRUE
A56: 46049.767 | B56: 46049 | C56: Bro Dk | D56: 65 | E56: 2 | F56: 130 | H56: =TEXT(B56, "MMMM YYYY") -> January 2026 | I56: =D56*E56 -> 130 | J56: =E56*30 -> 60 | K56: =IF(F56=I56,TRUE) -> TRUE
A57: 46049.766 | B57: 46049 | C57: Joyce Annan | D57: 50 | E57: 20 | F57: 1000 | H57: =TEXT(B57, "MMMM YYYY") -> January 2026 | I57: =D57*E57 -> 1000 | J57: =E57*30 -> 600 | K57: =IF(F57=I57,TRUE) -> TRUE
A58: 46050.471 | B58: 46049 | C58: Sis Maggie | D58: 45 | E58: 3 | F58: 135 | H58: =TEXT(B58, "MMMM YYYY") -> January 2026 | I58: =D58*E58 -> 135 | J58: =E58*30 -> 90 | K58: =IF(F58=I58,TRUE) -> TRUE
A59: 46049.319 | B59: 46048 | C59: Bubiashie | D59: 45 | E59: 2 | F59: 90 | H59: =TEXT(B59, "MMMM YYYY") -> January 2026 | I59: =D59*E59 -> 90 | J59: =E59*30 -> 60 | K59: =IF(F59=I59,TRUE) -> TRUE
A60: 46049.316 | B60: 46048 | C60: Bubiashie | D60: 55 | E60: 20 | F60: 1100 | H60: =TEXT(B60, "MMMM YYYY") -> January 2026 | I60: =D60*E60 -> 1100 | J60: =E60*30 -> 600 | K60: =IF(F60=I60,TRUE) -> TRUE
A61: 46048.064 | B61: 46047 | C61: Aberkuma North K | D61: 55 | E61: 10 | F61: 550 | H61: =TEXT(B61, "MMMM YYYY") -> January 2026 | I61: =D61*E61 -> 550 | J61: =E61*30 -> 300 | K61: =IF(F61=I61,TRUE) -> TRUE
... A73: 46046.45 | B73: 46045 | C73: Ice block woman | D73: 50 | E73: 2 | F73: 100 | H73: =TEXT(B73, "MMMM YYYY") -> January 2026 | I73: =D73*E73 -> 100 | J73: =E73*30 -> 60 | K73: =IF(F73=I73,TRUE) -> TRUE
A74: 46045.517 | B74: 46044 | C74: Vanessa | D74: 45 | E74: 1 | F74: 45 | H74: =TEXT(B74, "MMMM YYYY") -> January 2026 | I74: =D74*E74 -> 45 | J74: =E74*30 -> 30 | K74: =IF(F74=I74,TRUE) -> TRUE | L74: 3920
A75: 46044.671 | B75: 46044 | C75: Efya Bortey | D75: 50 | E75: 10 | F75: 500 | H75: =TEXT(B75, "MMMM YYYY") -> January 2026 | I75: =D75*E75 -> 500 | J75: =E75*30 -> 300 | K75: =IF(F75=I75,TRUE) -> TRUE
A76: 46044.67 | B76: 46044 | C76: Bro DK | D76: 65 | E76: 3 | F76: 195 | H76: =TEXT(B76, "MMMM YYYY") -> January 2026 | I76: =D76*E76 -> 195 | J76: =E76*30 -> 90 | K76: =IF(F76=I76,TRUE) -> TRUE
A77: 46044.571 | B77: 46044 | C77: Bubiashie | D77: 45 | E77: 20 | F77: 900 | H77: =TEXT(B77, "MMMM YYYY") -> January 2026 | I77: =D77*E77 -> 900 | J77: =E77*30 -> 600 | K77: =IF(F77=I77,TRUE) -> TRUE
A78: 46044.571 | B78: 46044 | C78: Bubiashie | D78: 50 | E78: 20 | F78: 1000 | H78: =TEXT(B78, "MMMM YYYY") -> January 2026 | I78: =D78*E78 -> 1000 | J78: =E78*30 -> 600 | K78: =IF(F78=I78,TRUE) -> TRUE
A79: 46044.57 | B79: 46044 | C79: Aberkuma North K | D79: 55 | E79: 10 | F79: 550 | H79: =TEXT(B79, "MMMM YYYY") -> January 2026 | I79: =D79*E79 -> 550 | J79: =E79*30 -> 300 | K79: =IF(F79=I79,TRUE) -> TRUE
A80: 46044.669 | B80: 46043 | C80: Bubiashie | D80: 55 | E80: 10 | F80: 550 | H80: =TEXT(B80, "MMMM YYYY") -> January 2026 | I80: =D80*E80 -> 550 | J80: =E80*30 -> 300 | K80: =IF(F80=I80,TRUE) -> TRUE
A81: 46043.325 | B81: 46042 | C81: Deborah Kotoku | D81: 45 | E81: 4 | F81: 180 | H81: =TEXT(B81, "MMMM YYYY") -> January 2026 | I81: =D81*E81 -> 180 | J81: =E81*30 -> 120 | K81: =IF(F81=I81,TRUE) -> TRUE
A82: 46042.7 | B82: 46042 | C82: Aberkuma North K | D82: 60 | E82: 10 | F82: 600 | H82: =TEXT(B82, "MMMM YYYY") -> January 2026 | I82: =D82*E82 -> 600 | J82: =E82*30 -> 300 | K82: =IF(F82=I82,TRUE) -> TRUE
A83: 46042.7 | B83: 46042 | C83: Aberkuma North K | D83: 55 | E83: 30 | F83: 1650 | H83: =TEXT(B83, "MMMM YYYY") -> January 2026 | I83: =D83*E83 -> 1650 | J83: =E83*30 -> 900 | K83: =IF(F83=I83,TRUE) -> TRUE
A84: 46042.699 | B84: 46042 | C84: Aberkuma North K | D84: 50 | E84: 10 | F84: 500 | H84: =TEXT(B84, "MMMM YYYY") -> January 2026 | I84: =D84*E84 -> 500 | J84: =E84*30 -> 300 | K84: =IF(F84=I84,TRUE) -> TRUE
A85: 46042.699 | B85: 46042 | C85: Bubiashie | D85: 50 | E85: 20 | F85: 1000 | H85: =TEXT(B85, "MMMM YYYY") -> January 2026 | I85: =D85*E85 -> 1000 | J85: =E85*30 -> 600 | K85: =IF(F85=I85,TRUE) -> TRUE | L85: 11605
A86: 46042.31 | B86: 46041 | C86: Martha Akuokor | D86: 40 | E86: 2 | F86: 80 | H86: =TEXT(B86, "MMMM YYYY") -> January 2026 | I86: =D86*E86 -> 80 | J86: =E86*30 -> 60 | K86: =IF(F86=I86,TRUE) -> TRUE
A87: 46042.296 | B87: 46041 | C87: Bubiashie - Percy | D87: 50 | E87: 10 | F87: 500 | H87: =TEXT(B87, "MMMM YYYY") -> January 2026 | I87: =D87*E87 -> 500 | J87: =E87*30 -> 300 | K87: =IF(F87=I87,TRUE) -> TRUE
A88: 46042.296 | B88: 46041 | C88: Bubiashie Kenkey | D88: 55 | E88: 5 | F88: 275 | H88: =TEXT(B88, "MMMM YYYY") -> January 2026 | I88: =D88*E88 -> 275 | J88: =E88*30 -> 150 | K88: =IF(F88=I88,TRUE) -> TRUE
A89: 46040.738 | B89: 46040 | C89: Vero Wele House | D89: 50 | E89: 5 | F89: 250 | H89: =TEXT(B89, "MMMM YYYY") -> January 2026 | I89: =D89*E89 -> 250 | J89: =E89*30 -> 150 | K89: =IF(F89=I89,TRUE) -> TRUE
A90: 46040.738 | B90: 46040 | C90: Vero Wele House | D90: 45 | E90: 10 | F90: 450 | H90: =TEXT(B90, "MMMM YYYY") -> January 2026 | I90: =D90*E90 -> 450 | J90: =E90*30 -> 300 | K90: =IF(F90=I90,TRUE) -> TRUE
A91: 46040.738 | B91: 46040 | C91: Wele House | D91: 50 | E91: 6 | F91: 300 | H91: =TEXT(B91, "MMMM YYYY") -> January 2026 | I91: =D91*E91 -> 300 | J91: =E91*30 -> 180 | K91: =IF(F91=I91,TRUE) -> TRUE
A92: 46040.737 | B92: 46040 | C92: Lady Tantra Hill | D92: 50 | E92: 5 | F92: 250 | H92: =TEXT(B92, "MMMM YYYY") -> January 2026 | I92: =D92*E92 -> 250 | J92: =E92*30 -> 150 | K92: =IF(F92=I92,TRUE) -> TRUE
A93: 46040.736 | B93: 46040 | C93: Amelia Adabraka | D93: 50 | E93: 10 | F93: 500 | H93: =TEXT(B93, "MMMM YYYY") -> January 2026 | I93: =D93*E93 -> 500 | J93: =E93*30 -> 300 | K93: =IF(F93=I93,TRUE) -> TRUE
A94: 46040.732 | B94: 46040 | C94: Maa j | D94: 55 | E94: 1 | F94: 55 | H94: =TEXT(B94, "MMMM YYYY") -> January 2026 | I94: =D94*E94 -> 55 | J94: =E94*30 -> 30 | K94: =IF(F94=I94,TRUE) -> TRUE
A95: 46040.731 | B95: 46040 | C95: Christiana Attafuah | D95: 50 | E95: 3 | F95: 150 | H95: =TEXT(B95, "MMMM YYYY") -> January 2026 | I95: =D95*E95 -> 150 | J95: =E95*30 -> 90 | K95: =IF(F95=I95,TRUE) -> TRUE
A96: 46040.731 | B96: 46040 | C96: Mummy | D96: 40 | E96: 2 | F96: 80 | H96: =TEXT(B96, "MMMM YYYY") -> January 2026 | I96: =D96*E96 -> 80 | J96: =E96*30 -> 60 | K96: =IF(F96=I96,TRUE) -> TRUE
A97: 46040.736 | B97: 46040 | C97: Sis Maggie | D97: 45 | E97: 10 | F97: 450 | H97: =TEXT(B97, "MMMM YYYY") -> January 2026 | I97: =D97*E97 -> 450 | J97: =E97*30 -> 300 | K97: =IF(F97=I97,TRUE) -> TRUE
... A126: 46032.163 | B126: 46031 | C126: Ken | D126: 45 | E126: 2 | F126: 90 | H126: =TEXT(B126, "MMMM YYYY") -> January 2026 | I126: =D126*E126 -> 90 | J126: =E126*30 -> 60 | K126: =IF(F126=I126,TRUE) -> TRUE
A127: 46031.156 | B127: 46031 | C127: Joseph | D127: 55 | E127: 1 | F127: 55 | H127: =TEXT(B127, "MMMM YYYY") -> January 2026 | I127: =D127*E127 -> 55 | J127: =E127*30 -> 30 | K127: =IF(F127=I127,TRUE) -> TRUE | L127: 6640
A128: 46031.133 | B128: 46030 | C128: Thasha | D128: 40 | E128: 5 | F128: 200 | H128: =TEXT(B128, "MMMM YYYY") -> January 2026 | I128: =D128*E128 -> 200 | J128: =E128*30 -> 150 | K128: =IF(F128=I128,TRUE) -> TRUE
A129: 46031.133 | B129: 46030 | C129: Ant Lydia | D129: 50 | E129: 10 | F129: 500 | H129: =TEXT(B129, "MMMM YYYY") -> January 2026 | I129: =D129*E129 -> 500 | J129: =E129*30 -> 300 | K129: =IF(F129=I129,TRUE) -> TRUE
A130: 46031.132 | B130: 46030 | C130: Ice block woman | D130: 40 | E130: 3 | F130: 120 | H130: =TEXT(B130, "MMMM YYYY") -> January 2026 | I130: =D130*E130 -> 120 | J130: =E130*30 -> 90 | K130: =IF(F130=I130,TRUE) -> TRUE
A131: 46031.132 | B131: 46030 | C131: Deborah Kotoku | D131: 45 | E131: 6 | F131: 270 | H131: =TEXT(B131, "MMMM YYYY") -> January 2026 | I131: =D131*E131 -> 270 | J131: =E131*30 -> 180 | K131: =IF(F131=I131,TRUE) -> TRUE
A132: 46031.131 | B132: 46030 | C132: Kojo | D132: 55 | E132: 1 | F132: 55 | H132: =TEXT(B132, "MMMM YYYY") -> January 2026 | I132: =D132*E132 -> 55 | J132: =E132*30 -> 30 | K132: =IF(F132=I132,TRUE) -> TRUE
A133: 46031.131 | B133: 46030 | C133: Judith | D133: 45 | E133: 2 | F133: 90 | H133: =TEXT(B133, "MMMM YYYY") -> January 2026 | I133: =D133*E133 -> 90 | J133: =E133*30 -> 60 | K133: =IF(F133=I133,TRUE) -> TRUE
A134: 46031.131 | B134: 46030 | C134: Christiana Kotoku | D134: 40 | E134: 5 | F134: 200 | H134: =TEXT(B134, "MMMM YYYY") -> January 2026 | I134: =D134*E134 -> 200 | J134: =E134*30 -> 150 | K134: =IF(F134=I134,TRUE) -> TRUE
A135: 46030.654 | B135: 46030 | C135: Maa J | D135: 65 | E135: 4 | F135: 260 | H135: =TEXT(B135, "MMMM YYYY") -> January 2026 | I135: =D135*E135 -> 260 | J135: =E135*30 -> 120 | K135: =IF(F135=I135,TRUE) -> TRUE
A136: 46030.653 | B136: 46030 | C136: Grandma Mother | D136: 45 | E136: 2 | F136: 90 | H136: =TEXT(B136, "MMMM YYYY") -> January 2026 | I136: =D136*E136 -> 90 | J136: =E136*30 -> 60 | K136: =IF(F136=I136,TRUE) -> TRUE
A137: 46029.516 | B137: 46029 | C137: Osabu | D137: 45 | E137: 10 | F137: 450 | H137: =TEXT(B137, "MMMM YYYY") -> January 2026 | I137: =D137*E137 -> 450 | J137: =E137*30 -> 300 | K137: =IF(F137=I137,TRUE) -> TRUE
A138: 46029.511 | B138: 46028 | C138: Bro DK | D138: 60 | E138: 5 | F138: 300 | H138: =TEXT(B138, "MMMM YYYY") -> January 2026 | I138: =D138*E138 -> 300 | J138: =E138*30 -> 150 | K138: =IF(F138=I138,TRUE) -> TRUE
A139: 46029.119 | B139: 46028 | C139: Thasha | D139: 40 | E139: 5 | F139: 200 | H139: =TEXT(B139, "MMMM YYYY") -> January 2026 | I139: =D139*E139 -> 200 | J139: =E139*30 -> 150 | K139: =IF(F139=I139,TRUE) -> TRUE
... A141: 46029.117 | B141: 46028 | C141: Christiana Attafuah | D141: 50 | E141: 2 | F141: 100 | H141: =TEXT(B141, "MMMM YYYY") -> January 2026 | I141: =D141*E141 -> 100 | J141: =E141*30 -> 60 | K141: =IF(F141=I141,TRUE) -> TRUE
A142: 46028.438 | B142: 46028 | C142: Aberkuma North K | D142: 55 | E142: 20 | F142: 1100 | H142: =TEXT(B142, "MMMM YYYY") -> January 2026 | I142: =D142*E142 -> 1100 | J142: =E142*30 -> 600 | K142: =IF(F142=I142,TRUE) -> TRUE | L142: 6495
A143: 46028.435 | B143: 46028 | C143: Aberkuma North K | D143: 50 | E143: 20 | F143: 1000 | H143: =TEXT(B143, "MMMM YYYY") -> January 2026 | I143: =D143*E143 -> 1000 | J143: =E143*30 -> 600 | K143: =IF(F143=I143,TRUE) -> TRUE
A144: 46028.426 | B144: 46028 | C144: Tei | D144: 45 | E144: 10 | F144: 450 | H144: =TEXT(B144, "MMMM YYYY") -> January 2026 | I144: =D144*E144 -> 450 | J144: =E144*30 -> 300 | K144: =IF(F144=I144,TRUE) -> TRUE
A145: 46028.434 | B145: 46028 | C145: Sis Maggie | D145: 45 | E145: 5 | F145: 225 | H145: =TEXT(B145, "MMMM YYYY") -> January 2026 | I145: =D145*E145 -> 225 | J145: =E145*30 -> 150 | K145: =IF(F145=I145,TRUE) -> TRUE
A146: 46028.434 | B146: 46028 | C146: Sis Maggie | D146: 40 | E146: 5 | F146: 200 | H146: =TEXT(B146, "MMMM YYYY") -> January 2026 | I146: =D146*E146 -> 200 | J146: =E146*30 -> 150 | K146: =IF(F146=I146,TRUE) -> TRUE
A147: 46028.405 | B147: 46027 | C147: Carpenter | D147: 50 | E147: 8 | F147: 400 | H147: =TEXT(B147, "MMMM YYYY") -> January 2026 | I147: =D147*E147 -> 400 | J147: =E147*30 -> 240 | K147: =IF(F147=I147,TRUE) -> TRUE
A148: 46028.405 | B148: 46027 | C148: Osabu | D148: 50 | E148: 3 | F148: 150 | H148: =TEXT(B148, "MMMM YYYY") -> January 2026 | I148: =D148*E148 -> 150 | J148: =E148*30 -> 90 | K148: =IF(F148=I148,TRUE) -> TRUE
A149: 46028.402 | B149: 46027 | C149: Ice Block Woman | D149: 50 | E149: 4 | F149: 200 | H149: =TEXT(B149, "MMMM YYYY") -> January 2026 | I149: =D149*E149 -> 200 | J149: =E149*30 -> 120 | K149: =IF(F149=I149,TRUE) -> TRUE
A150: 46027.266 | B150: 46026 | C150: Moda | D150: 60 | E150: 2 | F150: 120 | H150: =TEXT(B150, "MMMM YYYY") -> January 2026 | I150: =D150*E150 -> 120 | J150: =E150*30 -> 60 | K150: =IF(F150=I150,TRUE) -> TRUE
A151: 46027.264 | B151: 46026 | C151: Joyce Annan | D151: 50 | E151: 10 | F151: 500 | H151: =TEXT(B151, "MMMM YYYY") -> January 2026 | I151: =D151*E151 -> 500 | J151: =E151*30 -> 300 | K151: =IF(F151=I151,TRUE) -> TRUE
A152: 46027.264 | B152: 46026 | C152: Joyce Annan | D152: 45 | E152: 30 | F152: 1350 | H152: =TEXT(B152, "MMMM YYYY") -> January 2026 | I152: =D152*E152 -> 1350 | J152: =E152*30 -> 900 | K152: =IF(F152=I152,TRUE) -> TRUE
...

Sheet Dec 2025 Sales
A1: Timestamp | B1: Sales Date | C1: Customer name | D1: Product type | E1: Quantity | F1: Unit Price | G1: Payment Method | H1: Delivery Method | I1: Total | J1: Column 1
A2: 46038.613 | B2: 46022 | C2: Farmer | D2: Layer | E2: 15 | F2: 60 | G2: Cash | H2: Pick up | I2: =E2*F2 -> 900 | J2: TEI | L2: TEI | M2: =SUMIF(J:J,L2,I:I) -> 46520
A3: 46038.613 | B3: 46022 | C3: Farmer | D3: Layer | E3: 10 | F3: 50 | G3: Cash | H3: Pick up | I3: =E3*F3 -> 500 | J3: TEI | L3: PERCY | M3: =SUMIF(J:J,L3,I:I) -> 16300
A4: 46026.753 | B4: 46022 | C4: Farmer @Kotoku | D4: Layer | E4: 20 | F4: 60 | G4: Cash | H4: Delivery | I4: =E4*F4 -> 1200 | J4: TEI | L4: ENT | M4: =SUMIF(J:J,L4,I:I) -> 11310
A5: 46026.754 | B5: 46022 | C5: Farmer @Kotoku | D5: Layer | E5: 10 | F5: 45 | G5: Cash | H5: Delivery | I5: =E5*F5 -> 450 | J5: TEI | M5: =M2+M3+M4 -> 74130
A6: 46024.507 | B6: 46022 | C6: Auntie Doris | D6: Broiler | E6: 2 | F6: 250 | G6: Cash | H6: Delivery | I6: =E6*F6 -> 500 | J6: TEI
A7: 46024.507 | B7: 46022 | C7: Auntie Evelyn | D7: Broiler | E7: 2 | F7: 250 | G7: Cash | H7: Delivery | I7: =E7*F7 -> 500 | J7: TEI
A8: 46024.508 | B8: 46022 | C8: Bro John | D8: Broiler | E8: 1 | F8: 250 | G8: Cash | H8: Delivery | I8: =E8*F8 -> 250 | J8: TEI
A9: 46024.508 | B9: 46022 | C9: Christiana Attafuah | D9: Broiler | E9: 2 | F9: 250 | G9: Cash | H9: Delivery | I9: =E9*F9 -> 500 | J9: TEI
A10: 46024.509 | B10: 46022 | C10: Grandma moda | D10: Broiler | E10: 1 | F10: 250 | G10: Cash | H10: Delivery | I10: =E10*F10 -> 250 | J10: TEI
A11: 46024.508 | B11: 46022 | C11: Mercy | D11: Broiler | E11: 1 | F11: 250 | G11: Cash | H11: Delivery | I11: =E11*F11 -> 250 | J11: TEI
A12: 46024.507 | B12: 46022 | C12: Rev Elliot | D12: Broiler | E12: 2 | F12: 250 | G12: Cash | H12: Delivery | I12: =E12*F12 -> 500 | J12: TEI
A13: 46015.362 | B13: 46022 | C13: Mama lit | D13: Layer | E13: 2 | F13: 100 | G13: Cash | H13: Delivery | I13: =E13*F13 -> 200 | J13: PERCY
A14: 46015.362 | B14: 46022 | C14: Mama lit | D14: Broiler | E14: 4 | F14: 250 | G14: Cash | H14: Delivery | I14: =E14*F14 -> 1000 | J14: PERCY
A15: 46015.362 | B15: 46022 | C15: Percy | D15: Broiler | E15: 6 | F15: 250 | G15: Cash | H15: Delivery | I15: =E15*F15 -> 1500 | J15: PERCY
A16: 46018.197 | B16: 46017 | C16: Bro Atta | D16: Broiler | E16: 1 | F16: 250 | G16: Cash | H16: Delivery | I16: =E16*F16 -> 250 | J16: TEI
A17: 46018.196 | B17: 46017 | C17: Joe | D17: Broiler | E17: 2 | F17: 200 | G17: Cash | H17: Delivery | I17: =E17*F17 -> 400 | J17: TEI
... A94: 46046.457 | B94: 46022 | C94: Naa Amerley | D94: Layer | E94: 10 | F94: 60 | G94: Cash | H94: Delivery | I94: =E94*F94 -> 600 | J94: PERCY
A98: Total | I98: =SUM(Form_Responses2[Total]) -> 74130

Sheet Form responses 11
A1: Timestamp | B1: Sales Date | C1: Customer name | D1: Product type | E1: Quantity | F1: Unit Price | G1: Delivery Method | H1: Payment Method
A2: 45743.104 | B2: 45742 | C2: Maa j | E2: 1 | F2: 220 | G2: Delivery
A3: 45743.104 | B3: 45742 | C3: Mummy | E3: 1 | F3: 220 | G3: Pick up
A4: 45744.734 | B4: 45744 | C4: Genevieve korle bu | E4: 3 | F4: 220 | G4: Delivery
A5: 45745.435 | B5: 45745 | C5: Prince CBG | E5: 4 | F5: 250 | G5: Delivery
A6: 45748.201 | B6: 45748 | C6: Mummy | E6: 2 | F6: 200 | G6: Delivery
A7: 45748.626 | B7: 45748 | C7: Naa Dedei | E7: 1 | F7: 220 | G7: Delivery
A8: 45748.627 | B8: 45748 | C8: Maame Dede | E8: 2 | F8: 220 | G8: Delivery
A9: 45749.923 | B9: 45749 | C9: Benedicta | E9: 5 | F9: 250 | G9: Delivery
A10: 45750.388 | B10: 45750 | C10: Bro Kofi | E10: 2 | F10: 220 | G10: Delivery
A11: 45753.556 | B11: 45753 | C11: Emefa Onyinase | E11: 1 | F11: 220 | G11: Delivery | H11: Mobile
A12: 45753.644 | B12: 45753 | C12: Fiifi sage | E12: 2 | F12: 250 | G12: Delivery | H12: Cash
A13: 45758.598 | B13: 45758 | C13: Agege old lady | E13: 2 | F13: 220 | G13: Delivery | H13: Cash
A14: 45760.755 | B14: 45760 | C14: Sister | E14: 1 | F14: 220 | G14: Delivery | H14: Cash
A15: 45760.755 | B15: 45760 | C15: Tina (Sister) | E15: 4 | F15: 220 | G15: Delivery | H15: Cash
A16: 45761.732 | B16: 45761 | C16: Mummy | E16: 2 | F16: 100 | G16: Pick up | H16: Cash
A17: 45762.316 | B17: 45761 | C17: Sis Adoley | E17: 1 | F17: 200 | G17: Pick up | H17: Cash
A18: 45762.434 | B18: 45762 | C18: Moda | E18: 1 | F18: 220 | G18: Delivery
A19: 45762.52 | B19: 45762 | C19: Ben - Maa J | E19: 3 | F19: 250 | G19: Delivery | H19: Cash
A20: 45763.864 | B20: 45763 | C20: Lady’s Boss | E20: 1 | F20: 220 | G20: Delivery | H20: Cash
A21: 45764.682 | B21: 45764 | C21: Ant Vivian - Sister - Dansoman | E21: 2 | F21: 220 | G21: Delivery | H21: Cash
A22: 45765.148 | B22: 45764 | C22: Rev Class Peters | E22: 1 | F22: 220 | G22: Delivery | H22: Cash
A23: 45765.468 | B23: 45765 | C23: Sinclair | E23: 5 | F23: 220 | G23: Delivery | H23: Mobile
A24: 45765.47 | B24: 45765 | C24: Ant Joyce - Sister Labone | E24: 1 | F24: 220 | G24: Delivery | H24: Cash
A25: 45765.668 | B25: 45764 | C25: Chorkor | E25: 3 | F25: 220 | G25: Delivery | H25: Cash
A26: 45765.668 | B26: 45765 | C26: Patience Spintex | E26: 3 | F26: 220 | G26: Delivery | H26: Cash
A27: 45765.678 | B27: 45765 | C27: Marilyn | E27: 2 | F27: 220 | G27: Delivery | H27: Cash
A28: 45767.578 | B28: 45767 | C28: Belinda | E28: 1 | F28: 220 | G28: Delivery | H28: Cash
A29: 45767.73 | B29: 45767 | C29: Aakaa | E29: 4 | F29: 220 | G29: Delivery | H29: Cash
A30: 45768.328 | B30: 45768 | C30: Bro Atta | E30: 1 | F30: 220 | G30: Pick up | H30: Cash
... A46: 45798.325 | B46: 45797 | C46: Tei | E46: 1 | F46: 200 | G46: Pick up | H46: Cash

Sheet Copy of Mortality and Transfers
A1: Timestamp | B1: Record date | C1: Recorder Name/ID | D1: Were there any mortalities today? | E1: Where did mortality occur | F1: Pen/House/Flock ID (where mortality occurred) | G1: Number of Mortalities | H1: Age/Stage of Birds (at time of mortality) | I1: Enter Age(number) | J1: Suspected Cause(s) of Mortality | K1: Additional Notes on Mortality | L1: Was there any bird movement today? | M1: Type of Movement | N1: Number of Birds Moved | O1: Source Pen/Location ID (from where birds moved) | P1: Destination Pen/Location (to where birds moved) | Q1: Reason for Movement | R1: Additional Notes on Bird Movement
A2: 45798.801 | B2: 45798 | C2: PERCY | D2: Yes | E2: SET A | F2: B46 | G2: 1 | H2: MONTHS | I2: 15 | J2: UKN | K2: It had no fat in it which is good news but it’s too bony and no traits of food Above all it looked like intestines with feaces got burst cos the inner was filled with waste liquid | L2: No
A3: 45799.912 | B3: 45799 | C3: Tei | D3: Yes | E3: SET B | F3: B143 | G3: 1 | H3: WEEKS | I3: 21 | J3: Prolapse | K3: State of prolapse was bad so I had to slaughter it | L3: No
A4: 45801.912 | B4: 45801 | C4: Tei | D4: Yes | E4: SET C | F4: House | G4: 1 | H4: DAYS | I4: 7 | J4: Stampede | K4: Light out overnight | L4: No
A5: 45801.929 | B5: 45801 | C5: Tei | D5: Yes | E5: SET A | F5: B34 | G5: 1 | H5: MONTHS | I5: 15 | J5: Perking | K5: Anal Perking during laying | L5: No
A6: 45805.06 | B6: 45803 | C6: Tei | D6: Yes | E6: SET A | F6: B65 | G6: 1 | H6: MONTHS | I6: 15 | J6: Unknown | L6: No
A7: 45805.063 | B7: 45803 | C7: Tei | D7: Yes | E7: SET B | F7: Pen | G7: 1 | H7: MONTHS | I7: 5 | J7: Prolapse | K7: Administering detox | L7: No
A8: 45805.064 | B8: 45804 | C8: Tei | D8: Yes | E8: SET B | F8: Pen | G8: 1 | H8: MONTHS | I8: 5 | J8: Prolapse | K8: Administering detox | L8: No
A9: 45805.886 | B9: 45805 | C9: Tei | D9: Yes | E9: SET A | F9: B18 | G9: 1 | H9: MONTHS | I9: 15 | J9: Accident/Injury | K9: Its head got stuck overnight | L9: No
A10: 45807.204 | B10: 45806 | C10: Tei | D10: Yes | E10: SET A | F10: QT | G10: 2 | H10: MONTHS | I10: 15 | J10: Unknown | K10: They were weak and have been quarantined for 2 weeks but wasn’t able to recover | L10: No

Sheet Broiler Sales
A1: Timestamp | B1: Sales Date | C1: Customer name | D1: Quantity | E1: Unit Price | F1: Delivery Method | G1: Payment Method | H1: Product type | I1: Total | J1: Amount Banked | K1: Column 1
A2: 45798.325 | B2: 45797 | C2: Tei | D2: 1 | E2: 200 | F2: Pick up | G2: Cash | I2: =D2*E2 -> 200 | J2: 960 | K2: =20*D2 -> 20
A3: 45796.869 | B3: 45795 | C3: Elfreda Agege old lady | D3: 2 | E3: 200 | F3: Delivery | G3: Cash | I3: =D3*E3 -> 400 | K3: =20*D3 -> 40
A4: 45796.868 | B4: 45795 | C4: Bro Atta | D4: 1 | E4: 180 | F4: Pick up | G4: Cash | I4: =D4*E4 -> 180 | K4: =20*D4 -> 20
A5: 45796.867 | B5: 45795 | C5: Mummy | D5: 1 | E5: 180 | F5: Pick up | G5: Cash | I5: =D5*E5 -> 180 | K5: =20*D5 -> 20
A6: 45793.566 | B6: 45793 | C6: David Airport | D6: 3 | E6: 200 | F6: Delivery | G6: Cash | I6: =D6*E6 -> 600 | J6: 600 | K6: =20*D6 -> 60
A7: 45789.43 | B7: 45788 | C7: Naa Dedei | D7: 2 | E7: 180 | F7: Delivery | G7: Cash | I7: =D7*E7 -> 360 | J7: 360 | K7: =20*D7 -> 40
A8: 45784.809 | B8: 45784 | C8: Bro Kofi | D8: 1 | E8: 180 | F8: Pick up | G8: Cash | I8: =D8*E8 -> 180 | J8: =303+1597 -> 1900
A9: 45782.139 | B9: 45781 | C9: Mrs Opara | D9: 1 | E9: 200 | F9: Delivery | G9: Cash | I9: =D9*E9 -> 200 | K9: =20*D9 -> 20
A10: 45782.126 | B10: 45781 | C10: Moda’s Tenant Sapeiman | D10: 1 | E10: 200 | F10: Delivery | G10: Cash | I10: =D10*E10 -> 200 | K10: =20*D10 -> 20
A11: 45780.757 | B11: 45780 | C11: Mama Lee Kwabenya | D11: 1 | E11: 220 | F11: Delivery | G11: Cash | I11: =D11*E11 -> 220 | K11: =20*D11 -> 20
A12: 45777.615 | B12: 45777 | C12: Bro Kofi’s Friend | D12: 1 | E12: 220 | F12: Delivery | G12: Cash | I12: =D12*E12 -> 220 | K12: =20*D12 -> 20
A13: 45776.156 | B13: 45775 | C13: Prince Spintex | D13: 4 | E13: 220 | F13: Delivery | G13: Cash | I13: =D13*E13 -> 880 | K13: =20*D13 -> 80
A14: 45775.157 | B14: 45774 | C14: Moda | D14: 2 | E14: 220 | F14: Delivery | G14: Cash | I14: =D14*E14 -> 440 | J14: 1919 | K14: =20*D14 -> 40
A15: 45773.371 | B15: 45773 | C15: Ewurafua Domeabra | D15: 3 | E15: 220 | F15: Delivery | G15: Cash | I15: =D15*E15 -> 660 | K15: =20*D15 -> 60
A16: 45773.37 | B16: 45773 | C16: Bro Atta | D16: 1 | E16: 200 | F16: Pick up | G16: Cash | I16: =D16*E16 -> 200
A17: 45771.875 | B17: 45771 | C17: Maame Dede | D17: 2 | E17: 220 | F17: Delivery | G17: Cash | I17: =D17*E17 -> 440 | K17: =20*D17 -> 40
A18: 45768.328 | B18: 45768 | C18: Bro Atta | D18: 1 | E18: 220 | F18: Pick up | G18: Cash | I18: =D18*E18 -> 220 | J18: 4913
A19: 45767.73 | B19: 45767 | C19: Aakaa | D19: 4 | E19: 220 | F19: Delivery | G19: Cash | I19: =D19*E19 -> 880 | K19: =20*D19 -> 80
A20: 45767.578 | B20: 45767 | C20: Belinda | D20: 1 | E20: 220 | F20: Delivery | G20: Cash | I20: =D20*E20 -> 220 | K20: =20*D20 -> 20
A21: 45765.678 | B21: 45765 | C21: Marilyn | D21: 2 | E21: 220 | F21: Delivery | G21: Cash | I21: =D21*E21 -> 440 | K21: =20*D21 -> 40
A22: 45765.668 | B22: 45765 | C22: Patience Spintex | D22: 3 | E22: 220 | F22: Delivery | G22: Cash | I22: =D22*E22 -> 660 | J22: =60 -> 60 | K22: =20*D22 -> 60
A23: 45765.668 | B23: 45764 | C23: Chorkor | D23: 3 | E23: 220 | F23: Delivery | G23: Cash | I23: =D23*E23 -> 660 | J23: 660 | K23: =20*D23 -> 60
A24: 45765.47 | B24: 45765 | C24: Ant Joyce - Sister Labone | D24: 1 | E24: 220 | F24: Delivery | G24: Cash | I24: =D24*E24 -> 220 | K24: =20*D24 -> 20
A25: 45765.468 | B25: 45765 | C25: Sinclair | D25: 5 | E25: 220 | F25: Delivery | G25: Mobile | I25: =D25*E25 -> 1100 | K25: =20*D25 -> 100
A26: 45765.148 | B26: 45764 | C26: Rev Class Peters | D26: 1 | E26: 220 | F26: Delivery | G26: Cash | I26: =D26*E26 -> 220 | K26: =20*D26 -> 20
A27: 45764.682 | B27: 45764 | C27: Ant Vivian - Sister - Dansoman | D27: 2 | E27: 220 | F27: Delivery | G27: Cash | I27: =D27*E27 -> 440 | K27: =20*D27 -> 40
A28: 45763.864 | B28: 45763 | C28: Lady’s Boss | D28: 1 | E28: 220 | F28: Delivery | G28: Cash | I28: =D28*E28 -> 220 | K28: =20*D28 -> 20
A29: 45762.52 | B29: 45762 | C29: Ben - Maa J | D29: 3 | E29: 250 | F29: Delivery | G29: Cash | I29: =D29*E29 -> 750 | K29: =20*D29 -> 60
A30: 45762.434 | B30: 45762 | C30: Moda | D30: 1 | E30: 220 | F30: Delivery | G30: Cash | I30: =D30*E30 -> 220 | J30: 2378 | K30: =20*D30 -> 20
A31: 45762.316 | B31: 45761 | C31: Sis Adoley | D31: 1 | E31: 200 | F31: Pick up | G31: Cash | I31: =D31*E31 -> 200
A32: 45761.732 | B32: 45761 | C32: Mummy | D32: 2 | E32: 100 | F32: Pick up | G32: Cash | I32: =D32*E32 -> 200
A33: 45760.755 | B33: 45760 | C33: Tina (Sister) | D33: 4 | E33: 220 | F33: Delivery | G33: Cash | I33: =D33*E33 -> 880 | K33: =20*D33 -> 80
A34: 45760.755 | B34: 45760 | C34: Sister | D34: 1 | E34: 220 | F34: Delivery | G34: Cash | I34: =D34*E34 -> 220 | K34: =20*D34 -> 20
A35: 45758.598 | B35: 45758 | C35: Agege old lady | D35: 2 | E35: 220 | F35: Delivery | G35: Cash | I35: =D35*E35 -> 440 | K35: =20*D35 -> 40
A36: 45753.644 | B36: 45753 | C36: Fiifi sage | D36: 2 | E36: 250 | F36: Delivery | G36: Cash | I36: =D36*E36 -> 500 | J36: 4320 | K36: =20*D36 -> 40
A37: 45753.556 | B37: 45753 | C37: Emefa Onyinase | D37: 1 | E37: 220 | F37: Delivery | G37: Mobile | I37: =D37*E37 -> 220 | K37: =20*D37 -> 20
A38: 45750.388 | B38: 45750 | C38: Bro Kofi | D38: 2 | E38: 220 | F38: Delivery | G38: Cash | I38: =D38*E38 -> 440 | K38: =20*D38 -> 40
A39: 45749.923 | B39: 45749 | C39: Benedicta | D39: 5 | E39: 250 | F39: Delivery | G39: Bank | I39: =D39*E39 -> 1250 | J39: =I39 -> 1250 | K39: =20*D39 -> 100
A40: 45748.627 | B40: 45748 | C40: Maame Dede | D40: 2 | E40: 220 | F40: Delivery | G40: Cash | I40: =D40*E40 -> 440 | K40: =20*D40 -> 40
A41: 45748.626 | B41: 45748 | C41: Naa Dedei | D41: 1 | E41: 220 | F41: Delivery | G41: Cash | I41: =D41*E41 -> 220 | K41: =20*D41 -> 20
A42: 45748.201 | B42: 45748 | C42: Mummy | D42: 2 | E42: 200 | F42: Delivery | G42: Cash | I42: =D42*E42 -> 400 | K42: =20*D42 -> 40
A43: 45745.435 | B43: 45745 | C43: Prince CBG | D43: 4 | E43: 250 | F43: Delivery | G43: Cash | I43: =D43*E43 -> 1000 | K43: =20*D43 -> 80
A44: 45744.734 | B44: 45744 | C44: Genevieve korle bu | D44: 3 | E44: 220 | F44: Delivery | G44: Cash | I44: =D44*E44 -> 660 | K44: =20*D44 -> 60
A45: 45743.104 | B45: 45742 | C45: Mummy | D45: 1 | E45: 220 | F45: Pick up | G45: Cash | I45: =D45*E45 -> 220
A46: 45743.104 | B46: 45742 | C46: Maa j | D46: 1 | E46: 220 | F46: Delivery | G46: Cash | I46: =D46*E46 -> 220 | K46: =20*D46 -> 20

Sheet Broiler Orders
A1: Timestamp | B1: Order date | C1: Customer Name | D1: Quantity | E1: Delivery date | F1: Delivery Location | G1: Payment Status | H1: Chicken Type | I1: Customer contact | J1: Delivery Status | K1: Comments
A2: 46007.764 | B2: 46003 | C2: Grandma Mother | D2: 1 | E2: 46007 | F2: Opah | G2: On-Delivery | H2: Broiler | I2: 267269919 | J2: Pending
A3: 46015.548 | B3: 46015 | C3: Aakaa | D3: 2 | E3: 46015 | F3: Abeka | G3: On-Delivery | H3: Layer | I3: Tbd | J3: Delivered
A4: 46011.534 | B4: 46011 | C4: Lady | D4: 2 | E4: 46013 | F4: Lapaz | G4: On-Delivery | H4: Broiler | I4: 553134447 | J4: Pending
A5: 46008.276 | B5: 46008 | C5: Aakaa | D5: 8 | E5: 46014 | F5: Abeka | G5: Paid | H5: Broiler | I5: 269710510 | J5: Delivered
A6: 46010.22 | B6: 46010 | C6: Agege | D6: 6 | E6: 46010 | F6: Dansoman | G6: On-Delivery | H6: Layer | I6: 026 222 1212 | J6: Delivered
A7: 46008.281 | B7: 46008 | C7: Adwoa | D7: 1 | E7: 46010 | F7: Lapaz | G7: Paid | H7: Broiler | I7: 546918667 | J7: Delivered
A8: 46011.104 | B8: 46011 | C8: Afia Bortey | D8: 2 | E8: 46013 | F8: Pokuase | G8: On-Delivery | H8: Broiler | I8: 244449517 | J8: Delivered
A9: 46008.282 | B9: 46008 | C9: Augustina | D9: 1 | E9: 46010 | F9: Osu | G9: Paid | H9: Layer | I9: 268871851 | J9: Delivered
A10: 46010.217 | B10: 46010 | C10: Agege Dansoman/ Tei | D10: 2 | E10: 46010 | F10: Dansoman | G10: On-Delivery | H10: Broiler | I10: 262221212 | J10: Delivered
A11: 46008.607 | B11: 46008 | C11: Aunt Mabel | D11: 3 | E11: 46010 | F11: East Legon | G11: On-Delivery | H11: Layer | I11: ‪+1 (404) 388‑6448‬ | J11: Delivered
A12: 46007.77 | B12: 46003 | C12: Amin | D12: 15 | E12: 46010 | F12: Airport | G12: On-Delivery | H12: Broiler | I12: 541094876 | J12: Delivered | K12: 5 boxes
A13: 46008.281 | B13: 46008 | C13: Augustina | D13: 1 | E13: 46010 | F13: Osu | G13: Paid | H13: Broiler | I13: 268871851 | J13: Delivered
A14: 46008.607 | B14: 46008 | C14: Aunt Mabel | D14: 3 | E14: 46010 | F14: East Legon | G14: On-Delivery | H14: Broiler | I14: ‪+1(404)3886448‬ | J14: Delivered
A15: 46012.741 | B15: 46012 | C15: Auntie Doris | D15: 3 | E15: 46013 | F15: Pokuase | G15: Paid | H15: Broiler | I15: =233277773889 -> 233277773889 | J15: Delivered
A16: 46010.199 | B16: 46010 | C16: Auntie Gina | D16: 2 | E16: 46013 | F16: Ashongman | G16: On-Delivery | H16: Broiler | I16: 267269919 | J16: Delivered
C17: Auntie Evelyn | D17: 2 | H17: Broiler | J17: Delivered
C18: Naa Celebrity | D18: 1 | H18: Broiler | J18: Delivered
C19: Mercy | D19: 1 | H19: Broiler | J19: Delivered
C20: Bro John | D20: 1 | H20: Broiler | J20: Delivered
A21: 46007.771 | B21: 46003 | C21: Auntie Gina | D21: 1 | E21: 46010 | F21: Lapaz | G21: On-Delivery | H21: Broiler | I21: 267269919 | J21: Delivered
A22: 46011.104 | B22: 46011 | C22: Belinda Koranteng | D22: 5 | E22: 46013 | F22: Lapaz | G22: On-Delivery | H22: Broiler | I22: +233 54 333 3589 | J22: Delivered
A23: 46010.457 | B23: 46010 | C23: Bro Dk | D23: 2 | E23: 46014 | F23: Lapaz | G23: On-Delivery | H23: Layer | I23: 267269919 | J23: Delivered
A24: 46008.279 | B24: 46008 | C24: Bro Amos | D24: 2 | E24: 46014 | F24: Kotoku | G24: On-Delivery | H24: Broiler | I24: 243010450 | J24: Delivered
A25: 46010.2 | B25: 46010 | C25: Bro DK | D25: 2 | E25: 46014 | F25: Lapaz | G25: On-Delivery | H25: Layer | I25: 77744465 | J25: Delivered
A26: 46010.457 | B26: 46010 | C26: Bro Dk | D26: 4 | E26: 46014 | F26: Lapaz | G26: On-Delivery | H26: Broiler | I26: 267269919 | J26: Delivered
A27: 46008.28 | B27: 46008 | C27: Bro Dk | D27: 2 | E27: 46014 | F27: Lapaz | G27: On-Delivery | H27: Broiler | I27: 277338536 | J27: Delivered
A28: 46013.356 | B28: 46010 | C28: Bro kofi | D28: 2 | E28: 46011 | F28: Kotoku | G28: Paid | H28: Broiler | I28: Tbd | J28: Delivered
A29: 46009.529 | B29: 46009 | C29: Christiana Attafuah | D29: 8 | E29: 46014 | F29: Omanjor D/A | G29: Pending | H29: Broiler | I29: +233 20 418 5566 | J29: Delivered
A30: 46014.17 | B30: 46003 | C30: Derrick | D30: 3 | E30: 46014 | F30: Bubiashie | G30: On-Delivery | H30: Layer | I30: 665 | J30: Pending
A31: 46011.514 | B31: 46011 | C31: Class Peters | D31: 5 | E31: 46013 | F31: Kasoa | G31: On-Delivery | H31: Broiler | I31: 243746751 | J31: Delivered
A32: 46013.257 | B32: 46003 | C32: corners- nsumfa | D32: 3 | E32: 46016 | F32: Tbd | G32: On-Delivery | H32: Broiler | I32: Tbd | J32: Delivered
A33: 46013.257 | B33: 46003 | C33: Edwin CBG | D33: 1 | E33: 46016 | F33: Tbd | G33: On-Delivery | H33: Broiler | I33: Tbd | J33: Delivered | K33: All cut
A34: 46008.278 | B34: 46008 | C34: Ellis Amuzu | D34: 10 | E34: 46010 | F34: Lapaz | G34: On-Delivery | H34: Broiler | I34: 265061724 | J34: Delivered | K34: 5 boxes
A35: 46008.336 | B35: 46008 | C35: Emefa | D35: 6 | E35: 46010 | F35: 3 locations | G35: Paid | H35: Broiler | I35: 0246973448-6 | J35: Delivered
A36: 46008.238 | B36: 46008 | C36: Enterprise Life | D36: 87 | E36: 45999 | F36: Dzorwulu | G36: Paid | H36: Broiler | I36: 243025315 | J36: Delivered
A37: 46008.606 | B37: 46008 | C37: Grandma Bishop | D37: 3 | E37: 46010 | F37: Korle bu | G37: On-Delivery | H37: Layer | I37: 243025315 | J37: Delivered
A38: 46008.283 | B38: 46008 | C38: Eric Gyan | D38: 7 | E38: 46014 | F38: Lapaz | G38: On-Delivery | H38: Broiler | I38: 555249425 | J38: Delivered
A39: 46012.472 | B39: 46012 | C39: Freda yeboah | D39: 2 | E39: 46013 | F39: Korle gonno | G39: On-Delivery | H39: Broiler | I39: +233 27 204 6771 | J39: Delivered | K39: Cut one
A40: 46008.605 | B40: 46008 | C40: Grandma bishop | D40: 3 | E40: 46010 | F40: Korle bu | G40: On-Delivery | H40: Broiler | I40: 243025315 | J40: Delivered
A41: 46007.764 | B41: 46003 | C41: Grandma Sarah | D41: 1 | E41: 46007 | F41: Lapaz | G41: On-Delivery | H41: Broiler | I41: 267269919 | J41: Delivered
A42: 46008.234 | B42: 46008 | C42: Harold | D42: 5 | E42: 46010 | F42: West lands | G42: On-Delivery | H42: Broiler | I42: 243025315 | J42: Delivered
A43: 46012.441 | B43: 46012 | C43: Harold | D43: 5 | E43: 46014 | F43: Spintex | G43: On-Delivery | H43: Broiler | I43: Tbd | J43: Delivered
A44: 46008.603 | B44: 46008 | C44: Koran | D44: 2 | E44: 46010 | F44: Mamprobi | G44: On-Delivery | H44: Layer | I44: ‪+233 24 313 4447‬ | J44: Delivered
A45: 46008.231 | B45: 46008 | C45: Kobby Loso | D45: 3 | E45: 46010 | F45: Awoshie | G45: Paid | H45: Broiler | I45: 249616716 | J45: Delivered | K45: Cut one - so 2 whole chicken and 1 cut
A46: 46008.275 | B46: 46008 | C46: Linda | D46: 2 | E46: 46010 | F46: Kwabenya | G46: Paid | H46: Layer | I46: 543414695 | J46: Delivered
A47: 46008.275 | B47: 46008 | C47: Linda | D47: 2 | E47: 46010 | F47: Kwabenya | G47: Paid | H47: Broiler | I47: 543414695 | J47: Delivered | K47: Box each one
A48: 46009.511 | B48: 46009 | C48: Maame Dede | D48: 6 | E48: 46010 | F48: Amormorley | G48: Paid | H48: Broiler | I48: +233 24 387 1605 | J48: Delivered
A49: 46014.43 | B49: 46003 | C49: Mama lit | D49: 2 | E49: 46015 | F49: Kaneshie | G49: On-Delivery | H49: Layer | I49: Tbd | J49: Delivered
A50: 46014.429 | B50: 46003 | C50: Mama lit | D50: 10 | E50: 46013 | F50: Kaneshie | G50: On-Delivery | H50: Broiler | I50: Tbd | J50: Delivered
A51: 46014.429 | B51: 46003 | C51: Mama lit | D51: 5 | E51: 46013 | F51: Kaneshie | G51: On-Delivery | H51: Broiler | I51: Tbd | J51: Pending
A52: 46008.268 | B52: 46008 | C52: Mrs. Yeboah/Auntie Didi | D52: 3 | E52: 46010 | F52: Airport Hills | G52: Paid | H52: Broiler | I52: 244628199 | J52: Delivered | K52: 1 box
A53: 46007.771 | B53: 46003 | C53: Mummy Joyce | D53: 5 | E53: 46007 | F53: Lapaz | G53: Paid | H53: Broiler | I53: 267269919 | J53: Delivered
A54: 46009.49 | B54: 46009 | C54: Mz Jones | D54: 3 | E54: 46013 | F54: Mile 7 | G54: On-Delivery | H54: Layer | I54: 244627336 | J54: Delivered | K54: all cut
A55: 46009.367 | B55: 46009 | C55: Mz zones | D55: 5 | E55: 46013 | F55: Mile 7 | G55: On-Delivery | H55: Broiler | I55: 244627336 | J55: Delivered | K55: 3 cut
A56: 46008.274 | B56: 46008 | C56: Naa Dedei | D56: 4 | E56: 46016 | F56: Ashingman | G56: Pending | H56: Layer | I56: 545134758 | J56: Delivered
A57: 46008.274 | B57: 46008 | C57: Naa Dedei | D57: 3 | E57: 46016 | F57: Ashongman | G57: On-Delivery | H57: Broiler | I57: 545134758 | J57: Delivered
A58: 46009.723 | B58: 46002 | C58: Nii Dodoo | D58: 30 | E58: 46001 | F58: Bubiashie | G58: Paid | H58: Layer | I58: 242343760 | J58: Delivered
A59: 46008.618 | B59: 46008 | C59: Percy | D59: 10 | E59: 46010 | F59: TDB | G59: On-Delivery | H59: Broiler | I59: 243025315 | J59: Delivered
A60: 46008.618 | B60: 46008 | C60: Percy/ Nii Ayitey | D60: 3 | E60: 46010 | F60: TDB | G60: On-Delivery | H60: Broiler | I60: 243025315 | J60: Pending
A61: 46014.742 | B61: 46008 | C61: Percy | D61: 50 | E61: 46010 | F61: Bubuashie | G61: Paid | H61: Layer | I61: Tbd | J61: Delivered
A62: 46015.573 | B62: 46015 | C62: Prince CBG | D62: 4 | E62: 46016 | F62: Tbd | G62: On-Delivery | H62: Broiler | I62: Tbd | J62: Delivered | K62: All cut
A63: 46008.273 | B63: 46008 | C63: Priscilla/ Naa Dedei | D63: 1 | E63: 46010 | F63: School of law | G63: Paid | H63: Layer | I63: 267871474 | J63: Delivered | K63: Cut 1
A64: 46008.272 | B64: 46008 | C64: Priscilla/ Naa Dedei | D64: 2 | E64: 46010 | F64: School of law | G64: Paid | H64: Broiler | I64: 267871474 | J64: Delivered | K64: Cut 1
A65: 46012.742 | B65: 46012 | C65: Ps Robert Armatey | D65: 3 | E65: 46013 | F65: Tbd | G65: On-Delivery | H65: Broiler | I65: Tbd | J65: Delivered
A66: 46014.37 | B66: 46014 | C66: Renald | D66: 2 | E66: 46014 | F66: Tbd | G66: Pending | H66: Broiler | I66: Tbd | J66: Delivered
A67: 46014.37 | B67: 46014 | C67: Renald | D67: 4 | E67: 46015 | F67: Tbd | G67: On-Delivery | H67: Layer | I67: Tbd | J67: Delivered
A68: 46015 | B68: 46014 | C68: Rev ClassPeters | D68: 4 | E68: 46015 | F68: Kwashieman | G68: On-Delivery | H68: Broiler | I68: Tbd | J68: Delivered
A69: 46011.515 | B69: 46011 | C69: Rev Maud | D69: 2 | E69: 46013 | F69: Unknown | G69: On-Delivery | H69: Broiler | I69: 244582807 | J69: Delivered
A70: 46012.702 | B70: 46012 | C70: Rev Quansah | D70: 1 | E70: 46013 | F70: Church on Sunday | G70: Paid | H70: Broiler | I70: +233 24 467 6945 | J70: Delivered
A71: 46008.22 | B71: 46000 | C71: Selase | D71: 4 | E71: 46010 | F71: East Legon | G71: On-Delivery | H71: Layer | I71: 243025315 | J71: Delivered
A72: 46008.22 | B72: 46000 | C72: Selase | D72: 4 | E72: 46010 | F72: East Legon | G72: On-Delivery | H72: Broiler | I72: 243025315 | J72: Delivered
A73: 46008.277 | B73: 46008 | C73: Sinclair | D73: 3 | E73: 46013 | F73: Mannhean Esakin | G73: On-Delivery | H73: Broiler | I73: 205449088 | J73: Delivered | K73: cut
A74: 46013.854 | B74: 46013 | C74: Sister | D74: 4 | E74: 46013 | F74: Lapaz | G74: Paid | H74: Broiler | I74: 243426067 | J74: Delivered
A75: 46008.229 | B75: 46008 | C75: Stanley | D75: 4 | E75: 46010 | F75: Pick Up | G75: On-Delivery | H75: Broiler | I75: 249486778 | J75: Delivered
A76: 46015.515 | B76: 46015 | C76: Stanley | D76: 4 | E76: 46015 | F76: Pick up | G76: On-Delivery | H76: Layer | I76: Tbd | J76: Delivered
A77: 46015.555 | B77: 46015 | C77: Tasha | D77: 2 | E77: 46015 | F77: Darkuman | G77: On-Delivery | H77: Broiler | I77: Tbd | J77: Delivered
A78: 46009.721 | B78: 45994 | C78: Tettehs | D78: 37 | E78: 46001 | F78: Lapaz | G78: Paid | H78: Layer | I78: 267269919 | J78: Delivered
A79: 46015.55 | B79: 46015 | C79: Tina | D79: 4 | E79: 46015 | F79: Osu | G79: On-Delivery | H79: Broiler | I79: Tbd | J79: Delivered
A80: 46008.607 | B80: 46008 | C80: Uncle George | D80: 2 | E80: 46010 | F80: Airport Hills | G80: On-Delivery | H80: Broiler | I80: ‪+233 54 434 9564‬ | J80: Delivered
A81: 46008.607 | B81: 46008 | C81: Uncle George | D81: 2 | E81: 46010 | F81: Airport Hills | G81: On-Delivery | H81: Layer | I81: ‪+233 54 434 9564‬ | J81: Delivered
A82: 46008.607 | B82: 46008 | C82: Unco- Patrick | D82: 1 | E82: 46010 | F82: Lapaz | G82: On-Delivery | H82: Broiler | I82: tbd | J82: Delivered
A83: 46013.257 | B83: 46003 | C83: Victor CBG | D83: 2 | E83: 46016 | F83: Tbd | G83: On-Delivery | H83: Broiler | I83: Tbd | J83: Delivered | K83: All cut
A84: 46015 | B84: 46014 | C84: Woman at kotoku | D84: 1 | E84: 46016 | F84: Kotoku | G84: On-Delivery | H84: Broiler | I84: Tbd | J84: Delivered

Sheet Mortality and Transfers
A1: Timestamp | B1: Mortality/Transfer date | C1: Recorder Name/ID | D1: Select record type | E1: Were there any mortalities today? | F1: Where did mortality occur | G1: Pen/House/Flock ID (where mortality occurred) | H1: Number of Mortalities | I1: Age/Stage of Birds (at time of mortality) | J1: Enter Age(number) | K1: Suspected Cause(s) of Mortality | L1: Additional Notes on Mortality | M1: Inventory Updated? | N1: Type of Movement | O1: Number of Birds Moved | P1: Source Pen/Location ID (from where birds moved) | Q1: Destination Pen/Location (to where birds moved) | R1: Reason for Movement | S1: Additional Notes on Bird Movement
A2: 46051.518 | B2: 45957 | C2: Tei | D2: Mortality | F2: SET B | G2: B174, 283 | H2: 2 | I2: MONTHS | J2: 8 | K2: Unknown
A3: 46051.513 | B3: 45956 | C3: Tei | D3: Mortality | F3: SET A | G3: W48 | H3: 1 | I3: MONTHS | J3: 19 | K3: Prolapse
A4: 46051.514 | B4: 45956 | C4: Tei | D4: Mortality | F4: SET B | G4: B299 | H4: 1 | I4: MONTHS | J4: 8 | K4: Pecking
A5: 46051.512 | B5: 45955 | C5: Tei | D5: Mortality | F5: SET B | G5: W105 | H5: 1 | I5: MONTHS | J5: 8 | K5: Prolapse
A6: 46051.406 | B6: 45954 | C6: Tei | D6: Mortality | F6: SET A | G6: B1 | H6: 1 | I6: MONTHS | J6: 19 | K6: Disease (specify in notes) | L6: Egg Yolk Peritonitis
A7: 46051.408 | B7: 45954 | C7: Tei | D7: Mortality | F7: SET B | G7: B214, 158 | H7: 2 | I7: MONTHS | J7: 8 | K7: Pecking
A8: 46051.402 | B8: 45953 | C8: Tei | D8: Mortality | F8: SET A | G8: B29 | H8: 1 | I8: MONTHS | J8: 19 | K8: Pecking
A9: 46051.402 | B9: 45953 | C9: Tei | D9: Mortality | F9: SET B | G9: W64 | H9: 1 | I9: MONTHS | J9: 8 | K9: Prolapse
A10: 46051.405 | B10: 45953 | C10: Tei | D10: Mortality | F10: SET D | G10: House | H10: 85 | I10: WEEKS | J10: 3 | K10: Predator Attack | L10: Stampede due to predator attack
A11: 46051.344 | B11: 45952 | C11: Tei | D11: Mortality | F11: SET A | G11: W51 | H11: 1 | I11: MONTHS | J11: 19 | K11: Disease (specify in notes) | L11: Egg Yolk Peritonitis
A12: 46051.345 | B12: 45952 | C12: Tei | D12: Mortality | F12: SET B | G12: W26, W83 | H12: 2 | I12: MONTHS | J12: 8 | K12: Mites Infestation
A13: 46051.256 | B13: 45951 | C13: Tei | D13: Mortality | F13: SET A | G13: B16, 19, 32 | H13: 3 | I13: MONTHS | J13: 19 | K13: Disease (specify in notes) | L13: Egg Yolk Peritonitis
A14: 46051.257 | B14: 45951 | C14: Tei | D14: Mortality | F14: SET B | G14: W4, B211, 8 | H14: 3 | I14: MONTHS | J14: 8 | K14: Mites Infestation
A15: 46051.104 | B15: 45950 | C15: Tei | D15: Mortality | F15: SET B | G15: B57 | H15: 1 | I15: MONTHS | J15: 8 | K15: Pecking
A16: 46051.103 | B16: 45949 | C16: Tei | D16: Mortality | F16: SET A | G16: B65 | H16: 1 | I16: MONTHS | J16: 19 | K16: Disease (specify in notes) | L16: Egg Yolk Peritonitis
A17: 46051.096 | B17: 45948 | C17: Tei | D17: Mortality | F17: SET A | G17: W6 | H17: 1 | I17: MONTHS | J17: 19 | K17: Pecking
A18: 46051.098 | B18: 45948 | C18: Tei | D18: Mortality | F18: SET B | G18: W91 | H18: 1 | I18: MONTHS | J18: 8 | K18: Pecking
A19: 46051.095 | B19: 45947 | C19: Tei | D19: Mortality | F19: SET B | G19: W78 | H19: 1 | I19: MONTHS | J19: 8 | K19: Unknown
A20: 46050.607 | B20: 45946 | C20: Tei | D20: Mortality | F20: SET A | G20: B3 | H20: 1 | I20: MONTHS | J20: 19 | K20: Pecking
A21: 46050.609 | B21: 45946 | C21: Tei | D21: Mortality | F21: SET B | G21: B243, 158, W82 | H21: 3 | I21: MONTHS | J21: 8 | K21: Pecking
A22: 46050.603 | B22: 45944 | C22: Tei | D22: Mortality | F22: SET B | G22: B52, B195 | H22: 2 | I22: MONTHS | J22: 8 | K22: Mites infestation
A23: 46050.599 | B23: 45943 | C23: Tei | D23: Mortality | F23: SET A | G23: W38 | H23: 1 | I23: MONTHS | J23: 19 | K23: Prolapse
A24: 46050.602 | B24: 45943 | C24: Tei | D24: Mortality | F24: SET B | G24: W45 | H24: 1 | I24: MONTHS | J24: 8 | K24: Mites infestation
A25: 46050.587 | B25: 45941 | C25: Tei | D25: Mortality | F25: SET B | G25: B55 | H25: 1 | I25: MONTHS | J25: 8 | K25: Prolapse
A26: 46050.581 | B26: 45940 | C26: Tei | D26: Mortality | F26: SET A | G26: B57 | H26: 1 | I26: MONTHS | J26: 19 | K26: Pecking
A27: 46050.582 | B27: 45940 | C27: Tei | D27: Mortality | F27: SET B | G27: W78 | H27: 1 | I27: MONTHS | J27: 8 | K27: Pecking
A28: 46050.576 | B28: 45939 | C28: Tei | D28: Mortality | F28: SET A | G28: W1, 7,27,39,48, B26,43,51,72 | H28: 9 | I28: MONTHS | J28: 19 | K28: Mites infestation
... A35: 46050.447 | B35: 45933 | C35: Tei | D35: Mortality | F35: SET B | G35: W1, B134 | H35: 2 | I35: MONTHS | J35: 8 | K35: Prolapse
A36: 46050.397 | B36: 45931 | C36: Tei | D36: Mortality | F36: SET A | G36: W22, W48 | H36: 2 | I36: MONTHS | J36: 8 | K36: Disease (specify in notes) | L36: Wry Neck (twisting neck)
A37: 46050.398 | B37: 45931 | C37: Tei | D37: Mortality | F37: SET B | G37: B65, W83 | H37: 2 | I37: MONTHS | J37: 8 | K37: Pecking
A38: 46050.405 | B38: 45931 | C38: Tei | D38: Mortality | F38: SET D | G38: House | H38: 1 | I38: DAYS | J38: 2 | K38: Accident/Injury
A39: 46050.393 | B39: 45930 | C39: Tei | D39: Mortality | F39: SET B | G39: B143 | H39: 1 | I39: MONTHS | J39: 8 | K39: Mites
A40: 46050.404 | B40: 45930 | C40: Tei | D40: Mortality | F40: SET D | G40: House | H40: 2 | I40: DAYS | J40: 1 | K40: Accident/Injury
A41: 46050.382 | B41: 45929 | C41: Tei | D41: Mortality | F41: SET A | G41: B51 | H41: 1 | I41: MONTHS | J41: 19 | K41: Pecking
A42: 46050.383 | B42: 45929 | C42: Tei | D42: Mortality | F42: SET B | G42: B269 | H42: 1 | I42: MONTHS | J42: 8 | K42: Pecking
A43: 46050.322 | B43: 45928 | C43: Tei | D43: Mortality | F43: SET B | G43: W89, B301 | H43: 2 | I43: MONTHS | J43: 8 | K43: Mites infestation
A44: 46050.297 | B44: 45927 | C44: Tei | D44: Mortality | F44: SET A | G44: W56 | H44: 1 | I44: MONTHS | J44: 19 | K44: Looking Weak
A45: 46050.314 | B45: 45927 | C45: Tei | D45: Mortality | F45: SET B | G45: W96 | H45: 1 | I45: MONTHS | J45: 8 | K45: Pecking
A46: 46050.295 | B46: 45926 | C46: Tei | D46: Mortality | F46: SET B | G46: B288, B113, W77 | H46: 3 | I46: MONTHS | J46: 8 | K46: Pecking
A47: 46050.293 | B47: 45925 | C47: Tei | D47: Mortality | F47: SET B | G47: B11 | H47: 1 | I47: MONTHS | J47: 8 | K47: Accident/Injury,
A48: 46050.285 | B48: 45924 | C48: Tei | D48: Mortality | F48: SET A | G48: B49 | H48: 1 | I48: MONTHS | J48: 19 | K48: Looking Weak
... A62: 46046.522 | B62: 45900 | C62: Tei | D62: Mortality | F62: SET B | G62: W73 | H62: 1 | I62: MONTHS | J62: 8 | K62: Perking
A63: 45898.018 | B63: 45896 | C63: Tei | D63: Mortality | F63: SET B | G63: B244, W132, W305 | H63: 3 | I63: MONTHS | J63: 8 | K63: Accident/Injury, | L63: Perking | M63: Yes
A64: 45898.017 | B64: 45896 | C64: Tei | D64: Mortality | F64: SET C | G64: House | H64: 2 | I64: WEEKS | J64: 14 | K64: Accident/Injury | L64: Stampede | M64: Yes
A65: 45887.703 | B65: 45887 | C65: Tei | D65: Mortality | F65: SET B | G65: B307, B211 | H65: 2 | I65: MONTHS | J65: 7 | K65: Prolapse and Mites | L65: Medication will begin tomorrow (Dufamec Solution) | M65: Yes
A66: 45886.702 | B66: 45885 | C66: Tei | D66: Mortality | F66: SET C | G66: House | H66: 6 | I66: WEEKS | J66: 12 | K66: Stress | L66: Feeling weak and vaccination stress | M66: Yes
A67: 45873.733 | B67: 45873 | C67: Tei | D67: Mortality | F67: SET A | G67: QT | H67: 2 | I67: MONTHS | J67: 17 | K67: Paralysis | L67: Been paralyzed and weak for a while | M67: Yes
A68: 45873.728 | B68: 45868 | C68: Tei | D68: Mortality | F68: SET B | G68: W188, B192, B232, B215 | H68: 4 | I68: WEEKS | J68: 31 | K68: Perking | L68: Debeaking ongoing to prevent perking | M68: Yes
A69: 45864.738 | B69: 45864 | C69: Tei | D69: Mortality | F69: SET C | G69: House | H69: 3 | I69: WEEKS | J69: 9 | K69: Disease (specify in notes) | L69: Coccidiosis | M69: Yes
A70: 45855.799 | B70: 45855 | C70: Tei | D70: Mortality | F70: SET B | G70: W104, W111 | H70: 2 | I70: WEEKS | J70: 29 | K70: Perking | L70: Perked while laying | M70: Yes
A71: 45855.795 | B71: 45855 | C71: Tei | D71: Mortality | F71: SET A | G71: B49 | H71: 1 | I71: WEEKS | J71: 74 | K71: Unknown | L71: Looking very weak till death | M71: Yes
A72: 45855.744 | B72: 45855 | C72: Tei | D72: Mortality | F72: SET C | G72: House | H72: 2 | I72: WEEKS | J72: 8 | K72: Disease (specify in notes) | L72: Coccidiosis under control. Treatment still in progress | M72: Yes
A73: 45847.802 | B73: 45846 | C73: Tei | D73: Mortality | F73: SET C | G73: House | H73: 10 | I73: WEEKS | J73: 6 | K73: Disease (specify in notes) | L73: Under treatment for coccidiosis | M73: Yes
A74: 45846.67 | B74: 45845 | C74: Tei | D74: Mortality | F74: SET B | G74: B92, B243 | H74: 2 | I74: MONTHS | J74: 6 | K74: Prolapse | M74: Yes
A75: 45834.999 | B75: 45835 | C75: Tei | D75: Mortality | F75: SET C | G75: House | H75: 5 | I75: WEEKS | J75: 6 | K75: Disease (specify in notes) | L75: Coccidiosis. Treatment ongoing | M75: Yes
A76: 45835.003 | B76: 45834 | C76: Tei | D76: Transfer/Relocation | M76: Yes | N76: Internal Transfer (between pens on farm) | O76: 2 | P76: W45 | Q76: QT | R76: SET A - Quarantine | S76: Reduction in weight and looking weak
A77: 45835.001 | B77: 45834 | C77: Tei | D77: Mortality | F77: SET B | G77: W168, B288 | H77: 2 | I77: MONTHS | J77: 6 | K77: Fats/Prolapse | M77: Yes
A78: 45832.299 | B78: 45832 | C78: Tei | D78: Transfer/Relocation | M78: Yes | N78: Internal Transfer (between pens on farm) | O78: 5 | P78: Quarantine | Q78: B66, W26 | R78: SET A - Quarantine | S78: They are looking better now but not laying yet
A79: 45830.813 | B79: 45830 | C79: Tei | D79: Mortality | E79: Yes | F79: SET C | G79: House | H79: 11 | I79: WEEKS | J79: 5 | K79: Stampede | M79: Yes
A80: 45830.803 | B80: 45825 | C80: Tei | D80: Mortality | E80: Yes | F80: SET B | G80: B244, B303 | H80: 2 | I80: MONTHS | J80: 6 | K80: Fatty Liver Syndrome | L80: Dufamec oral solution into their drinking water | M80: Yes
A81: 45824.893 | B81: 45824 | C81: Tei | D81: Mortality | E81: Yes | F81: SET B | G81: B203 | H81: 1 | I81: WEEKS | J81: 24 | K81: Unknown | L81: The bird looked like it had died for long so I couldn’t tell what the cause was even after doing my personal postmortem. It had started turning green so some of the organs were also changing in color | M81: Yes
A82: 45824.882 | B82: 45822 | C82: Tei | D82: Mortality | E82: Yes | F82: SET A | G82: B58 | H82: 1 | I82: MONTHS | J82: 16 | K82: Unknown | M82: Yes
A83: 45820.777 | B83: 45820 | C83: Tei | D83: Mortality | E83: Yes | F83: SET B | G83: W156 / B189 | H83: 2 | I83: WEEKS | J83: 24 | K83: Prolapse / Perking | M83: Yes
A84: 45820.774 | B84: 45819 | C84: Tei | D84: Mortality | E84: Yes | F84: SET B | G84: B266 | H84: 1 | I84: WEEKS | J84: 24 | K84: Unknown | L84: Guessing stressing from construction noise cos everything looked okay internally | M84: Yes
A85: 45813.938 | B85: 45813 | C85: Tei | D85: Mortality | E85: Yes | F85: SET A | G85: B54, W25 | H85: 2 | I85: MONTHS | J85: 15 | K85: Stress from construction | M85: Yes
A86: 45814.927 | B86: 45812 | C86: Tei | D86: Mortality | E86: Yes | F86: SET A | G86: B60 | H86: 1 | I86: MONTHS | J86: 15 | K86: Fats | L86: Fatty acid syndrome treatment didn’t go down well with all but I’m not supposed to give the medicine for more than 5 days so I had to stop But it’s been over two weeks now so I’ve started the detox treatment again today to meet the others | M86: Yes
A87: 45811.591 | B87: 45811 | C87: Tei | D87: Mortality | E87: Yes | F87: SET B | G87: B209 | H87: 1 | I87: MONTHS | J87: 5 | K87: Prolapse | L87: The change of feed is also having a little effect on them | M87: Yes
A88: 45811.588 | B88: 45811 | C88: Tei | D88: Mortality | E88: Yes | F88: SET A | G88: B64 | H88: 1 | I88: MONTHS | J88: 15 | K88: Predator Attack | L88: I saw a mouse around the farm about 3 days ago So I suspect they have a hand in it | M88: Yes
A89: 45809.835 | B89: 45809 | C89: Tei | D89: Mortality | E89: Yes | F89: SET A | G89: W33 | H89: 1 | I89: MONTHS | J89: 15 | K89: Unknown | M89: Yes
A90: 46054.777 | B90: 45958 | C90: Tei | D90: Mortality | F90: SET B | G90: B188 | H90: 1 | I90: MONTHS | J90: 9 | K90: Accident/Injury
A91: 46054.781 | B91: 45959 | C91: Tei | D91: Mortality | F91: SET A | G91: B41 | H91: 1 | I91: MONTHS | J91: 20 | K91: Disease (specify in notes), Egg Yolk Peritonitis
A92: 46054.783 | B92: 45959 | C92: Tei | D92: Mortality | F92: SET B | G92: W5, B83 | H92: 2 | I92: MONTHS | J92: 9 | K92: Pecking
A93: 46054.784 | B93: 45961 | C93: Tei | D93: Mortality | F93: SET B | G93: B87, B26 | H93: 2 | I93: MONTHS | J93: 9 | K93: Pecking
A94: 46054.789 | B94: 45962 | C94: Tei | D94: Mortality | F94: SET A | G94: W49, W2 | H94: 3 | I94: MONTHS | J94: 19 | K94: Pecking
A95: 46054.79 | B95: 45962 | C95: Tei | D95: Mortality | F95: SET B | G95: W82, B19, B194 | H95: 3 | I95: MONTHS | J95: 9 | K95: Pecking

Sheet Stock trace
A1: Timestamp | B1: Event Type | C1: Coop/Cage | D1: Quantity | E1: Details | F1: Action taken | G1: Remarks | H1: SET
A2: 45797.842 | B2: Mortality | C2: Cage | D2: 12 | E2: Excess fat | F2: Investigated cause | G2: Treating Fatty Acid Syndrome by detoxing | H2: LAYER SET A | I2: Mortality Summary | J2: LAYER SET A | K2: =SUMIF(H2:H2001,J2,D2:D2001) -> 42
A3: 45779.897 | B3: Mortality | C3: Coop | D3: 1 | E3: Stress | F3: Investigated cause | G3: Stampede | H3: LAYER SET B
A4: 45779.896 | B4: Mortality | C4: Cage | D4: 1 | E4: Stress | F4: Investigated cause | G4: Perking and Panicking | H4: LAYER SET A
A5: 45777.289 | B5: Mortality | C5: Cage | D5: 5 | E5: Stress | F5: Inspected health | G5: Still stepping on themselves, we stay there for long to prevent that but we still woke up to these mortalities | H5: LAYER SET A
A6: 45777.264 | B6: Mortality | C6: Cage | D6: 5 | E6: Stress | F6: Inspected health | G6: They keep standing on each other which bursts the yokes in them and causes infection | H6: LAYER SET A
A7: 45777.259 | B7: Mortality | C7: Coop | D7: 1 | E7: Stress | F7: Inspected health | G7: Stampede from rain | H7: LAYER SET B
A8: 45774.127 | B8: Mortality | C8: Cage | D8: 4 | E8: Stress | F8: Investigated cause | G8: Stress from construction | H8: LAYER SET A
A9: 45771.337 | B9: Mortality | C9: Cage | D9: 3 | E9: Stress | F9: Investigated cause | G9: Perking and egg-binding(dystopia). Selective Debeaking will be done and administering of lasota to help produce more healthy eggs | H9: LAYER SET A
A10: 45766.102 | B10: Mortality | C10: Coop | D10: 3 | E10: Stress | F10: Inspected health | G10: Overweight stress | H10: BROILER
A11: 45756.049 | B11: Mortality | C11: Cage | D11: 10 | E11: Disease | F11: Treatment initiated | G11: Mites infestation which was treated by using cypervet | H11: LAYER SET A
A12: 45756.045 | B12: Mortality | C12: Coop | D12: 6 | E12: Stress | F12: Treatment initiated | G12: Feed reduction at a point, visiting often to rectify falling on back issues | H12: BROILER
A13: 45756.034 | B13: Mortality | C13: Coop | D13: 2 | E13: Stress | F13: Investigated cause | G13: Stress from debeaking | H13: LAYER SET B
A14: 45756.033 | B14: Mortality | C14: Coop | D14: 40 | E14: Stress | F14: Investigated cause | G14: Avoid overcrowding during vaccinations to prevent stampede | H14: LAYER SET B
A15: 45734.323 | B15: Mortality | C15: W22/WQT | D15: 2 | E15: Disease | F15: Treatment initiated | G15: Sent them to the vet for post-mortem and they found mites on them so they're on medication now. | H15: LAYER SET A | I15: Layer SET A | J15: 430
A16: 45731.328 | B16: Mortality | C16: QT | D16: 1 | E16: Perking | F16: Investigated cause | G16: Under medication
A17: 45731.324 | B17: Mortality | C17: Broiler | D17: 1 | E17: Stress | F17: Treatment initiated | G17: Stress from sawdust change
A18: 45731.315 | B18: Mortality | C18: B2 | D18: 1 | E18: Stress | F18: Inspected health | G18: Medication to be administered
A19: 45727.01 | B19: Mortality | C19: B18 | D19: 1 | E19: Cause unidentified | F19: Inspected health | G19: Need to check they're kidneys and hearts
A20: 45726.973 | B20: Mortality | C20: W | D20: 1 | E20: Prolapse | F20: Inspected health | G20: Was under treatment but couldn't make it out of QT
A21: 45709.452 | B21: Mortality | C21: Broiler | D21: 1 | E21: Stress | F21: Inspected health | G21: Stress from transportation
A22: 45709.45 | B22: Quarantine | C22: B75 | D22: 2 | E22: Excess fat | F22: Treatment initiated | G22: Feed reduced
A23: 45709.443 | B23: Quarantine | C23: B44 | D23: 1 | E23: Paralysis | F23: Treatment initiated | G23: Isolated and taking antibiotic vitamins
A24: 45709.441 | B24: Quarantine | C24: W3 | D24: 1 | E24: Paralysis | F24: Treatment initiated | G24: Isolated and taking antibiotic vitamins
A25: 45709.439 | B25: Mortality | C25: SET 1 | D25: 4 | E25: Excess fat | F25: Investigated cause | G25: Measures like reduction in feed and detoxification is Being taken
A26: 45709.387 | B26: Mortality | C26: SET 2 | D26: 17 | E26: Perking | F26: Treatment initiated | G26: Mixed salt with their feed

Sheet Request Form
A1: Timestamp | B1: Item Name | C1: Quantity | D1: Price | E1: Due Date | F1: Purpose
A2: 45680.052 | B2: Day-Old Feeders | C2: 5 | E2: 45658 | F2: Farm Use
A3: 45680.053 | B3: 10L Drinker | C3: 4 | E3: 45658 | F3: Farm Use
A4: 45710.69 | B4: Feeder - Big | C4: 3 | E4: 45709 | F4: Farm Use
A5: 45710.691 | B5: 10L Drinker | C5: 11 | E5: 45709 | F5: Farm Use
A6: 45710.692 | B6: 10L Drinker | C6: 6 | E6: 45710 | F6: Sale
A7: 45710.692 | B7: Feeder - Big | C7: 6 | E7: 45710 | F7: Sale
A8: 45727.023 | B8: Overall | C8: 2 | E8: 45727 | F8: Farm Use
A9: 45727.023 | B9: Boot | C9: 2 | E9: 45727 | F9: Farm use
B10: big cooler box | C10: 1 | D10: 40 | F10: sale- Bank
B11: small cooler bag | C11: 1 | D11: 40 | F11: sale- Bank

Sheet COS Layers 1
A1: DATE
A2: Timestamp | B2: Item name/Service Description | C2: Service/item category | D2: Quantity | E2: Unit Price | F2: Amount Paid | G2: Column 1
A3: MED
A4: 45772.471 | B4: Lasota Vaccine | C4: Layers - SET 1 | D4: 1 | E4: 100 | F4: 100 | G4: =D4*E4 -> 100
A5: 45771.318 | B5: Postmortem | C5: Layers - SET 1 | D5: 2 | E5: 50 | F5: 100 | G5: =D5*E5 -> 100
A6: 45770.208 | B6: Colvit | C6: Layers - SET 1 | D6: 1 | E6: 175 | F6: 175 | G6: =D6*E6 -> 175
A7: 45750.561 | B7: Postmortem | C7: Layers - SET 1 | D7: 1 | E7: 50 | F7: 50 | G7: =D7*E7 -> 50
A8: 45736.915 | B8: MultiAmino-M 1kg | C8: Layers - SET 1 | D8: 1 | E8: 224 | F8: 224 | G8: =D8*E8 -> 224
A9: 45736.91 | B9: Cypervet 12% 1kg | C9: Layers - SET 1 | D9: 1 | E9: 226 | F9: 226 | G9: =D9*E9 -> 226
A10: 45736.91 | B10: Acalice Super 1kg | C10: Layers - SET 1 | D10: 1 | E10: 80 | F10: 80 | G10: =D10*E10 -> 80
A11: 45734.347 | B11: Med - Dufamec | C11: Layers - SET 1 | D11: 1 | E11: 356 | F11: 356 | G11: =D11*E11 -> 356
A12: 45734.337 | B12: Post-mortem | C12: Layers - SET 1 | D12: 2 | E12: 50 | F12: 100 | G12: =D12*E12 -> 100
A13: 45674.175 | B13: 2nd Gumboro Vaccination | C13: Layers | D13: 1 | E13: 340 | F13: 340 | G13: =D13*E13 -> 340
A14: 45668.451 | B14: Oxytetravet aerosol | C14: Layers | D14: 1 | E14: 78 | F14: 78 | G14: =D14*E14 -> 78
A15: 45665.832 | B15: 1st Gumboro Vaccination | C15: Layers | D15: 1 | E15: 320 | F15: 320 | G15: =D15*E15 -> 320
... A17: 45667.304 | B17: 1st Newcastle Vaccination | C17: Layers | D17: 1 | E17: 270 | F17: 270 | G17: =D17*E17 -> 270
G18: =D18*E18 -> 0
G19: =D19*E19 -> 0
G20: =D20*E20 -> 0
A21: FEED | G21: =D21*E21 -> 0
A22: 45770.204 | B22: Koudijs Layer 2 | C22: Layers - SET 1 | D22: 20 | E22: 424 | F22: 8480 | G22: =D22*E22 -> 8480
A23: 45767.07 | B23: Koudijs layer 2 Mash | C23: Layers - SET 1 | D23: 1 | E23: 424 | F23: 424 | G23: =D23*E23 -> 424
A24: 45752.941 | B24: Koudijs Layer 2 Mash | C24: Layers - SET 1 | D24: 15 | E24: 424 | F24: 6360 | G24: =D24*E24 -> 6360
A25: 45750.368 | B25: Koudijs Layer 2 Mash | C25: Layers - SET 1 | D25: 5 | E25: 424 | F25: 2120 | G25: =D25*E25 -> 2120
A26: 45747.787 | B26: Koudijs Layer 2 Mash | C26: Layers - SET 1 | D26: 2 | E26: 424 | F26: 848 | G26: =D26*E26 -> 848
A27: 45739.004 | B27: Layer 2 Mash | C27: Layers - SET 1 | D27: 10 | E27: 424 | F27: 4240 | G27: =D27*E27 -> 4240
A28: 45736.911 | B28: Layer 2 Mash | C28: Layers - SET 1 | D28: 1 | E28: 424 | F28: 424 | G28: =D28*E28 -> 424
A29: 45736.023 | B29: Layer 2 Mash | C29: Layers - SET 1 | D29: 1 | E29: 424 | F29: 424 | G29: =D29*E29 -> 424
A30: 45727.528 | B30: Layer 2 Mash | C30: Layers - SET 1 | D30: 12 | E30: 424 | F30: 5088 | G30: =D30*E30 -> 5088
A31: 45713.083 | B31: Koudijs Layer 2 Mash | C31: Layers - SET 1 | D31: 12 | E31: 424 | F31: 5088 | G31: =D31*E31 -> 5088
A32: 45702.446 | B32: Koudijs Layer 2 Mash | C32: Layers - SET 1 | D32: 10 | E32: 424 | F32: 4240 | G32: =D32*E32 -> 4240
A33: 45696.565 | B33: Koudijs Layer 2 Mash | C33: Layers - SET 1 | D33: 6 | E33: 424 | F33: 2544 | G33: =D33*E33 -> 2544
... A39: 45668.45 | B39: Layer 1 Mash | C39: Layers | D39: 5 | E39: 414 | F39: 2070 | G39: =D39*E39 -> 2070
G40: =D40*E40 -> 0
G41: =D41*E41 -> 0
G42: =D42*E42 -> 0
G43: =D43*E43 -> 0
A44: OTHERS | G44: =D44*E44 -> 0
A45: 45713.085 | B45: Crates | C45: Layers - SET 1 | D45: 10 | E45: 82 | F45: 820 | G45: =D45*E45 -> 820
A46: 45702.445 | B46: Crates | C46: Layers - SET 1 | D46: 5 | E46: 82 | F46: 410 | G46: =D46*E46 -> 410
A47: 45668.451 | B47: Crates | C47: Layers | D47: 5 | E47: 80 | F47: 400 | G47: =D47*E47 -> 400
A48: 45665.833 | B48: Crates | C48: Layers | D48: 2 | E48: 82 | F48: 164 | G48: =D48*E48 -> 164
A49: 45773.76 | B49: Sawdust | C49: Admin expense | D49: 1 | E49: 250 | F49: 250 | G49: =D49*E49 -> 250
A50: 45771.821 | B50: Withdrawal charge | C50: Admin expense | D50: 1 | E50: 15 | F50: 15 | G50: =D50*E50 -> 15
A51: 45770.208 | B51: Patholyte Disinfectant | C51: Admin expense | D51: 1 | E51: 230 | F51: 230 | G51: =D51*E51 -> 230
A52: 45770.206 | B52: Egg Crates | C52: Admin expense | D52: 10 | E52: 80 | F52: 800 | G52: =D52*E52 -> 800
A53: 45766.277 | B53: Sawdust | C53: Admin expense | D53: 1 | E53: 155 | F53: 155 | G53: =D53*E53 -> 155
A54: 45763.452 | B54: Momo Charges | C54: Admin expense | D54: 1 | E54: 80 | F54: 80 | G54: =D54*E54 -> 80
A55: 45749.84 | B55: Sawdust | C55: Admin expense | D55: 1 | E55: 65 | F55: 65 | G55: =D55*E55 -> 65
A56: 45747.734 | B56: Sawdust | C56: Admin expense | D56: 32 | E56: 8 | F56: 256 | G56: =D56*E56 -> 256
... A74: 45668.276 | B74: Transporting farm materials | C74: Transportation | D74: 1 | E74: 500 | F74: 500 | G74: =D74*E74 -> 500

Sheet PMT Summary
A1: EGG SALES SUMMARY
A2: Total Sales | B2: Amount Banked | C2: Not Banked | D2: MoMo Sales | E2: Cash Sales | F2: Sold(singles) | G2: Sold(crates)
A3: =SUM('Egg Sales'!I:I) -> 604093 | B3: =SUM('Egg Sales'!L:L) -> 600653 | C3: =A3-B3-D3 -> 3440 | D3: =SUMIFS('Egg Sales'!H:H,'Egg Sales'!F:F,"MOMO") -> 0 | E3: =SUMIFS('Egg Sales'!I:I,'Egg Sales'!G:G,"Bank") -> 301286 | F3: =SUM('Egg Sales'!J:J) -> 351420 | G3: =F3/30 -> 11714
A6: EGGS TOTAL INVENTORY
A7: Total Collected | B7: Actual Total | C7: In Stock(singles) | D7: In Stock(Crate) | E7: Damaged(Singles) | F7: Damaged(Crates) | G7: % Damaged
A8: =SUM(Production!J:J) -> 352087 | B8: =F23+B18+F28 -> 344299 | C8: =B8-F3 -> -7121 | D8: =C8/30 -> -237.36667 | E8: =E23+C18+E28+C23 -> 7788 | F8: =E8/30 -> 259.6 | G8: =E8/A8 -> 0.022119533
A11: ACCOUNT SUMMARY
A12: Amount Spent | B12: Amount Issued | C12: Balance | D12: Deposit | E12: TOTAL | F12: REVENUE | G12: Gross Profit
A13: =SUM('Accountable Imprest '!O:O) -> 1332023.2 | B13: =SUM(Imprest!B:B) -> 1304609 | C13: =B13-A13 -> -27414.2 | E13: =C13+D32+C3 -> -23974.2 | F13: =A3+B32+E36+G36 -> 697543 | G13: =F13-A13 -> -634480.2
A16: EGGS INVENTORY SUMMARY - SET A
A17: Total Collected | B17: Actual Total | C17: Damaged(Singles) | D17: Damaged(Crates)
A18: =SUMIF(Production!G:G,"SET A",Production!J:J) -> 118074 | B18: =SUMIF(Production!G:G,"SET A",Production!K:K) -> 115575 | C18: =SUMIF(Production!G:G,"SET A",Production!E:E) -> 2499 | D18: =C18/30 -> 83.3 | E18: =C18/A18 -> 0.021164693
A21: EGGS INVENTORY SUMMARY - SET B
A22: Total Collected | B22: Actual Total | C22: D(singles) | D22: D(crate) | E22: Damaged(Singles) | F22: Actual | G22: % Damaged
A23: =SUMIF(Production!G:G,"SET B",Production!J:J) -> 194908 | B23: =SUMIF(Production!G:G,"SET B",Production!K:K) -> 190508 | C23: =D23*30 -> 240 | D23: 8 | E23: =SUMIF(Production!G:G,"SET B",Production!E:E) -> 4400 | F23: =A23-E23-C23 -> 190268 | G23: =E23/A23 -> 0.022574753
A26: EGGS INVENTORY SUMMARY - SET C
A27: Total Collected | B27: Actual Total | C27: D(singles) | D27: D(crate) | E27: Damaged(Singles) | F27: Actual | G27: % Damaged
A28: =SUMIF(Production!G:G,"SET C",Production!J:J) -> 39105 | B28: =SUMIF(Production!G:G,"SET C",Production!K:K) -> 38456 | C28: =D28*30 -> 0 | D28: 0 | E28: =SUMIF(Production!G:G,"SET C",Production!E:E) -> 649 | F28: =A28-E28-C28 -> 38456 | G28: =E28/A28 -> 0.016596343
A30: BROILER SUMMARY
A31: QTY Sold | B31: TOTAL SALES | C31: Sales Banked | D31: NOT BANKED | E31: LIVE QTY | F31: LIVE QTY | G31: FROZEN QTY
A32: =SUM('Broiler Sales'!D:D) -> 89 | B32: =SUM('Broiler Sales'!I:I) -> 19320 | C32: =SUM('Broiler Sales'!J:J) -> 19320 | D32: =B32-C32 -> 0
A34: XMAS BROILER SUMMARY
A35: Ordered QTY | B35: Total Stock | C35: In Stock | D35: QTY Delivered | E35: Amount Sold | F35: Pending Delivery | G35: Layers SOLD AMT
A36: =SUMIF('Broiler Orders'!H:H,"Broiler",'Broiler Orders'!D:D) -> 304 | B36: =239+40+20+20 -> 319 | C36: =B36-A36 -> 15 | D36: =SUMIF('Dec 2025 Sales'!D:D,"Broiler",'Dec 2025 Sales'!E:E) -> 304 | E36: =SUMIF('Dec 2025 Sales'!D:D,"Broiler",'Dec 2025 Sales'!I:I) -> 63380 | F36: =A36-D36 -> 0 | G36: =SUMIF('Dec 2025 Sales'!D:D,"Layer",'Dec 2025 Sales'!I:I) -> 10750
A38: LAYERS INVENTORY SUMMARY
A39: SET A | B39: SET B | C39: SET C | D39: TOTAL(Laying)
A40: =SUMIF(Stock!C:C,"SET A",Stock!B:B) -> 410 | B40: =SUMIF(Stock!C:C,"SET B",Stock!B:B) -> 1126 | C40: =SUMIF(Stock!C:C,"SET C",Stock!B:B) -> 465 | D40: =SUM(A40:B40) -> 1536
A42: SET A - QTN | B42: SET B - QTN | C42: SET C - QTN | D42: QTN TOTAL
A43: =SUMIF(Stock!C:C,"SET A - Quarantine",Stock!B:B) -> 4 | B43: =SUMIF(Stock!C:C,"SET B - Quarantine",Stock!B:B) -> 0 | C43: =SUMIF(Stock!C:C,"SET C - Quarantine",Stock!B:B) -> 0 | D43: =SUM(A43:C44) -> 4
A46: SET A TOTAL | B46: SET B TOTAL | C46: SET C TOTAL | D46: SET D TOTAL | E46: BROILERS TOTAL | G46: TOTAL
A47: =SUM(A40,A43) -> 414 | B47: =SUM(B40,B43) -> 1126 | C47: =SUM(C40,C43) -> 465 | D47: =Stock!F6 -> 2020 | G47: =SUM(A47:D48) -> 4025
A49: MORTALITY
A50: SET A | B50: SET B | C50: SET C
A51: =SUMIF('Mortality and Transfers'!F:F,"SET A",'Mortality and Transfers'!H:H)/Stock!F3 -> 0.11352657 | B51: =SUMIF('Mortality and Transfers'!F:F,"SET B",'Mortality and Transfers'!H:H)/Stock!F4 -> 0.071428571 | C51: =SUMIF('Mortality and Transfers'!F:F,"SET C",'Mortality and Transfers'!H:H)/Stock!F5 -> 0.077380952
A52: =SUMIF('Mortality and Transfers'!F:F,"SET A",'Mortality and Transfers'!H:H) -> 47 | B52: =SUMIF('Mortality and Transfers'!F:F,"SET B",'Mortality and Transfers'!H:H) -> 82 | C52: =SUMIF('Mortality and Transfers'!F:F,"SET C",'Mortality and Transfers'!H:H) -> 39
A54: Weeks of Age - WOA
A55: SET A | B55: SET B | C55: SET C | D55: SET D | E55: Broilers
A56: =(TODAY()-Stock!F12)/7 -> 103.85714 | B56: =(TODAY()-Stock!F13)/7 -> 58.428571 | C56: =(TODAY()-Stock!F14)/7 -> 37.714286 | D56: =(TODAY()-Stock!F15)/7 -> 19.285714 | E56: =(TODAY()-Stock!F16)/7 -> 16.714286

Sheet MoM Summary
A1: Month | B1: Opening Balance | C1: Total Production | D1: Damaged | E1: Actual | F1: Total Eggs Sold | G1: Closing Balance | H1: Running Total | I1: Total Sales
A2: =TEXT(DATE(2025, ROW(A1), 1), "MMMM YYYY") -> January 2025 | B2: 0 | C2: =SUMIF(Production!L:L, A2, Production!J:J) -> 13491 | D2: =SUMIF(Production!L:L, A2, Production!E:E) -> 226 | E2: =SUMIF(Production!L:L, A2, Production!K:K) -> 13265 | F2: =SUMIF('Egg Sales'!H:H, A2, 'Egg Sales'!J:J) -> 13260 | G2: 5 | H2: =B2+C2 -> 13491 | I2: =SUMIF('Egg Sales'!H:H, A2, 'Egg Sales'!I:I) -> 23503
A3: =TEXT(DATE(2025, ROW(A2), 1), "MMMM YYYY") -> February 2025 | B3: =G2 -> 5 | C3: =SUMIF(Production!L:L, A3, Production!J:J) -> 11792 | D3: =SUMIF(Production!L:L, A3, Production!E:E) -> 167 | E3: =SUMIF(Production!L:L, A3, Production!K:K) -> 11625 | F3: =SUMIF('Egg Sales'!H:H, A3, 'Egg Sales'!J:J) -> 11610 | G3: =B3+E3-F3 -> 20 | H3: =B3+C3 -> 11797 | I3: =SUMIF('Egg Sales'!H:H, A3, 'Egg Sales'!I:I) -> 20687
A4: =TEXT(DATE(2025, ROW(A3), 1), "MMMM YYYY") -> March 2025 | B4: =G3 -> 20 | C4: =SUMIF(Production!L:L, A4, Production!J:J) -> 12333 | D4: =SUMIF(Production!L:L, A4, Production!E:E) -> 191 | E4: =SUMIF(Production!L:L, A4, Production!K:K) -> 12142 | F4: =SUMIF('Egg Sales'!H:H, A4, 'Egg Sales'!J:J) -> 11400 | G4: =B4+E4-F4 -> 762 | H4: =B4+C5 -> 11627 | I4: =SUMIF('Egg Sales'!H:H, A4, 'Egg Sales'!I:I) -> 20559
A5: =TEXT(DATE(2025, ROW(A4), 1), "MMMM YYYY") -> April 2025 | B5: =G4 -> 762 | C5: =SUMIF(Production!L:L, A5, Production!J:J) -> 11607 | D5: =SUMIF(Production!L:L, A5, Production!E:E) -> 197 | E5: =SUMIF(Production!L:L, A5, Production!K:K) -> 11410 | F5: =SUMIF('Egg Sales'!H:H, A5, 'Egg Sales'!J:J) -> 11340 | G5: =B5+E5-F5 -> 832 | H5: =B5+C5 -> 12369 | I5: =SUMIF('Egg Sales'!H:H, A5, 'Egg Sales'!I:I) -> 20555
A6: =TEXT(DATE(2025, ROW(A5), 1), "MMMM YYYY") -> May 2025 | B6: =G5 -> 832 | C6: =SUMIF(Production!L:L, A6, Production!J:J) -> 20419 | D6: =SUMIF(Production!L:L, A6, Production!E:E) -> 1271 | E6: =SUMIF(Production!L:L, A6, Production!K:K) -> 19148 | F6: =SUMIF('Egg Sales'!H:H, A6, 'Egg Sales'!J:J) -> 15990 | G6: =B6+E6-F6 -> 3990 | H6: =B6+C6 -> 21251 | I6: =SUMIF('Egg Sales'!H:H, A6, 'Egg Sales'!I:I) -> 27685
A7: =TEXT(DATE(2025, ROW(A6), 1), "MMMM YYYY") -> June 2025 | B7: =G6 -> 3990 | C7: =SUMIF(Production!L:L, A7, Production!J:J) -> 38028 | D7: =SUMIF(Production!L:L, A7, Production!E:E) -> 970 | E7: =SUMIF(Production!L:L, A7, Production!K:K) -> 37058 | F7: =SUMIF('Egg Sales'!H:H, A7, 'Egg Sales'!J:J) -> 36750 | G7: =(B7+E7)-F7-'PMT Summary'!C23 -> 4058 | H7: =B7+C7 -> 42018 | I7: =SUMIF('Egg Sales'!H:H, A7, 'Egg Sales'!I:I) -> 61456
A8: =TEXT(DATE(2025, ROW(A7), 1), "MMMM YYYY") -> July 2025 | B8: =G7 -> 4058 | C8: =SUMIF(Production!L:L, A8, Production!J:J) -> 37791 | D8: =SUMIF(Production!L:L, A8, Production!E:E) -> 637 | E8: =SUMIF(Production!L:L, A8, Production!K:K) -> 37154 | F8: =SUMIF('Egg Sales'!H:H, A8, 'Egg Sales'!J:J) -> 37590 | G8: =B8+E8-F8 -> 3622 | H8: =B8+C8 -> 41849 | I8: =SUMIF('Egg Sales'!H:H, A8, 'Egg Sales'!I:I) -> 66110
A9: =TEXT(DATE(2025, ROW(A8), 1), "MMMM YYYY") -> August 2025 | B9: =G8 -> 3622 | C9: =SUMIF(Production!L:L, A9, Production!J:J) -> 38340 | D9: =SUMIF(Production!L:L, A9, Production!E:E) -> 547 | E9: =SUMIF(Production!L:L, A9, Production!K:K) -> 37793 | F9: =SUMIF('Egg Sales'!H:H, A9, 'Egg Sales'!J:J) -> 29820 | G9: =B9+E9-F9 -> 11595 | H9: =B9+C9 -> 41962 | I9: =SUMIF('Egg Sales'!H:H, A9, 'Egg Sales'!I:I) -> 55280
A10: =TEXT(DATE(2025, ROW(A9), 1), "MMMM YYYY") -> September 2025 | B10: =G9 -> 11595 | C10: =SUMIF(Production!L:L, A10, Production!J:J) -> 33261 | D10: =SUMIF(Production!L:L, A10, Production!E:E) -> 516 | E10: =SUMIF(Production!L:L, A10, Production!K:K) -> 32745 | F10: =SUMIF('Egg Sales'!H:H, A10, 'Egg Sales'!J:J) -> 39000 | G10: =B10+E10-F10 -> 5340 | H10: =B10+C10 -> 44856 | I10: =SUMIF('Egg Sales'!H:H, A10, 'Egg Sales'!I:I) -> 70285
A11: =TEXT(DATE(2025, ROW(A10), 1), "MMMM YYYY") -> October 2025 | B11: =G10 -> 5340 | C11: =SUMIF(Production!L:L, A11, Production!J:J) -> 36746 | D11: =SUMIF(Production!L:L, A11, Production!E:E) -> 673 | E11: =SUMIF(Production!L:L, A11, Production!K:K) -> 36073 | F11: =SUMIF('Egg Sales'!H:H, A11, 'Egg Sales'!J:J) -> 37500 | G11: =B11+E11-F11 -> 3913 | H11: =B11+C11 -> 42086 | I11: =SUMIF('Egg Sales'!H:H, A11, 'Egg Sales'!I:I) -> 61332
A12: =TEXT(DATE(2025, ROW(A11), 1), "MMMM YYYY") -> November 2025 | B12: =G11 -> 3913 | C12: =SUMIF(Production!L:L, A12, Production!J:J) -> 38195 | D12: =SUMIF(Production!L:L, A12, Production!E:E) -> 654 | E12: =SUMIF(Production!L:L, A12, Production!K:K) -> 37541 | F12: =SUMIF('Egg Sales'!H:H, A12, 'Egg Sales'!J:J) -> 32160 | G12: =B12+E12-F12 -> 9294 | H12: =B12+C12 -> 42108 | I12: =SUMIF('Egg Sales'!H:H, A12, 'Egg Sales'!I:I) -> 53541
A13: =TEXT(DATE(2025, ROW(A12), 1), "MMMM YYYY") -> December 2025 | B13: =G12 -> 9294 | C13: =SUMIF(Production!L:L, A13, Production!J:J) -> 33909 | D13: =SUMIF(Production!L:L, A13, Production!E:E) -> 728 | E13: =SUMIF(Production!L:L, A13, Production!K:K) -> 33181 | F13: =SUMIF('Egg Sales'!H:H, A13, 'Egg Sales'!J:J) -> 40470 | G13: =B13+E13-F13 -> 2005 | H13: =B13+C13 -> 43203 | I13: =SUMIF('Egg Sales'!H:H, A13, 'Egg Sales'!I:I) -> 66410
A14: =TEXT(DATE(2025, ROW(A13), 1), "MMMM YYYY") -> January 2026 | B14: =G13 -> 2005 | C14: =SUMIF(Production!L:L, A14, Production!J:J) -> 25311 | D14: =SUMIF(Production!L:L, A14, Production!E:E) -> 744 | E14: =SUMIF(Production!L:L, A14, Production!K:K) -> 24567 | F14: =SUMIF('Egg Sales'!H:H, A14, 'Egg Sales'!J:J) -> 25080 | G14: =B14+E14-F14 -> 1492 | H14: =B14+C14 -> 27316 | I14: =SUMIF('Egg Sales'!H:H, A14, 'Egg Sales'!I:I) -> 40940
A15: =TEXT(DATE(2025, ROW(A14), 1), "MMMM YYYY") -> February 2026 | B15: =G14 -> 1492 | C15: =SUMIF(Production!L:L, A15, Production!J:J) -> 864 | D15: =SUMIF(Production!L:L, A15, Production!E:E) -> 27 | E15: =SUMIF(Production!L:L, A15, Production!K:K) -> 837 | F15: =SUMIF('Egg Sales'!H:H, A15, 'Egg Sales'!J:J) -> 9450 | G15: =B15+E15-F15 -> -7121 | H15: =B15+C15 -> 2356 | I15: =SUMIF('Egg Sales'!H:H, A15, 'Egg Sales'!I:I) -> 15750
A16: =TEXT(DATE(2025, ROW(A15), 1), "MMMM YYYY") -> March 2026 | B16: =G15 -> -7121 | C16: =SUMIF(Production!L:L, A16, Production!J:J) -> 0 | D16: =SUMIF(Production!L:L, A16, Production!E:E) -> 0 | E16: =SUMIF(Production!L:L, A16, Production!K:K) -> 0 | F16: =SUMIF('Egg Sales'!H:H, A16, 'Egg Sales'!J:J) -> 0 | G16: =B16+E16-F16 -> -7121 | H16: =B16+C16 -> -7121 | I16: =SUMIF('Egg Sales'!H:H, A16, 'Egg Sales'!I:I) -> 0
A17: =TEXT(DATE(2025, ROW(A16), 1), "MMMM YYYY") -> April 2026 | B17: =G16 -> -7121 | C17: =SUMIF(Production!L:L, A17, Production!J:J) -> 0 | D17: =SUMIF(Production!L:L, A17, Production!E:E) -> 0 | E17: =SUMIF(Production!L:L, A17, Production!K:K) -> 0 | F17: =SUMIF('Egg Sales'!H:H, A17, 'Egg Sales'!J:J) -> 0 | G17: =B17+E17-F17 -> -7121 | H17: =B17+C17 -> -7121 | I17: =SUMIF('Egg Sales'!H:H, A17, 'Egg Sales'!I:I) -> 0
A18: =TEXT(DATE(2025, ROW(A17), 1), "MMMM YYYY") -> May 2026 | B18: =G17 -> -7121 | C18: =SUMIF(Production!L:L, A18, Production!J:J) -> 0 | D18: =SUMIF(Production!L:L, A18, Production!E:E) -> 0 | E18: =SUMIF(Production!L:L, A18, Production!K:K) -> 0 | F18: =SUMIF('Egg Sales'!H:H, A18, 'Egg Sales'!J:J) -> 0 | G18: =B18+E18-F18 -> -7121 | H18: =B18+C18 -> -7121 | I18: =SUMIF('Egg Sales'!H:H, A18, 'Egg Sales'!I:I) -> 0
A19: =TEXT(DATE(2025, ROW(A18), 1), "MMMM YYYY") -> June 2026 | B19: =G18 -> -7121 | C19: =SUMIF(Production!L:L, A19, Production!J:J) -> 0 | D19: =SUMIF(Production!L:L, A19, Production!E:E) -> 0 | E19: =SUMIF(Production!L:L, A19, Production!K:K) -> 0 | F19: =SUMIF('Egg Sales'!H:H, A19, 'Egg Sales'!J:J) -> 0 | G19: =B19+E19-F19 -> -7121 | H19: =B19+C19 -> -7121 | I19: =SUMIF('Egg Sales'!H:H, A19, 'Egg Sales'!I:I) -> 0
... A25: =TEXT(DATE(2025, ROW(A24), 1), "MMMM YYYY") -> December 2026 | B25: =G24 -> -7121 | C25: =SUMIF(Production!L:L, A25, Production!J:J) -> 0 | D25: =SUMIF(Production!L:L, A25, Production!E:E) -> 0 | E25: =SUMIF(Production!L:L, A25, Production!K:K) -> 0 | F25: =SUMIF('Egg Sales'!H:H, A25, 'Egg Sales'!J:J) -> 0 | G25: =B25+E25-F25 -> -7121 | H25: =B25+C25 -> -7121 | I25: =SUMIF('Egg Sales'!H:H, A25, 'Egg Sales'!I:I) -> 0
A26: =TEXT(DATE(2025, ROW(A25), 1), "MMMM YYYY") -> January 2027 | B26: =G25 -> -7121
A29: Month | B29: Opening Balance | C29: Total Production | D29: Damaged | E29: Actual | F29: Total Eggs Sold | G29: Closing Balance | H29: Running Total | I29: Total Sales
A30: =TEXT(DATE(2026, ROW(A1), 1), "MMMM") -> January
A31: =TEXT(DATE(2026, ROW(A2), 1), "MMMM") -> February
A32: =TEXT(DATE(2026, ROW(A3), 1), "MMMM") -> March
A33: =TEXT(DATE(2026, ROW(A4), 1), "MMMM") -> April
A34: =TEXT(DATE(2026, ROW(A5), 1), "MMMM") -> May
A35: =TEXT(DATE(2026, ROW(A6), 1), "MMMM") -> June
A36: =TEXT(DATE(2026, ROW(A7), 1), "MMMM") -> July
A37: =TEXT(DATE(2026, ROW(A8), 1), "MMMM") -> August
A38: =TEXT(DATE(2026, ROW(A9), 1), "MMMM") -> September

Sheet Copy of MoM Summary
A1: Month | B1: Opening Balance | C1: Total Production | D1: Damaged | E1: Actual | F1: Total Eggs Sold | G1: Closing Balance | H1: Running Total | I1: Total Sales
A2: =TEXT(DATE(2025, ROW(A1), 1), "MMMM") -> January | B2: 0 | C2: =SUMIF(Production!L:L, A2, Production!J:J) -> 0 | D2: =SUMIF(Production!L:L, A2, Production!E:E) -> 0 | E2: =SUMIF(Production!L:L, A2, Production!K:K) -> 0 | F2: =SUMIF('Egg Sales'!H:H, A2, 'Egg Sales'!J:J) -> 0 | G2: 5 | H2: =B2+C2 -> 0 | I2: =SUMIF('Egg Sales'!H:H, A2, 'Egg Sales'!I:I) -> 0
A3: =TEXT(DATE(2025, ROW(A2), 1), "MMMM") -> February | B3: =G2 -> 5 | C3: =SUMIF(Production!L:L, A3, Production!J:J) -> 0 | D3: =SUMIF(Production!L:L, A3, Production!E:E) -> 0 | E3: =SUMIF(Production!L:L, A3, Production!K:K) -> 0 | F3: =SUMIF('Egg Sales'!H:H, A3, 'Egg Sales'!J:J) -> 0 | G3: =B3+E3-F3 -> 5 | H3: =B3+C3 -> 5 | I3: =SUMIF('Egg Sales'!H:H, A3, 'Egg Sales'!I:I) -> 0
A4: =TEXT(DATE(2025, ROW(A3), 1), "MMMM") -> March | B4: =G3 -> 5 | C4: =SUMIF(Production!L:L, A4, Production!J:J) -> 0 | D4: =SUMIF(Production!L:L, A4, Production!E:E) -> 0 | E4: =SUMIF(Production!L:L, A4, Production!K:K) -> 0 | F4: =SUMIF('Egg Sales'!H:H, A4, 'Egg Sales'!J:J) -> 0 | G4: =B4+E4-F4 -> 5 | H4: =B4+C5 -> 5 | I4: =SUMIF('Egg Sales'!H:H, A4, 'Egg Sales'!I:I) -> 0
A5: =TEXT(DATE(2025, ROW(A4), 1), "MMMM") -> April | B5: =G4 -> 5 | C5: =SUMIF(Production!L:L, A5, Production!J:J) -> 0 | D5: =SUMIF(Production!L:L, A5, Production!E:E) -> 0 | E5: =SUMIF(Production!L:L, A5, Production!K:K) -> 0 | F5: =SUMIF('Egg Sales'!H:H, A5, 'Egg Sales'!J:J) -> 0 | G5: =B5+E5-F5 -> 5 | H5: =B5+C5 -> 5 | I5: =SUMIF('Egg Sales'!H:H, A5, 'Egg Sales'!I:I) -> 0
A6: =TEXT(DATE(2025, ROW(A5), 1), "MMMM") -> May | B6: =G5 -> 5 | C6: =SUMIF(Production!L:L, A6, Production!J:J) -> 0 | D6: =SUMIF(Production!L:L, A6, Production!E:E) -> 0 | E6: =SUMIF(Production!L:L, A6, Production!K:K) -> 0 | F6: =SUMIF('Egg Sales'!H:H, A6, 'Egg Sales'!J:J) -> 0 | G6: =B6+E6-F6 -> 5 | H6: =B6+C6 -> 5 | I6: =SUMIF('Egg Sales'!H:H, A6, 'Egg Sales'!I:I) -> 0
A7: =TEXT(DATE(2025, ROW(A6), 1), "MMMM") -> June | B7: =G6 -> 5 | C7: =SUMIF(Production!L:L, A7, Production!J:J) -> 0 | D7: =SUMIF(Production!L:L, A7, Production!E:E) -> 0 | E7: =SUMIF(Production!L:L, A7, Production!K:K) -> 0 | F7: =SUMIF('Egg Sales'!H:H, A7, 'Egg Sales'!J:J) -> 0 | G7: =(B7+E7)-F7-'PMT Summary'!C23 -> -235 | H7: =B7+C7 -> 5 | I7: =SUMIF('Egg Sales'!H:H, A7, 'Egg Sales'!I:I) -> 0
A8: =TEXT(DATE(2025, ROW(A7), 1), "MMMM") -> July | B8: =G7 -> -235 | C8: =SUMIF(Production!L:L, A8, Production!J:J) -> 0 | D8: =SUMIF(Production!L:L, A8, Production!E:E) -> 0 | E8: =SUMIF(Production!L:L, A8, Production!K:K) -> 0 | F8: =SUMIF('Egg Sales'!H:H, A8, 'Egg Sales'!J:J) -> 0 | G8: =B8+E8-F8 -> -235 | H8: =B8+C8 -> -235 | I8: =SUMIF('Egg Sales'!H:H, A8, 'Egg Sales'!I:I) -> 0
A9: =TEXT(DATE(2025, ROW(A8), 1), "MMMM") -> August | B9: =G8 -> -235 | C9: =SUMIF(Production!L:L, A9, Production!J:J) -> 0 | D9: =SUMIF(Production!L:L, A9, Production!E:E) -> 0 | E9: =SUMIF(Production!L:L, A9, Production!K:K) -> 0 | F9: =SUMIF('Egg Sales'!H:H, A9, 'Egg Sales'!J:J) -> 0 | G9: =B9+E9-F9 -> -235 | H9: =B9+C9 -> -235 | I9: =SUMIF('Egg Sales'!H:H, A9, 'Egg Sales'!I:I) -> 0
A10: =TEXT(DATE(2025, ROW(A9), 1), "MMMM") -> September | B10: =G9 -> -235 | C10: =SUMIF(Production!L:L, A10, Production!J:J) -> 0 | D10: =SUMIF(Production!L:L, A10, Production!E:E) -> 0 | E10: =SUMIF(Production!L:L, A10, Production!K:K) -> 0 | F10: =SUMIF('Egg Sales'!H:H, A10, 'Egg Sales'!J:J) -> 0 | G10: =B10+E10-F10 -> -235 | H10: =B10+C10 -> -235 | I10: =SUMIF('Egg Sales'!H:H, A10, 'Egg Sales'!I:I) -> 0
A11: =TEXT(DATE(2025, ROW(A10), 1), "MMMM") -> October | B11: =G10 -> -235 | C11: =SUMIF(Production!L:L, A11, Production!J:J) -> 0 | D11: =SUMIF(Production!L:L, A11, Production!E:E) -> 0 | E11: =SUMIF(Production!L:L, A11, Production!K:K) -> 0 | F11: =SUMIF('Egg Sales'!H:H, A11, 'Egg Sales'!J:J) -> 0 | G11: =B11+E11-F11 -> -235 | H11: =B11+C11 -> -235 | I11: =SUMIF('Egg Sales'!H:H, A11, 'Egg Sales'!I:I) -> 0
A12: =TEXT(DATE(2025, ROW(A11), 1), "MMMM") -> November | B12: =G11 -> -235 | C12: =SUMIF(Production!L:L, A12, Production!J:J) -> 0 | D12: =SUMIF(Production!L:L, A12, Production!E:E) -> 0 | E12: =SUMIF(Production!L:L, A12, Production!K:K) -> 0 | F12: =SUMIF('Egg Sales'!H:H, A12, 'Egg Sales'!J:J) -> 0 | G12: =B12+E12-F12 -> -235 | H12: =B12+C12 -> -235 | I12: =SUMIF('Egg Sales'!H:H, A12, 'Egg Sales'!I:I) -> 0
A13: =TEXT(DATE(2025, ROW(A12), 1), "MMMM") -> December | B13: =G12 -> -235 | C13: =SUMIF(Production!L:L, A13, Production!J:J) -> 0 | D13: =SUMIF(Production!L:L, A13, Production!E:E) -> 0 | E13: =SUMIF(Production!L:L, A13, Production!K:K) -> 0 | F13: =SUMIF('Egg Sales'!H:H, A13, 'Egg Sales'!J:J) -> 0 | G13: =B13+E13-F13 -> -235 | H13: =B13+C13 -> -235 | I13: =SUMIF('Egg Sales'!H:H, A13, 'Egg Sales'!I:I) -> 0
A16: Month | B16: Opening Balance | C16: Total Production | D16: Damaged | E16: Actual | F16: Total Eggs Sold | G16: Closing Balance | H16: Running Total | I16: Total Sales
B17: 0

Sheet Sheet1
A1: 1. Sales Dashboard (Executive View)
A3: Data source: Egg Sales sheet
A5: Pivot Tables
A7: Total Sales by Month
A9: Sales by Product
A11: Sales by Customer
A13: Quantity Sold by Date
A15: 7 KPIs (top row, card-style)
A17: Total Sales
A19: Total Quantity Sold
A21: Average Selling Price
A23: Top Product
... A53: Expenses by Date
A55: Budget vs Actual (where applicable) | D55: Month | E55: (All)
A57: 7 KPIs | D57: Sum of Amount Paid | E57: Column Labels
D58: Row Labels | E58: 2026 | F58: Grand Total
A59: Total Revenue | D59: Jan | E59: 40940 | F59: 40940
D60: Feb | E60: 15750 | F60: 15750
A61: Total Expenses | D61: Grand Total | E61: 56690 | F61: 56690
A63: Net Balance
A65: Imprest Utilization Rate
A67: Budget Variance
A69: Cash Remaining
A71: Expense Growth Rate
A73: Charts
A75: Line chart: Expense trend over time
D76: Sum of Amount Paid | E76: Column Labels
A77: Column chart: Expenses by category | D77: Row Labels | E77: 2026 | F77: Grand Total
D78: Jan | E78: 99054 | F78: 99054
A79: Column chart: Budget vs Actual | D79: Feb | E79: 62420 | F79: 62420
D80: Grand Total | E80: 161474 | F80: 161474
A81: Interactivity
A83: Timeline for Date
A85: Slicers for Expense Category and Period
A87: Executive Design Standards I’ll apply
A89: Clean layout with KPIs at the top
A91: Neutral, professional color palette
A93: Clear titles and data labels
A95: No clutter, optimized for senior management review
A97: One-screen view per dashboard where possible
A99: Once you say “go ahead” or resend the file if needed, I’ll fully wire:
A101: Pivot tables
A103: KPI formulas
... A107: Slicers and timelines

Sheet Sales Dashboard
B1: SALES DASHBOARD

Sheet MOM Expenses
A3: Sum of Amount Paid | B3: Column Labels
A4: Row Labels | B4: 2026 | C4: Grand Total
A5: Jan | B5: 99054 | C5: 99054
A6: Feb | B6: 62420 | C6: 62420
A7: Grand Total | B7: 161474 | C7: 161474
A25: total expenses | B25: =GETPIVOTDATA("Amount Paid",$A$3) -> 161474

Sheet Expense by Setcategory
A4: Sum of Amount Paid | B4: Column Labels
A5: Row Labels | B5: Health & Nutrition | C5: Labor | D5: Marketing & Distribution | E5: (blank) | F5: Grand Total
A6: Layers - SET 4 | B6: 56190 | C6: 450 | F6: 56640
A7: General Admin | E7: 29841 | F7: 29841
A8: Layers - SET 2 | B8: 25870 | F8: 25870
A9: Construction | E9: 20314 | F9: 20314
A10: Layers - SET 3 | B10: 19113 | F10: 19113
A11: Layers - SET 1 | B11: 7696 | F11: 7696
A12: Broiler - Set B | D12: 2000 | F12: 2000
A13: Grand Total | B13: 108869 | C13: 450 | D13: 2000 | E13: 50155 | F13: 161474
A18: Sum of Amount Paid | B18: Column Labels
A19: Row Labels | B19: Layers - SET 4 | C19: General Admin | D19: Layers - SET 2 | E19: Construction | F19: Layers - SET 3 | G19: Layers - SET 1 | H19: Broiler - Set B | I19: Grand Total
A20: Health & Nutrition | B20: 56190 | D20: 25870 | F20: 19113 | G20: 7696 | I20: 108869
A21: Labor | B21: 450 | I21: 450
A22: Marketing & Distribution | H22: 2000 | I22: 2000
A23: (blank) | C23: 29841 | E23: 20314 | I23: 50155
A24: Grand Total | B24: 56640 | C24: 29841 | D24: 25870 | E24: 20314 | F24: 19113 | G24: 7696 | H24: 2000 | I24: 161474

Sheet Expense by Gencategory
A4: Sum of Amount Paid | B4: Column Labels
A5: Row Labels | B5: 2026 | C5: Grand Total
A6: Assets | B6: 2665 | C6: 2665
A7: Financial & Overheads | B7: 550 | C7: 550
A8: Health & Nutrition | B8: 2498 | C8: 2498
A9: Labor & Staffing | B9: 6200 | C9: 6200
A10: Maintenance & Equipment | B10: 14700 | C10: 14700
A11: Utilities & Operations | B11: 3228 | C11: 3228
A12: Construction | B12: 11603 | C12: 11603
A13: Grand Total | B13: 41444 | C13: 41444

Sheet Accountable Imprest 
A1: Timestamp | B1: Item name/Service Description | C1: Service/item category | D1: Select Set Categories | E1: Select General Category | F1: Select Project | G1: Health & Nutrition | H1: Marketing & Distribution | I1: Assets | J1: Labor | K1: Utilities & Operations | L1: Quantity | M1: Unit Price | N1: Amount Paid | O1: TOTAL(AUTO) | P1: Transaction Date | Q1: Select Category | R1: Maintenance & Equipment | S1: Labor & Staffing | T1: Financial & Overheads | U1: Column 3 | V1: Column 7 | W1: Column 2
A2: 46065.21 | B2: D4+ Disinfectant 1L | C2: General Admin | E2: Health & Nutrition | G2: Biosecurity | L2: 1 | M2: 195 | N2: 195 | O2: 195 | P2: 46328 | U2: 46054 | W2: TRUE
A3: 46065.21 | B3: Aliseryl WS 1kg | C3: General Admin | E3: Health & Nutrition | G3: Biosecurity | L3: 1 | M3: 438 | N3: 438 | O3: 438 | P3: 46328 | U3: 46054 | W3: TRUE
A4: 46065.21 | B4: Koudijs Pre-Layer Mash | C4: Layers - SET 4 | D4: Health & Nutrition | G4: Feed purchase | L4: 10 | M4: 370 | N4: 3700 | O4: 3700 | P4: 46328 | U4: 46054 | W4: TRUE
A5: 46065.21 | B5: Koudijs Layer 1 Mash | C5: Layers - SET 3 | D5: Health & Nutrition | G5: Feed purchase | L5: 4 | M5: 392 | N5: 1568 | O5: 1568 | P5: 46328 | U5: 46054 | W5: TRUE
A6: 46065.21 | B6: Koudijs Layer 1 Mash | C6: Layers - SET 2 | D6: Health & Nutrition | G6: Feed purchase | L6: 5 | M6: 392 | N6: 1960 | O6: 1960 | P6: 46328 | U6: 46054 | W6: TRUE
A7: 46065.21 | B7: Koudijs Layer 2 Mash | C7: Layers - SET 1 | D7: Health & Nutrition | G7: Feed purchase | L7: 2 | M7: 385 | N7: 770 | O7: 770 | P7: 46328 | U7: 46054 | W7: TRUE
A8: 46064.041 | B8: Ropes for hanging feeders | C8: Construction | L8: 2 | M8: 550 | N8: 1100 | O8: 1100 | P8: 46297 | U8: 46054 | W8: TRUE
A9: 46062.078 | B9: Interplast 3/4" Pipe | C9: Construction | L9: 3 | M9: 42 | N9: 126 | O9: 126 | P9: 46267 | U9: 46054 | W9: TRUE
A10: 46062.078 | B10: Ball Valve | C10: Construction | L10: 1 | M10: 60 | N10: 60 | O10: 60 | P10: 46267 | U10: 46054 | W10: TRUE
A11: 46062.078 | B11: Koudijs Pre-Layer Mash | C11: Layers - SET 4 | D11: Health & Nutrition | G11: Feed purchase | L11: 11 | M11: 370 | N11: 4070 | O11: 4070 | P11: 46205 | U11: 46054 | W11: TRUE
A12: 46062.078 | B12: Koudijs Layer 1 Mash | C12: Layers - SET 3 | D12: Health & Nutrition | G12: Feed purchase | L12: 2 | M12: 392 | N12: 784 | O12: 784 | P12: 46205 | U12: 46054 | W12: TRUE
A13: 46062.078 | B13: Koudijs Layer 1 Mash | C13: Layers - SET 2 | D13: Health & Nutrition | G13: Feed purchase | L13: 5 | M13: 392 | N13: 1960 | O13: 1960 | P13: 46205 | U13: 46054 | W13: TRUE
A14: 46062.078 | B14: Koudijs Layer 1 Mash | C14: Layers - SET 1 | D14: Health & Nutrition | G14: Feed purchase | L14: 1 | M14: 392 | N14: 392 | O14: 392 | P14: 46205 | U14: 46054 | W14: TRUE
A15: 46062.078 | B15: Plumber - Part Labor | C15: Construction | L15: 1 | M15: 1000 | N15: 1000 | O15: 1000 | P15: 46205 | U15: 46054 | W15: TRUE
A16: 46062.078 | B16: Plumbing Fittings | C16: Construction | L16: 1 | M16: 780 | N16: 780 | O16: 780 | P16: 46205 | U16: 46054 | W16: TRUE
A17: 46062.078 | B17: New Tank Stand/ Welder's Labor | C17: Construction | L17: 1 | M17: 600 | N17: 600 | O17: 600 | P17: 46205 | U17: 46054 | W17: TRUE
A18: 46062.078 | B18: Carpenter - Labor | C18: Construction | L18: 1 | M18: 800 | N18: 800 | O18: 800 | P18: 46205 | U18: 46054 | W18: TRUE
A19: 46061.081 | B19: Filling - Labor | C19: Construction | L19: 1 | M19: 1000 | N19: 1000 | O19: 1000 | P19: 46205 | U19: 46054 | W19: TRUE
A20: 46060.081 | B20: Sawdust | C20: General Admin | E20: Utilities & Operations | K20: Sawdust | L20: 1 | M20: 200 | N20: 200 | O20: 200 | P20: 46205 | U20: 46054 | W20: TRUE
A21: 46060.081 | B21: Glue | C21: Construction | L21: 1 | M21: 40 | N21: 40 | O21: 40 | P21: 46205 | U21: 46054 | W21: TRUE
A22: 46060.081 | B22: Hinges | C22: Construction | L22: 15 | M22: 3 | N22: 45 | O22: 45 | P22: 46175 | U22: 46054 | W22: TRUE
A23: 46060.081 | B23: Nails | C23: Construction | L23: 1 | M23: 60 | N23: 60 | O23: 60 | P23: 46175 | U23: 46054 | W23: TRUE
A24: 46060.081 | B24: Wood 2x2 | C24: Construction | L24: 4 | M24: 40 | N24: 160 | O24: 160 | P24: 46175 | U24: 46054 | W24: TRUE
A25: 46060.081 | B25: Wood 2x3 | C25: Construction | L25: 15 | M25: 60 | N25: 900 | O25: 900 | P25: 46175 | U25: 46054 | W25: TRUE
A26: 46060.081 | B26: Board | C26: Construction | L26: 3 | M26: 230 | N26: 690 | O26: 690 | P26: 46175 | U26: 46054 | W26: TRUE
A27: 46060.081 | B27: Poly Tank (400 litres) | C27: Construction | L27: 1 | M27: 750 | N27: 750 | O27: 750 | P27: 46175 | U27: 46054 | W27: TRUE
A28: 46060.081 | B28: Blue Drum | C28: Construction | L28: 1 | M28: 600 | N28: 600 | O28: 600 | P28: 46175 | U28: 46054 | W28: TRUE
A29: 46057.081 | B29: Koudijs Pre-Layer Mash | C29: Layers - SET 4 | D29: Health & Nutrition | G29: Feed purchase | L29: 10 | M29: 370 | N29: 3700 | O29: 3700 | P29: 46114 | U29: 46054 | W29: TRUE
A30: 46057.081 | B30: Koudijs Layer 1 Mash | C30: Layers - SET 3 | D30: Health & Nutrition | G30: Feed purchase | L30: 5 | M30: 392 | N30: 1960 | O30: 1960 | P30: 46114 | U30: 46054 | W30: TRUE
A31: 46057.081 | B31: Koudijs Layer 1 Mash | C31: Layers - SET 2 | D31: Health & Nutrition | G31: Feed purchase | L31: 4 | M31: 392 | N31: 1568 | O31: 1568 | P31: 46114 | U31: 46054 | W31: TRUE
A32: 46057.081 | B32: Koudijs Layer 1 Mash | C32: Layers - SET 1 | D32: Health & Nutrition | G32: Feed purchase | L32: 1 | M32: 392 | N32: 392 | O32: 392 | P32: 46114 | U32: 46054 | W32: TRUE
A33: 46056.081 | B33: Tei-Fuel for Farm Rounds | C33: General Admin | E33: Utilities & Operations | K33: Fuel/Lubricants | L33: 1 | M33: 1200 | N33: 1200 | O33: 1200 | P33: 46083 | U33: 46054 | W33: TRUE
A34: 46056.081 | B34: Tei-Salary for January | C34: General Admin | E34: Labor & Staffing | L34: 1 | M34: 4000 | N34: 4000 | O34: 4000 | P34: 46083 | S34: Salaries | U34: 46054 | W34: TRUE
A35: 46056.081 | B35: Delivery for Nipples and pipelines | C35: General Admin | E35: Utilities & Operations | K35: Transportation | L35: 1 | M35: 90 | N35: 90 | O35: 90 | P35: 46083 | U35: 46054 | W35: TRUE
A36: 46056.081 | B36: End Cups | C36: General Admin | E36: Assets | I36: Drinkers | L36: 10 | M36: 3 | N36: 30 | O36: 30 | P36: 46083 | U36: 46054 | W36: TRUE
A37: 46056.081 | B37: Straight Joints for Pipes | C37: General Admin | E37: Assets | I37: Drinkers | L37: 20 | M37: 3 | N37: 60 | O37: 60 | P37: 46083 | U37: 46054 | W37: TRUE
A38: 46056.081 | B38: PVC Pipes with nipple holes | C38: General Admin | E38: Assets | I38: Drinkers | L38: 30 | M38: 26 | N38: 780 | O38: 780 | P38: 46083 | U38: 46054 | W38: TRUE
A39: 46056.081 | B39: Nipples with cups | C39: General Admin | E39: Assets | I39: Drinkers | L39: 150 | M39: 6 | N39: 900 | O39: 900 | P39: 46083 | U39: 46054 | W39: TRUE
A40: 46056.081 | B40: Fuel for Tricycle | C40: General Admin | E40: Utilities & Operations | K40: Fuel/Lubricants | L40: 1 | M40: 160 | N40: 160 | O40: 160 | P40: 30/01/2026 | U40: 46054 | W40: TRUE
A41: 46056.081 | B41: Wheel Barrow | C41: General Admin | E41: Assets | I41: Wheel Barrow | L41: 1 | M41: 620 | N41: 620 | O41: 620 | P41: 46055 | U41: 46054 | W41: TRUE
A42: 46056.079 | B42: Prepaid | C42: General Admin | E42: Utilities & Operations | K42: Electricity | L42: 1 | M42: 500 | N42: 500 | O42: 500 | P42: 30/01/2026 | U42: 46054 | W42: TRUE
A43: 46055.741 | B43: Toyota Hilux (GE-8785-20) Repairs | C43: General Admin | E43: Maintenance & Equipment | L43: 1 | M43: 13950 | N43: 13950 | O43: 13950 | P43: 46024 | R43: Repairs/Maintenance | U43: 46054 | W43: TRUE
A44: 46054.47 | B44: Koudijs Developer Mash | C44: Layers - SET 4 | D44: Health & Nutrition | G44: Feed purchase | L44: 13 | M44: 386 | N44: 5018 | O44: =L44*M44 -> 5018 | P44: 46053 | U44: =TEXT(A44, "MMMM YYYY") -> February 2026 | W44: =IF(N44=O44,TRUE,FALSE) -> TRUE
A45: 46054.466 | B45: Koudijs Layer 1 Mash | C45: Layers - SET 3 | D45: Health & Nutrition | G45: Feed purchase | L45: 4 | M45: 392 | N45: 1568 | O45: =L45*M45 -> 1568 | P45: 46053 | U45: =TEXT(A45, "MMMM YYYY") -> February 2026 | W45: =IF(N45=O45,TRUE,FALSE) -> TRUE
A46: 46054.465 | B46: Koudijs Layer 1 Mash | C46: Layers - SET 2 | D46: Health & Nutrition | G46: Feed purchase | L46: 2 | M46: 392 | N46: 784 | O46: =L46*M46 -> 784 | P46: 46053 | U46: =TEXT(A46, "MMMM YYYY") -> February 2026 | W46: =IF(N46=O46,TRUE,FALSE) -> TRUE
A47: 46054.46 | B47: Koudijs Layer 1 Mash | C47: Layers - SET 1 | D47: Health & Nutrition | G47: Feed purchase | L47: 1 | M47: 392 | N47: 392 | O47: =L47*M47 -> 392 | P47: 46053 | U47: =TEXT(A47, "MMMM YYYY") -> February 2026 | W47: =IF(N47=O47,TRUE,FALSE) -> TRUE
A48: 46052.514 | B48: Sawdust | C48: General Admin | E48: Utilities & Operations | K48: Sawdust | L48: 1 | M48: 80 | N48: 80 | O48: =L48*M48 -> 80 | P48: 46052 | U48: =TEXT(A48, "MMMM YYYY") -> January 2026 | W48: =IF(N48=O48,TRUE,FALSE) -> TRUE
A49: 46052.511 | B49: Sawdust | C49: General Admin | E49: Utilities & Operations | K49: Sawdust | L49: 1 | M49: 85 | N49: 85 | O49: =L49*M49 -> 85 | P49: 46050 | U49: =TEXT(A49, "MMMM YYYY") -> January 2026 | W49: =IF(N49=O49,TRUE,FALSE) -> TRUE
A50: 46052.509 | B50: Sawdust | C50: General Admin | E50: Utilities & Operations | K50: Sawdust | L50: 1 | M50: 100 | N50: 100 | O50: =L50*M50 -> 100 | P50: 46042 | U50: =TEXT(A50, "MMMM YYYY") -> January 2026 | W50: =IF(N50=O50,TRUE,FALSE) -> TRUE
A51: 46052.354 | B51: Vanessa - Salary for January | C51: General Admin | E51: Labor & Staffing | L51: 1 | M51: 600 | N51: 600 | O51: =L51*M51 -> 600 | P51: 46052 | S51: Salaries | U51: =TEXT(A51, "MMMM YYYY") -> January 2026 | W51: =IF(N51=O51,TRUE,FALSE) -> TRUE
A52: 46052.353 | B52: Okunka - Salary for January | C52: General Admin | E52: Labor & Staffing | L52: 1 | M52: 800 | N52: 800 | O52: =L52*M52 -> 800 | P52: 46052 | S52: Salaries | U52: =TEXT(A52, "MMMM YYYY") -> January 2026 | W52: =IF(N52=O52,TRUE,FALSE) -> TRUE
A53: 46052.353 | B53: Osabu - Salary for January | C53: General Admin | E53: Labor & Staffing | L53: 1 | M53: 800 | N53: 800 | O53: =L53*M53 -> 800 | P53: 46052 | S53: Salaries | U53: =TEXT(A53, "MMMM YYYY") -> January 2026 | W53: =IF(N53=O53,TRUE,FALSE) -> TRUE
A54: 46052.347 | B54: Sand for filling | C54: Construction | E54: Construction | L54: 1 | M54: 1700 | N54: 1700 | O54: =L54*M54 -> 1700 | P54: 46052 | U54: =TEXT(A54, "MMMM YYYY") -> January 2026 | W54: =IF(N54=O54,TRUE,FALSE) -> TRUE
A55: 46052.336 | B55: Welder - Tank Platform | C55: Construction | E55: Construction | L55: 1 | M55: 1500 | N55: 1500 | O55: =L55*M55 -> 1500 | P55: 46052 | U55: =TEXT(A55, "MMMM YYYY") -> January 2026 | W55: =IF(N55=O55,TRUE,FALSE) -> TRUE
A56: 46052.335 | B56: Lasota Vaccine | C56: Layers - SET 3 | D56: Health & Nutrition | G56: Vaccines | L56: 1 | M56: 70 | N56: 70 | O56: =L56*M56 -> 70 | P56: 46052 | U56: =TEXT(A56, "MMMM YYYY") -> January 2026 | W56: =IF(N56=O56,TRUE,FALSE) -> TRUE
A57: 46052.334 | B57: Lasota Vaccine | C57: Layers - SET 2 | D57: Health & Nutrition | G57: Vaccines | L57: 1 | M57: 95 | N57: 95 | O57: =L57*M57 -> 95 | P57: 46052 | U57: =TEXT(A57, "MMMM YYYY") -> January 2026 | W57: =IF(N57=O57,TRUE,FALSE) -> TRUE
A58: 46052.331 | B58: Lasota Vaccine | C58: Layers - SET 1 | D58: Health & Nutrition | G58: Vaccines | L58: 1 | M58: 45 | N58: 45 | O58: =L58*M58 -> 45 | P58: 46052 | U58: =TEXT(A58, "MMMM YYYY") -> January 2026 | W58: =IF(N58=O58,TRUE,FALSE) -> TRUE
A59: 46051.446 | B59: Plumber - Labor for Laying all drainage pipes | C59: Construction | E59: Construction | L59: 1 | M59: 500 | N59: 500 | O59: =L59*M59 -> 500 | P59: 46051 | U59: =TEXT(A59, "MMMM YYYY") -> January 2026 | W59: =IF(N59=O59,TRUE,FALSE) -> TRUE
A60: 46051.445 | B60: Elbow 2" | C60: Construction | E60: Construction | L60: 4 | M60: 8 | N60: 32 | O60: =L60*M60 -> 32 | P60: 46051 | U60: =TEXT(A60, "MMMM YYYY") -> January 2026 | W60: =IF(N60=O60,TRUE,FALSE) -> TRUE
A61: 46051.444 | B61: Interplast Pipe 2" | C61: Construction | E61: Construction | L61: 1 | M61: 70 | N61: 70 | O61: =L61*M61 -> 70 | P61: 46051 | U61: =TEXT(A61, "MMMM YYYY") -> January 2026 | W61: =IF(N61=O61,TRUE,FALSE) -> TRUE
A62: 46051.443 | B62: Reducer 3x2" | C62: Construction | E62: Construction | L62: 5 | M62: 15 | N62: 75 | O62: =L62*M62 -> 75 | P62: 46051 | U62: =TEXT(A62, "MMMM YYYY") -> January 2026 | W62: =IF(N62=O62,TRUE,FALSE) -> TRUE
A63: 46051.442 | B63: Tee Swerve 3" | C63: Construction | E63: Construction | L63: 4 | M63: 19 | N63: 76 | O63: =L63*M63 -> 76 | P63: 46051 | U63: =TEXT(A63, "MMMM YYYY") -> January 2026 | W63: =IF(N63=O63,TRUE,FALSE) -> TRUE
A64: 46051.441 | B64: Interplast Pipe 3" | C64: Construction | E64: Construction | L64: 5 | M64: 105 | N64: 525 | O64: =L64*M64 -> 525 | P64: 46051 | U64: =TEXT(A64, "MMMM YYYY") -> January 2026 | W64: =IF(N64=O64,TRUE,FALSE) -> TRUE
A65: 46051.44 | B65: Carpenter - Part Labor | C65: Construction | E65: Construction | L65: 1 | M65: 1200 | N65: 1200 | O65: =L65*M65 -> 1200 | P65: 46050 | U65: =TEXT(A65, "MMMM YYYY") -> January 2026 | W65: =IF(N65=O65,TRUE,FALSE) -> TRUE
A66: 46050.538 | B66: Omnicide Disinfectant 5L | C66: General Admin | E66: Health & Nutrition | G66: Biosecurity | L66: 1 | M66: 760 | N66: 760 | O66: =L66*M66 -> 760 | P66: 46050 | U66: =TEXT(A66, "MMMM YYYY") -> January 2026 | W66: =IF(N66=O66,TRUE,FALSE) -> TRUE
A67: 46050.537 | B67: Patholyte 5L | C67: General Admin | E67: Health & Nutrition | G67: Biosecurity | L67: 1 | M67: 230 | N67: 230 | O67: =L67*M67 -> 230 | P67: 46050 | U67: =TEXT(A67, "MMMM YYYY") -> January 2026 | W67: =IF(N67=O67,TRUE,FALSE) -> TRUE
A68: 46050.537 | B68: Koudijs Developer Mash | C68: Layers - SET 4 | D68: Health & Nutrition | G68: Feed purchase | L68: 8 | M68: 386 | N68: 3088 | O68: =L68*M68 -> 3088 | P68: 46050 | U68: =TEXT(A68, "MMMM YYYY") -> January 2026 | W68: =IF(N68=O68,TRUE,FALSE) -> TRUE
A69: 46050.535 | B69: Koudijs Layer 1 Mash | C69: Layers - SET 3 | D69: Health & Nutrition | G69: Feed purchase | L69: 3 | M69: 392 | N69: 1176 | O69: =L69*M69 -> 1176 | P69: 46050 | U69: =TEXT(A69, "MMMM YYYY") -> January 2026 | W69: =IF(N69=O69,TRUE,FALSE) -> TRUE
A70: 46050.533 | B70: Koudijs Layer 1 Mash | C70: Layers - SET 2 | D70: Health & Nutrition | G70: Feed purchase | L70: 7 | M70: 392 | N70: 2744 | O70: =L70*M70 -> 2744 | P70: 46050 | U70: =TEXT(A70, "MMMM YYYY") -> January 2026 | W70: =IF(N70=O70,TRUE,FALSE) -> TRUE
A71: 46050.53 | B71: Koudijs Layer 1 Mash | C71: Layers - SET 1 | D71: Health & Nutrition | G71: Feed purchase | L71: 2 | M71: 392 | N71: 784 | O71: =L71*M71 -> 784 | P71: 46050 | U71: =TEXT(A71, "MMMM YYYY") -> January 2026 | W71: =IF(N71=O71,TRUE,FALSE) -> TRUE
A72: 46050.526 | B72: Roofing Nails | C72: Construction | E72: Construction | L72: 1 | M72: 40 | N72: 40 | O72: =L72*M72 -> 40 | P72: 46050 | U72: =TEXT(A72, "MMMM YYYY") -> January 2026 | W72: =IF(N72=O72,TRUE,FALSE) -> TRUE
A73: 46050.526 | B73: Roofing Sheet | C73: Construction | E73: Construction | L73: 2 | M73: 80 | N73: 160 | O73: =L73*M73 -> 160 | P73: 46050 | U73: =TEXT(A73, "MMMM YYYY") -> January 2026 | W73: =IF(N73=O73,TRUE,FALSE) -> TRUE
A74: 46050.525 | B74: 1/4 Plywood | C74: Construction | E74: Construction | L74: 2 | M74: 140 | N74: 280 | O74: =L74*M74 -> 280 | P74: 46050 | U74: =TEXT(A74, "MMMM YYYY") -> January 2026 | W74: =IF(N74=O74,TRUE,FALSE) -> TRUE
A75: 46050.524 | B75: Batteries for scale | C75: General Admin | E75: Utilities & Operations | K75: Regulatory Expenses | L75: 1 | M75: 28 | N75: 28 | O75: =L75*M75 -> 28 | P75: 46050 | U75: =TEXT(A75, "MMMM YYYY") -> January 2026 | W75: =IF(N75=O75,TRUE,FALSE) -> TRUE
A76: 46050.521 | B76: Sponge | C76: General Admin | E76: Health & Nutrition | G76: Biosecurity | L76: 1 | M76: 30 | N76: 30 | O76: =L76*M76 -> 30 | P76: 46050 | U76: =TEXT(A76, "MMMM YYYY") -> January 2026 | W76: =IF(N76=O76,TRUE,FALSE) -> TRUE
A77: 46050.52 | B77: Brake Pads-T/Hilux(GE-8785-20) | C77: General Admin | E77: Maintenance & Equipment | L77: 1 | M77: 750 | N77: 750 | O77: =L77*M77 -> 750 | P77: 46049 | R77: Repairs/Maintenance | U77: =TEXT(A77, "MMMM YYYY") -> January 2026 | W77: =IF(N77=O77,TRUE,FALSE) -> TRUE
A78: 46050.518 | B78: Road Worthy T-Hilux GE-8785-20 | C78: General Admin | E78: Financial & Overheads | L78: 1 | M78: 350 | N78: 350 | O78: =L78*M78 -> 350 | P78: 46049 | T78: Insurance | U78: =TEXT(A78, "MMMM YYYY") -> January 2026 | W78: =IF(N78=O78,TRUE,FALSE) -> TRUE
A79: 46049.316 | B79: Nails | C79: Construction | E79: Construction | L79: 3 | M79: 60 | N79: 180 | O79: =L79*M79 -> 180 | P79: 46048 | U79: =TEXT(A79, "MMMM YYYY") -> January 2026 | W79: =IF(N79=O79,TRUE,FALSE) -> TRUE
A80: 46049.315 | B80: 1/4 Plywood | C80: Construction | E80: Construction | L80: 4 | M80: 140 | N80: 560 | O80: =L80*M80 -> 560 | P80: 46048 | U80: =TEXT(A80, "MMMM YYYY") -> January 2026 | W80: =IF(N80=O80,TRUE,FALSE) -> TRUE
A81: 46049.314 | B81: 2x4 Wood | C81: Construction | E81: Construction | L81: 5 | M81: 75 | N81: 375 | O81: =L81*M81 -> 375 | P81: 46048 | U81: =TEXT(A81, "MMMM YYYY") -> January 2026 | W81: =IF(N81=O81,TRUE,FALSE) -> TRUE
A82: 46049.313 | B82: 2x3 Wood | C82: Construction | E82: Construction | L82: 10 | M82: 55 | N82: 550 | O82: =L82*M82 -> 550 | P82: 46048 | U82: =TEXT(A82, "MMMM YYYY") -> January 2026 | W82: =IF(N82=O82,TRUE,FALSE) -> TRUE
A83: 46049.038 | B83: Board | C83: Construction | E83: Construction | L83: 21 | M83: 180 | N83: 3780 | O83: =L83*M83 -> 3780 | P83: 46048 | U83: =TEXT(A83, "MMMM YYYY") -> January 2026 | W83: =IF(N83=O83,TRUE,FALSE) -> TRUE
A84: 46048.321 | B84: Koudijs Developer Mash | C84: Layers - SET 4 | D84: Health & Nutrition | G84: Feed purchase | L84: 11 | M84: 388 | N84: 4268 | O84: =L84*M84 -> 4268 | P84: 46046 | U84: =TEXT(A84, "MMMM YYYY") -> January 2026 | W84: =IF(N84=O84,TRUE,FALSE) -> TRUE
A85: 46048.32 | B85: Koudijs Layer 1 Mash | C85: Layers - SET 3 | D85: Health & Nutrition | G85: Feed purchase | L85: 2 | M85: 392 | N85: 784 | O85: =L85*M85 -> 784 | P85: 46046 | U85: =TEXT(A85, "MMMM YYYY") -> January 2026 | W85: =IF(N85=O85,TRUE,FALSE) -> TRUE
A86: 46048.275 | B86: Koudijs Layer 1 Mash | C86: Layers - SET 2 | D86: Health & Nutrition | G86: Feed purchase | L86: 7 | M86: 392 | N86: 2744 | O86: =L86*M86 -> 2744 | P86: 46046 | U86: =TEXT(A86, "MMMM YYYY") -> January 2026 | W86: =IF(N86=O86,TRUE,FALSE) -> TRUE
A87: 46048.272 | B87: Koudijs Layer 1 Mash | C87: Layers - SET 1 | D87: Health & Nutrition | G87: Feed purchase | L87: 1 | M87: 392 | N87: 392 | O87: =L87*M87 -> 392 | P87: 46046 | U87: =TEXT(A87, "MMMM YYYY") -> January 2026 | W87: =IF(N87=O87,TRUE,FALSE) -> TRUE
A88: 46048.244 | B88: Vet for 3rd Newcastle Vaccination | C88: Layers - SET 4 | D88: Health & Nutrition | G88: Veterinary visits | L88: 1500 | M88: 0.8 | N88: 1200 | O88: =L88*M88 -> 1200 | P88: 46046 | U88: =TEXT(A88, "MMMM YYYY") -> January 2026 | W88: =IF(N88=O88,TRUE,FALSE) -> TRUE
A89: 46043.524 | B89: Koudijs Developer Mash | C89: Layers - SET 4 | D89: Health & Nutrition | G89: Feed purchase | L89: 10 | M89: 388 | N89: 3880 | O89: =L89*M89 -> 3880 | P89: 46043 | U89: =TEXT(A89, "MMMM YYYY") -> January 2026 | W89: =IF(N89=O89,TRUE,FALSE) -> TRUE
A90: 46043.523 | B90: Koudijs Layer 1 Mash | C90: Layers - SET 3 | D90: Health & Nutrition | G90: Feed purchase | L90: 5 | M90: 396 | N90: 1980 | O90: =L90*M90 -> 1980 | P90: 46043 | U90: =TEXT(A90, "MMMM YYYY") -> January 2026 | W90: =IF(N90=O90,TRUE,FALSE) -> TRUE
A91: 46043.522 | B91: Koudijs Layer 1 Mash | C91: Layers - SET 2 | D91: Health & Nutrition | G91: Feed purchase | L91: 4 | M91: 396 | N91: 1584 | O91: =L91*M91 -> 1584 | P91: 46043 | U91: =TEXT(A91, "MMMM YYYY") -> January 2026 | W91: =IF(N91=O91,TRUE,FALSE) -> TRUE
A92: 46043.52 | B92: Koudijs Layer 1 Mash | C92: Layers - SET 1 | D92: Health & Nutrition | G92: Feed purchase | L92: 2 | M92: 396 | N92: 792 | O92: =L92*M92 -> 792 | P92: 46043 | U92: =TEXT(A92, "MMMM YYYY") -> January 2026 | W92: =IF(N92=O92,TRUE,FALSE) -> TRUE
A93: 46038.658 | B93: AminTotal 1kg | C93: General Admin | E93: Health & Nutrition | G93: Supplements | L93: 1 | M93: 420 | N93: 420 | O93: =L93*M93 -> 420 | P93: 46036 | U93: =TEXT(A93, "MMMM YYYY") -> January 2026 | W93: =IF(N93=O93,TRUE,FALSE) -> TRUE
A94: 46038.656 | B94: Multi Amino M | C94: Layers - SET 4 | D94: Health & Nutrition | G94: Vitamins | L94: 1 | M94: 198 | N94: 198 | O94: =L94*M94 -> 198 | P94: 46036 | U94: =TEXT(A94, "MMMM YYYY") -> January 2026 | W94: =IF(N94=O94,TRUE,FALSE) -> TRUE
A95: 46038.653 | B95: Koudijs Developer Mash | C95: Layers - SET 4 | D95: Health & Nutrition | G95: Feed purchase | L95: 21 | M95: 396 | N95: 8316 | O95: =L95*M95 -> 8316 | P95: 46036 | U95: =TEXT(A95, "MMMM YYYY") -> January 2026 | W95: =IF(N95=O95,TRUE,FALSE) -> TRUE
A96: 46038.342 | B96: Koudijs Layer 1 Mash | C96: Layers - SET 3 | D96: Health & Nutrition | G96: Feed purchase | L96: 7 | M96: 401 | N96: 2807 | O96: =L96*M96 -> 2807 | P96: 46036 | U96: =TEXT(A96, "MMMM YYYY") -> January 2026 | W96: =IF(N96=O96,TRUE,FALSE) -> TRUE
A97: 46038.34 | B97: Koudijs Layer 1 Mash | C97: Layers - SET 2 | D97: Health & Nutrition | G97: Feed purchase | L97: 10 | M97: 401 | N97: 4010 | O97: =L97*M97 -> 4010 | P97: 46036 | U97: =TEXT(A97, "MMMM YYYY") -> January 2026 | W97: =IF(N97=O97,TRUE,FALSE) -> TRUE
A98: 46038.329 | B98: Koudijs Layer 1 Mash | C98: Layers - SET 1 | D98: Health & Nutrition | G98: Feed purchase | L98: 3 | M98: 401 | N98: 1203 | O98: =L98*M98 -> 1203 | P98: 46036 | U98: =TEXT(A98, "MMMM YYYY") -> January 2026 | W98: =IF(N98=O98,TRUE,FALSE) -> TRUE
A99: 46036.313 | B99: Prepaid | C99: General Admin | E99: Utilities & Operations | K99: Electricity | L99: 1 | M99: 400 | N99: 400 | O99: =L99*M99 -> 400 | P99: 46034 | U99: =TEXT(A99, "MMMM YYYY") -> January 2026 | W99: =IF(N99=O99,TRUE,FALSE) -> TRUE
A100: 46032.445 | B100: 3rd Newcastle Vaccine | C100: Layers - SET 4 | D100: Health & Nutrition | G100: Vaccines | L100: 2 | M100: 590 | N100: 1180 | O100: =L100*M100 -> 1180 | P100: 46032 | U100: =TEXT(A100, "MMMM YYYY") -> January 2026 | W100: =IF(N100=O100,TRUE,FALSE) -> TRUE
...

Sheet Sheet23

Sheet Imprest
A1: Date Issued | B1: Imprest Amount | C1: Imprest Account | D1: Purpose Description | E1: Column 1 | F1: Comments | G1: TOTAL | H1: =SUM(B:B) -> 1304609
A2: 45658 | B2: 5787 | C2: Egg Sales | D2: Operational Expenses
A3: 45658 | B3: =1700+1050 -> 2750 | C3: Cash | D3: Operational Expenses
A4: 45678 | B4: 15000 | C4: CBG | D4: Operational Expenses
A5: 45684 | B5: 9452 | C5: Egg Sales | D5: Operational Expenses
A6: 45686 | B6: 1698 | C6: Egg Sales | D6: Operational Expenses
A7: 45688 | B7: 6240 | C7: Egg Sales | D7: Operational Expenses
A8: 45695 | B8: 5883 | C8: Egg Sales | D8: Operational Expenses
A9: 45702 | B9: 10639 | C9: Egg Sales | D9: Operational Expenses
A10: 45707 | B10: 4358 | C10: Egg Sales | D10: Operational Expenses
A11: 45709 | B11: 15000 | C11: Ecobank | D11: Operational Expenses
A12: 45718 | B12: 4850 | C12: Egg Sales | D12: Operational Expenses
A13: 45721 | B13: 1812 | C13: Egg Sales | D13: Operational Expenses
A14: 45727 | B14: 11299 | C14: Ecobank | D14: Operational Expenses
A15: 45727 | B15: 6711 | C15: Egg Sales | D15: Operational Expenses
... A23: 45752 | B23: 5393 | C23: Egg Sales | D23: Operational Expenses
A24: 45754 | B24: 4320 | C24: Cash | D24: Operational Expenses | F24: from broiler sales
A25: 45755 | B25: 680 | C25: Egg Sales | D25: Operational Expenses
A26: 45762 | B26: 4578 | C26: Egg Sales | D26: Operational Expenses
A27: 45762 | B27: 2378 | C27: Cash | D27: Operational Expenses | F27: Broiler sales
A28: 45765 | B28: 4015 | C28: CBG | D28: Operational Expenses
A29: 45766 | B29: 13000 | C29: Ecobank | D29: Operational Expenses
A30: 45767 | B30: 20000 | C30: Cash | D30: Operational Expenses
A31: 45771 | B31: 20000 | C31: Cash | D31: Operational Expenses
A32: 45774 | B32: 8748 | C32: Egg Sales | D32: Operational Expenses
A33: 45774 | B33: 1919 | C33: Cash | D33: Operational Expenses | F33: Broiler sales
A34: 45775 | B34: 20000 | C34: Ecobank | D34: Operational Expenses
A35: 45775 | B35: 15000 | C35: CBG | D35: Operational Expenses
A36: 45782 | B36: 5000 | C36: CBG | D36: Operational Expenses
A37: 45784 | B37: =303+1597 -> 1900 | C37: Cash | D37: Operational Expenses | F37: Broiler sales
A38: 45785 | B38: 6611 | C38: Egg Sales | D38: Operational Expenses
A39: 45786 | B39: 15000 | C39: CBG | D39: Operational Expenses
A40: 45788 | B40: 2055 | C40: Egg Sales | D40: Operational Expenses
A41: 45788 | B41: 360 | C41: Cash | D41: Operational Expenses | F41: Broiler sales
A42: 45789 | B42: 5500 | C42: CBG | D42: Operational Expenses
A43: 45790 | B43: 1515 | C43: Egg Sales | D43: Operational Expenses
A44: 45791 | B44: 8000 | C44: CBG | D44: Operational Expenses
A45: 45793 | B45: 4000 | C45: Ecobank | D45: Operational Expenses
A46: 45793 | B46: 1320 | C46: Egg Sales | D46: Operational Expenses
A47: 45793 | B47: 600 | C47: Cash | D47: Operational Expenses | F47: Broiler sales
A48: 45795 | B48: 10000 | C48: Ecobank | D48: Operational Expenses
A49: 45797 | B49: 960 | C49: Cash | D49: Operational Expenses | F49: Broiler sales
A50: 45802 | B50: 11019 | C50: Egg Sales | D50: Operational Expenses
A51: 45805 | B51: 20000 | C51: Ecobank | D51: Operational Expenses
A52: 45809 | B52: 8203 | C52: Egg Sales | D52: Operational Expenses
A53: 45812 | B53: 8037 | C53: Egg Sales | D53: Operational Expenses
A54: 45817 | B54: 9910 | C54: Egg Sales | D54: Operational Expenses
A55: 45818 | B55: 20000 | C55: CBG | D55: Operational Expenses
A56: 45823 | B56: 12399 | C56: Egg Sales | D56: Operational Expenses
A57: 45831 | B57: 13977 | C57: Egg Sales | D57: Operational Expenses
A58: 45832 | B58: 18000 | C58: CBG | D58: Operational Expenses
A59: 45835 | B59: 8000 | C59: CBG | D59: Operational Expenses
A60: 45837 | B60: 11790 | C60: Egg Sales | D60: Operational Expenses
A61: 45840 | B61: 9612 | C61: Egg Sales | D61: Operational Expenses
... A96: 45944 | B96: 13616 | C96: Egg Sales | D96: Operational Expenses
A97: 45950 | B97: =15000+20000 -> 35000 | C97: Cash | D97: Operational Expenses
A98: 45949 | B98: 9770 | C98: Egg Sales | D98: Operational Expenses
A99: 45951 | B99: 3265 | C99: Egg Sales | D99: Operational Expenses
A100: 45956 | B100: 14291 | C100: Egg Sales | D100: Operational Expenses
A101: 45965 | B101: 13363 | C101: Egg Sales | D101: Operational Expenses
A102: 45965 | B102: 5000 | C102: Cash | D102: Operational Expenses
A103: 45967 | B103: 5000 | C103: Cash | D103: Operational Expenses
A104: 45970 | B104: =7719+1140 -> 8859 | C104: Egg Sales | D104: Operational Expenses
A105: 45972 | B105: 20000 | C105: Cash | D105: Operational Expenses
A106: 45975 | B106: 10550 | C106: Egg Sales | D106: Operational Expenses
A107: 45978 | B107: 6266 | C107: Egg Sales | D107: Operational Expenses
A108: 45983 | B108: 7190 | C108: Egg Sales | D108: Operational Expenses
A109: 45986 | B109: 20000 | C109: Cash | D109: Operational Expenses
A110: 45994 | B110: 11000 | C110: Cash | D110: Operational Expenses
A111: 45995 | B111: 21140 | C111: Egg Sales | D111: Operational Expenses
A112: 45996 | B112: 5055 | C112: Egg Sales | D112: Operational Expenses
A113: 46004 | B113: 11000 | C113: CBG | D113: Operational Expenses
A114: 46009 | B114: 4000 | C114: CBG | D114: Operational Expenses
A115: 46004 | B115: 17955 | C115: Egg Sales | D115: Operational Expenses
A116: 46017 | B116: 17100 | C116: Egg Sales | D116: Operational Expenses
... A119: 46028 | B119: 6495 | C119: Egg Sales | D119: Operational Expenses
A120: 46028 | B120: ='Dec 2025 Sales'!M2 -> 46520 | C120: Cash | D120: Operational Expenses | F120: Christmas sale from Tei
A121: 46030 | B121: 20000 | C121: Cash | D121: Operational Expenses
A122: 46031 | B122: 6640 | C122: Egg Sales | D122: Operational Expenses
A123: 46042 | B123: 11605 | C123: Egg Sales | D123: Operational Expenses
A124: 46044 | B124: 3920 | C124: Egg Sales | D124: Operational Expenses
A125: 46048 | B125: 10000 | C125: Cash | D125: Operational Expenses
A126: 46050 | B126: 25000 | C126: Ecobank | D126: Operational Expenses
A127: 46050 | B127: 7655 | C127: Egg Sales | D127: Operational Expenses
A128: 46054 | B128: 25000 | C128: Ecobank | D128: Operational Expenses

Sheet Production
A1: Timestamp | B1: Production date | C1: Number of crates | D1: Loose | E1: Damaged Eggs | F1: Collected by | G1: Select SET | H1: Number of laying hens | I1: Mortality | J1: Total Collected | K1: Actual Total | L1: Month | M1: Prod Rate | N1: Column 13 | O1: Column 1 | P1: Column 2 | Q1: Column 3
A2: 46055.319 | B2: 46054 | C2: 11 | D2: 3 | E2: 7 | F2: Osabu | G2: SET C | H2: 432 | I2: =IFERROR(ABS(H2 - INDEX(H3:H5834, MATCH(G2, G3:G5834, 0))), "") -> 0 | J2: =(C2*30+D2) -> 333 | K2: =J2-E2 -> 326 | L2: =TEXT(B2, "MMMM YYYY") -> February 2026 | M2: =J2/H2 -> 0.77083333 | O2: Total Collected | P2: =SUM(J:J) -> 352087
A3: 46055.318 | B3: 46054 | C3: 15 | D3: 20 | E3: 14 | F3: Okunka | G3: SET B | H3: 612 | I3: =IFERROR(ABS(H3 - INDEX(H4:H5835, MATCH(G3, G4:G5835, 0))), "") -> 5 | J3: =(C3*30+D3) -> 470 | K3: =J3-E3 -> 456 | L3: =TEXT(B3, "MMMM YYYY") -> February 2026 | M3: =J3/H3 -> 0.76797386 | O3: Damaged | P3: =SUM(E:E) -> 7548
A4: 46055.311 | B4: 46054 | C4: 2 | D4: 1 | E4: 6 | F4: Okunka | G4: SET A | H4: 176 | I4: =IFERROR(ABS(H4 - INDEX(H5:H5836, MATCH(G4, G5:G5836, 0))), "") -> 3 | J4: =(C4*30+D4) -> 61 | K4: =J4-E4 -> 55 | L4: =TEXT(B4, "MMMM YYYY") -> February 2026 | M4: =J4/H4 -> 0.34659091 | O4: Actual Total | P4: =SUM(K:K) -> 344539
A5: 46054.454 | B5: 46053 | C5: 11 | D5: 26 | E5: 8 | F5: Vanessa | G5: SET C | H5: 432 | I5: =IFERROR(ABS(H5 - INDEX(H6:H5837, MATCH(G5, G6:G5837, 0))), "") -> 0 | J5: =(C5*30+D5) -> 356 | K5: =J5-E5 -> 348 | L5: =TEXT(B5, "MMMM YYYY") -> January 2026 | M5: =J5/H5 -> 0.82407407
A6: 46054.453 | B6: 46053 | C6: 13 | D6: 29 | E6: 10 | F6: Vanessa | G6: SET B | H6: 617 | I6: =IFERROR(ABS(H6 - INDEX(H7:H5838, MATCH(G6, G7:G5838, 0))), "") -> 4 | J6: =(C6*30+D6) -> 419 | K6: =J6-E6 -> 409 | L6: =TEXT(B6, "MMMM YYYY") -> January 2026 | M6: =J6/H6 -> 0.67909238
A7: 46054.452 | B7: 46053 | C7: 2 | D7: 18 | E7: 4 | F7: Vanessa | G7: SET A | H7: 179 | I7: =IFERROR(ABS(H7 - INDEX(H8:H5839, MATCH(G7, G8:G5839, 0))), "") -> 2 | J7: =(C7*30+D7) -> 78 | K7: =J7-E7 -> 74 | L7: =TEXT(B7, "MMMM YYYY") -> January 2026 | M7: =J7/H7 -> 0.43575419
A8: 46054.056 | B8: 46052 | C8: 11 | D8: 19 | E8: 8 | F8: Vanessa | G8: SET C | H8: 432 | I8: =IFERROR(ABS(H8 - INDEX(H9:H5840, MATCH(G8, G9:G5840, 0))), "") -> 0 | J8: =(C8*30+D8) -> 349 | K8: =J8-E8 -> 341 | L8: =TEXT(B8, "MMMM YYYY") -> January 2026 | M8: =J8/H8 -> 0.80787037
A9: 46054.05 | B9: 46052 | C9: 14 | D9: 26 | E9: 7 | F9: Vanessa | G9: SET B | H9: 621 | I9: =IFERROR(ABS(H9 - INDEX(H10:H5841, MATCH(G9, G10:G5841, 0))), "") -> 4 | J9: =(C9*30+D9) -> 446 | K9: =J9-E9 -> 439 | L9: =TEXT(B9, "MMMM YYYY") -> January 2026 | M9: =J9/H9 -> 0.71819646
A10: 46054.047 | B10: 46052 | C10: 2 | D10: 28 | E10: 5 | F10: Vanessa | G10: SET A | H10: 181 | I10: =IFERROR(ABS(H10 - INDEX(H11:H5842, MATCH(G10, G11:G5842, 0))), "") -> 4 | J10: =(C10*30+D10) -> 88 | K10: =J10-E10 -> 83 | L10: =TEXT(B10, "MMMM YYYY") -> January 2026 | M10: =J10/H10 -> 0.48618785
A11: 46052.328 | B11: 46051 | C11: 11 | D11: 13 | E11: 4 | F11: Vanessa | G11: SET C | H11: 432 | I11: =IFERROR(ABS(H11 - INDEX(H12:H5843, MATCH(G11, G12:G5843, 0))), "") -> 2 | J11: =(C11*30+D11) -> 343 | K11: =J11-E11 -> 339 | L11: =TEXT(B11, "MMMM YYYY") -> January 2026 | M11: =J11/H11 -> 0.79398148
A12: 46052.327 | B12: 46051 | C12: 14 | D12: 22 | E12: 9 | F12: Vanessa | G12: SET B | H12: 625 | I12: =IFERROR(ABS(H12 - INDEX(H13:H5844, MATCH(G12, G13:G5844, 0))), "") -> 6 | J12: =(C12*30+D12) -> 442 | K12: =J12-E12 -> 433 | L12: =TEXT(B12, "MMMM YYYY") -> January 2026 | M12: =J12/H12 -> 0.7072
A13: 46052.32 | B13: 46051 | C13: 3 | D13: 1 | E13: 5 | F13: Osabu | G13: SET A | H13: 185 | I13: =IFERROR(ABS(H13 - INDEX(H14:H5845, MATCH(G13, G14:G5845, 0))), "") -> 2 | J13: =(C13*30+D13) -> 91 | K13: =J13-E13 -> 86 | L13: =TEXT(B13, "MMMM YYYY") -> January 2026 | M13: =J13/H13 -> 0.49189189
A14: 46051.009 | B14: 46050 | C14: 11 | D14: 18 | E14: 7 | F14: Vanessa | G14: SET C | H14: 434 | I14: =IFERROR(ABS(H14 - INDEX(H15:H5846, MATCH(G14, G15:G5846, 0))), "") -> 1 | J14: =(C14*30+D14) -> 348 | K14: =J14-E14 -> 341 | L14: =TEXT(B14, "MMMM YYYY") -> January 2026 | M14: =J14/H14 -> 0.80184332
A15: 46051.007 | B15: 46050 | C15: 15 | D15: 2 | E15: 7 | F15: Vanessa | G15: SET B | H15: 631 | I15: =IFERROR(ABS(H15 - INDEX(H16:H5847, MATCH(G15, G16:G5847, 0))), "") -> 4 | J15: =(C15*30+D15) -> 452 | K15: =J15-E15 -> 445 | L15: =TEXT(B15, "MMMM YYYY") -> January 2026 | M15: =J15/H15 -> 0.7163233
A16: 46051.006 | B16: 46050 | C16: 3 | D16: 5 | E16: 9 | F16: Okunka | G16: SET A | H16: 187 | I16: =IFERROR(ABS(H16 - INDEX(H17:H5848, MATCH(G16, G17:G5848, 0))), "") -> 2 | J16: =(C16*30+D16) -> 95 | K16: =J16-E16 -> 86 | L16: =TEXT(B16, "MMMM YYYY") -> January 2026 | M16: =J16/H16 -> 0.50802139
... A631: 45809.751 | B631: 45808 | C631: 10 | D631: 7 | E631: 6 | F631: Kweku | G631: SET A | H631: 414 | I631: =IFERROR(ABS(H631 - INDEX(H632:H6463, MATCH(G631, G632:G6463, 0))), "") -> 0 | J631: =(C631*30+D631) -> 307 | K631: =J631-E631 -> 301 | L631: =TEXT(B631, "MMMM YYYY") -> May 2025 | M631: =J631/H631 -> 0.74154589
A632: 45808.131 | B632: 45807 | C632: 27 | D632: 8 | E632: 39 | F632: Richard | G632: SET B | H632: 1148 | I632: 0 | J632: =(C632*30+D632) -> 818 | K632: =J632-E632 -> 779 | L632: =TEXT(B632, "MMMM YYYY") -> May 2025 | M632: =J632/H632 -> 0.71254355
A633: 45808.127 | B633: 45807 | C633: 10 | D633: 9 | E633: 7 | F633: Kweku | G633: SET A | H633: 414 | I633: 0 | J633: =(C633*30+D633) -> 309 | K633: =J633-E633 -> 302 | L633: =TEXT(B633, "MMMM YYYY") -> May 2025 | M633: =J633/H633 -> 0.74637681
A634: 45806.766 | B634: 45806 | C634: 26 | D634: 16 | E634: 46 | F634: Tei | G634: SET B | I634: =IFERROR(ABS(H634 - INDEX(H635:H5834, MATCH(G634, G635:G5834, 0))), "") -> 0 | J634: =(C634*30+D634) -> 796 | K634: =J634-E634 -> 750 | L634: =TEXT(B634, "MMMM YYYY") -> May 2025 | M634: 0
A635: 45806.764 | B635: 45806 | C635: 10 | D635: 2 | E635: 6 | F635: Tei | G635: SET A | I635: =IFERROR(ABS(H635 - INDEX(H636:H5835, MATCH(G635, G636:G5835, 0))), "") -> 0 | J635: =(C635*30+D635) -> 302 | K635: =J635-E635 -> 296 | L635: =TEXT(B635, "MMMM YYYY") -> May 2025 | M635: 0
A636: 45805.872 | B636: 45805 | C636: 26 | D636: 2 | E636: 57 | F636: Richard | G636: SET B | I636: =IFERROR(ABS(H636 - INDEX(H637:H5836, MATCH(G636, G637:G5836, 0))), "") -> 0 | J636: =(C636*30+D636) -> 782 | K636: =J636-E636 -> 725 | L636: =TEXT(B636, "MMMM YYYY") -> May 2025 | M636: 0
A637: 45805.866 | B637: 45805 | C637: 10 | D637: 7 | E637: 8 | F637: Tei | G637: SET A | I637: =IFERROR(ABS(H637 - INDEX(H638:H5837, MATCH(G637, G638:G5837, 0))), "") -> 0 | J637: =(C637*30+D637) -> 307 | K637: =J637-E637 -> 299 | L637: =TEXT(B637, "MMMM YYYY") -> May 2025 | M637: 0
A638: 45805.053 | B638: 45804 | C638: 24 | D638: 15 | E638: 47 | F638: Tei | G638: SET B | I638: =IFERROR(ABS(H638 - INDEX(H639:H5838, MATCH(G638, G639:G5838, 0))), "") -> 0 | J638: =(C638*30+D638) -> 735 | K638: =J638-E638 -> 688 | L638: =TEXT(B638, "MMMM YYYY") -> May 2025 | M638: 0
A639: 45805.052 | B639: 45804 | C639: 10 | D639: 9 | E639: 7 | F639: Tei | G639: SET A | I639: =IFERROR(ABS(H639 - INDEX(H640:H5839, MATCH(G639, G640:G5839, 0))), "") -> 0 | J639: =(C639*30+D639) -> 309 | K639: =J639-E639 -> 302 | L639: =TEXT(B639, "MMMM YYYY") -> May 2025 | M639: 0
A640: 45804.597 | B640: 45803 | C640: 10 | D640: 19 | E640: 6 | F640: Tei | G640: SET A | I640: =IFERROR(ABS(H640 - INDEX(H641:H5840, MATCH(G640, G641:G5840, 0))), "") -> 0 | J640: =(C640*30+D640) -> 319 | K640: =J640-E640 -> 313 | L640: =TEXT(B640, "MMMM YYYY") -> May 2025 | M640: 0
A641: 45804.596 | B641: 45803 | C641: 23 | D641: 10 | E641: 54 | F641: Tei | G641: SET B | I641: =IFERROR(ABS(H641 - INDEX(H642:H5841, MATCH(G641, G642:G5841, 0))), "") -> 0 | J641: =(C641*30+D641) -> 700 | K641: =J641-E641 -> 646 | L641: =TEXT(B641, "MMMM YYYY") -> May 2025 | M641: 0
A642: 45803.111 | B642: 45802 | C642: 22 | D642: 5 | E642: 49 | F642: Richard | G642: SET B | I642: =IFERROR(ABS(H642 - INDEX(H643:H5842, MATCH(G642, G643:G5842, 0))), "") -> 0 | J642: =(C642*30+D642) -> 665 | K642: =J642-E642 -> 616 | L642: =TEXT(B642, "MMMM YYYY") -> May 2025 | M642: 0
A643: 45803.11 | B643: 45802 | C643: 10 | D643: 13 | E643: 7 | F643: Richard | G643: SET A | I643: =IFERROR(ABS(H643 - INDEX(H644:H5843, MATCH(G643, G644:G5843, 0))), "") -> 0 | J643: =(C643*30+D643) -> 313 | K643: =J643-E643 -> 306 | L643: =TEXT(B643, "MMMM YYYY") -> May 2025 | M643: 0
A644: 45801.952 | B644: 45801 | C644: 20 | D644: 21 | E644: 54 | F644: Tei | G644: SET B | I644: =IFERROR(ABS(H644 - INDEX(H645:H5844, MATCH(G644, G645:G5844, 0))), "") -> 0 | J644: =(C644*30+D644) -> 621 | K644: =J644-E644 -> 567 | L644: =TEXT(B644, "MMMM YYYY") -> May 2025 | M644: 0
A645: 45801.947 | B645: 45801 | C645: 10 | D645: 19 | E645: 6 | F645: Tei | G645: SET A | I645: =IFERROR(ABS(H645 - INDEX(H646:H5845, MATCH(G645, G646:G5845, 0))), "") -> 0 | J645: =(C645*30+D645) -> 319 | K645: =J645-E645 -> 313 | L645: =TEXT(B645, "MMMM YYYY") -> May 2025 | M645: 0
... A735: 45739.002 | B735: 45736 | C735: 13 | D735: 2 | E735: 9 | F735: Tei | G735: SET A | I735: =IFERROR(ABS(H735 - INDEX(H736:H5935, MATCH(G735, G736:G5935, 0))), "") -> 0 | J735: =(C735*30+D735) -> 392 | K735: =J735-E735 -> 383 | L735: =TEXT(B735, "MMMM YYYY") -> March 2025 | M735: 0
A736: 45736.025 | B736: 45735 | C736: 13 | D736: 10 | E736: 11 | F736: Tei | G736: SET A | I736: {=IFERROR(ABS(H736 - INDEX(H755:H5834, MATCH(G736, G755:G5834, 0))), "")} -> 0 | J736: =(C736*30+D736) -> 400 | K736: =J736-E736 -> 389 | L736: =TEXT(B736, "MMMM YYYY") -> March 2025 | M736: 0
A737: 45734.806 | B737: 45734 | C737: 13 | D737: 16 | E737: 7 | F737: Tei | G737: SET A | I737: =IFERROR(ABS(H737 - INDEX(H738:H5834, MATCH(G737, G738:G5834, 0))), "") -> 0 | J737: =(C737*30+D737) -> 406 | K737: =J737-E737 -> 399 | L737: =TEXT(B737, "MMMM YYYY") -> March 2025 | M737: 0
A738: 45733.621 | B738: 45733 | C738: 13 | D738: 11 | E738: 4 | F738: Tei | G738: SET A | I738: =IFERROR(ABS(H738 - INDEX(H739:H5835, MATCH(G738, G739:G5835, 0))), "") -> 0 | J738: =(C738*30+D738) -> 401 | K738: =J738-E738 -> 397 | L738: =TEXT(B738, "MMMM YYYY") -> March 2025 | M738: 0
A739: 45733.619 | B739: 45732 | C739: 13 | D739: 4 | E739: 7 | F739: Tei | G739: SET A | I739: =IFERROR(ABS(H739 - INDEX(H740:H5836, MATCH(G739, G740:G5836, 0))), "") -> 0 | J739: =(C739*30+D739) -> 394 | K739: =J739-E739 -> 387 | L739: =TEXT(B739, "MMMM YYYY") -> March 2025 | M739: 0
A740: 45732.07 | B740: 45731 | C740: 13 | D740: 3 | E740: 4 | F740: Tei | G740: SET A | I740: =IFERROR(ABS(H740 - INDEX(H741:H5837, MATCH(G740, G741:G5837, 0))), "") -> 0 | J740: =(C740*30+D740) -> 393 | K740: =J740-E740 -> 389 | L740: =TEXT(B740, "MMMM YYYY") -> March 2025 | M740: 0
A741: 45732.07 | B741: 45730 | C741: 13 | D741: 10 | E741: 7 | F741: Tei | G741: SET A | I741: =IFERROR(ABS(H741 - INDEX(H742:H5838, MATCH(G741, G742:G5838, 0))), "") -> 0 | J741: =(C741*30+D741) -> 400 | K741: =J741-E741 -> 393 | L741: =TEXT(B741, "MMMM YYYY") -> March 2025 | M741: 0
A742: 45730.275 | B742: 45729 | C742: 13 | D742: 23 | E742: 6 | F742: Tei | G742: SET A | I742: =IFERROR(ABS(H742 - INDEX(H743:H5839, MATCH(G742, G743:G5839, 0))), "") -> 0 | J742: =(C742*30+D742) -> 413 | K742: =J742-E742 -> 407 | L742: =TEXT(B742, "MMMM YYYY") -> March 2025 | M742: 0
A743: 45729.227 | B743: 45728 | C743: 13 | D743: 25 | E743: 5 | F743: Tei | G743: SET A | I743: =IFERROR(ABS(H743 - INDEX(H744:H5840, MATCH(G743, G744:G5840, 0))), "") -> 0 | J743: =(C743*30+D743) -> 415 | K743: =J743-E743 -> 410 | L743: =TEXT(B743, "MMMM YYYY") -> March 2025 | M743: 0
A744: 45727.778 | B744: 45727 | C744: 13 | D744: 29 | E744: 5 | F744: Tei | G744: SET A | I744: =IFERROR(ABS(H744 - INDEX(H745:H5841, MATCH(G744, G745:G5841, 0))), "") -> 0 | J744: =(C744*30+D744) -> 419 | K744: =J744-E744 -> 414 | L744: =TEXT(B744, "MMMM YYYY") -> March 2025 | M744: 0
A745: 45726.996 | B745: 45726 | C745: 13 | D745: 24 | E745: 6 | F745: Tei | G745: SET A | I745: =IFERROR(ABS(H745 - INDEX(H746:H5842, MATCH(G745, G746:G5842, 0))), "") -> 0 | J745: =(C745*30+D745) -> 414 | K745: =J745-E745 -> 408 | L745: =TEXT(B745, "MMMM YYYY") -> March 2025 | M745: 0
A746: 45726.141 | B746: 45725 | C746: 13 | D746: 12 | E746: 7 | F746: Tei | G746: SET A | I746: =IFERROR(ABS(H746 - INDEX(H747:H5843, MATCH(G746, G747:G5843, 0))), "") -> 0 | J746: =(C746*30+D746) -> 402 | K746: =J746-E746 -> 395 | L746: =TEXT(B746, "MMMM YYYY") -> March 2025 | M746: 0
A747: 45725.559 | B747: 45724 | C747: 13 | D747: 14 | E747: 6 | F747: Tei | G747: SET A | I747: =IFERROR(ABS(H747 - INDEX(H748:H5844, MATCH(G747, G748:G5844, 0))), "") -> 0 | J747: =(C747*30+D747) -> 404 | K747: =J747-E747 -> 398 | L747: =TEXT(B747, "MMMM YYYY") -> March 2025 | M747: 0
A748: 45723.804 | B748: 45723 | C748: 13 | D748: 8 | E748: 5 | F748: Tei | G748: SET A | I748: =IFERROR(ABS(H748 - INDEX(H749:H5845, MATCH(G748, G749:G5845, 0))), "") -> 0 | J748: =(C748*30+D748) -> 398 | K748: =J748-E748 -> 393 | L748: =TEXT(B748, "MMMM YYYY") -> March 2025 | M748: 0
... A813: 45663.524 | B813: 45660 | C813: 14 | D813: 8 | E813: 8 | F813: Tei | G813: SET A | I813: =IFERROR(ABS(H813 - INDEX(H814:H5910, MATCH(G813, G814:G5910, 0))), "") | J813: =(C813*30+D813) -> 428 | K813: =J813-E813 -> 420 | L813: =TEXT(B813, "MMMM YYYY") -> January 2025 | M813: 0
I814: =IFERROR(ABS(H814 - INDEX(H815:H5911, MATCH(G814, G815:G5911, 0))), "") | L814: =TEXT(B814, "MMMM YYYY") -> January 1900
I815: =IFERROR(ABS(H815 - INDEX(H816:H5912, MATCH(G815, G816:G5912, 0))), "") | L815: =TEXT(B815, "MMMM YYYY") -> January 1900
I816: =IFERROR(ABS(H816 - INDEX(H817:H5913, MATCH(G816, G817:G5913, 0))), "") | L816: =TEXT(B816, "MMMM YYYY") -> January 1900
I817: =IFERROR(ABS(H817 - INDEX(H818:H5914, MATCH(G817, G818:G5914, 0))), "") | L817: =TEXT(B817, "MMMM YYYY") -> January 1900
I818: =IFERROR(ABS(H818 - INDEX(H819:H5915, MATCH(G818, G819:G5915, 0))), "") | L818: =TEXT(B818, "MMMM YYYY") -> January 1900
I819: =IFERROR(ABS(H819 - INDEX(H820:H5916, MATCH(G819, G820:G5916, 0))), "") | L819: =TEXT(B819, "MMMM YYYY") -> January 1900
I820: =IFERROR(ABS(H820 - INDEX(H821:H5917, MATCH(G820, G821:G5917, 0))), "") | L820: =TEXT(B820, "MMMM YYYY") -> January 1900
I821: =IFERROR(ABS(H821 - INDEX(H822:H5918, MATCH(G821, G822:G5918, 0))), "") | L821: =TEXT(B821, "MMMM YYYY") -> January 1900
I822: =IFERROR(ABS(H822 - INDEX(H823:H5919, MATCH(G822, G823:G5919, 0))), "") | L822: =TEXT(B822, "MMMM YYYY") -> January 1900
I823: =IFERROR(ABS(H823 - INDEX(H824:H5920, MATCH(G823, G824:G5920, 0))), "") | L823: =TEXT(B823, "MMMM YYYY") -> January 1900
I824: =IFERROR(ABS(H824 - INDEX(H825:H5921, MATCH(G824, G825:G5921, 0))), "") | L824: =TEXT(B824, "MMMM YYYY") -> January 1900
I825: =IFERROR(ABS(H825 - INDEX(H826:H5922, MATCH(G825, G826:G5922, 0))), "") | L825: =TEXT(B825, "MMMM YYYY") -> January 1900
... I1732: =IFERROR(ABS(H1732 - INDEX(H1733:H6829, MATCH(G1732, G1733:G6829, 0))), "") | L1732: =TEXT(B1732, "MMMM YYYY") -> January 1900

Sheet Stock
A1: Pen / Coop Number | B1: Qty | C1: SET
A2: W64 | B2: 4 | C2: SET B | E2: Starting Stock | F2: Quantity | G2: Christmas Sale 2026 | H2: Total Mortality | I2: Balance | J2: Balance/ Prod. Records | K2: Difference
A3: W65 | B3: 4 | C3: SET B | E3: SET A | F3: 414 | G3: 98 | H3: =SUMIF('Mortality and Transfers'!$F:$F,E3,'Mortality and Transfers'!$H:$H) -> 47
A4: W66 | B4: 4 | C4: SET B | E4: SET B | F4: 1148 | G4: 203 | H4: =SUMIF('Mortality and Transfers'!$F:$F,E4,'Mortality and Transfers'!$H:$H) -> 82
A5: W67 | B5: 4 | C5: SET B | E5: SET C | F5: 504 | H5: =SUMIF('Mortality and Transfers'!$F:$F,E5,'Mortality and Transfers'!$H:$H) -> 39
A6: W68 | B6: 4 | C6: SET B | E6: SET D | F6: 2020 | H6: =SUMIF('Mortality and Transfers'!$F:$F,E6,'Mortality and Transfers'!$H:$H) -> 88
A7: W69 | B7: 4 | C7: SET B
A8: W70 | B8: 4 | C8: SET B
A9: W71 | B9: 4 | C9: SET B
A10: W72 | B10: 4 | C10: SET B
A11: W73 | B11: 4 | C11: SET B | E11: Start Dates
A12: W74 | B12: 4 | C12: SET B | E12: SET A | F12: 45338
A13: W75 | B13: 4 | C13: SET B | E13: SET B | F13: 45656
A14: W76 | B14: 4 | C14: SET B | E14: SET C | F14: 45801
A15: W77 | B15: 4 | C15: SET B | E15: SET D | F15: 45930
A16: W78 | B16: 4 | C16: SET B | E16: Broilers | F16: 45948
A17: W79 | B17: 4 | C17: SET B
A18: W80 | B18: 4 | C18: SET B
A19: W81 | B19: 4 | C19: SET B
A20: W82 | B20: 4 | C20: SET B
A21: W83 | B21: 4 | C21: SET B
A22: W84 | B22: 4 | C22: SET B
A23: W85 | B23: 4 | C23: SET B
A24: W86 | B24: 4 | C24: SET B
A25: W87 | B25: 4 | C25: SET B
A26: W88 | B26: 3 | C26: SET B
A27: W89 | B27: 4 | C27: SET B
A28: W90 | B28: 4 | C28: SET B
... A42: W104 | B42: 3 | C42: SET B
A43: W105 | B43: =4-1 -> 3 | C43: SET B
A44: W106 | B44: 4 | C44: SET B
A45: W107 | B45: 4 | C45: SET B
A46: W108 | B46: 4 | C46: SET B
A47: W109 | B47: 4 | C47: SET B
A48: W110 | B48: 4 | C48: SET B
A49: W111 | B49: 3 | C49: SET B
A50: W112 | B50: 4 | C50: SET B
A51: W113 | B51: 4 | C51: SET B
A52: W114 | B52: 4 | C52: SET B
A53: W115 | B53: 4 | C53: SET B
A54: W116 | B54: 4 | C54: SET B
A55: W117 | B55: 4 | C55: SET B
... A69: W131 | B69: 4 | C69: SET B
A70: W132 | B70: =4-1 -> 3 | C70: SET B
A71: W133 | B71: 4 | C71: SET B
A72: W134 | B72: 4 | C72: SET B
A73: W135 | B73: 4 | C73: SET B
A74: W136 | B74: 4 | C74: SET B
A75: W137 | B75: 4 | C75: SET B
A76: W138 | B76: 4 | C76: SET B
A77: W139 | B77: 4 | C77: SET B
A78: W140 | B78: 4 | C78: SET B
A79: W141 | B79: 4 | C79: SET B
A80: W142 | B80: 4 | C80: SET B
A81: W143 | B81: 4 | C81: SET B
A82: W144 | B82: 4 | C82: SET B
... A495: W63 | B495: 2 | C495: SET A
A496: Brooder House | B496: =478-6-5-2 -> 465 | C496: SET C
A497: Quarantine | B497: =6-2 -> 4 | C497: SET A - Quarantine
A498: Brooder House | B498: 2020 | C498: SET D

Sheet Cash Flows
B1: PMT FARMS
B2: CASHFLOWS FOR 2025 | H2: Net Cash flows | I2: =E31-D31 -> 244747.21
A3: DATE | B3: Column1 | D3: DR (GHS) | E3: CR(GHS) | F3: NOTE | I3: =I2+'PMT Summary'!E13 -> 220773.01
A4: 45658 | B4: Bal b/f | E4: 9307.91
A5: 45658 | B5: Additional Capital- 2025 | C5: 88347.5 | E5: =SUM(C5:C16) -> 1185619.5 | F5: Commission from T.Bill
C6: =30000+20000 -> 50000 | F6: Pmt from Ellis
C7: =50000+5000+10000+6000+15000+15000+20000+18000+15000+15000+20000+20000+10000+15000+20000+5000+5000+20000+20000+11000 -> 315000 | F7: Equity owed Percy
C8: =40000+75000+30000+30000+25000+10000 -> 210000 | F8: Equity owed Mercy
C9: =40000 -> 40000 | F9: others(MW)
A10: 45867 | C10: 14572 | F10: Commission from T.Bill
C11: 30000 | F11: Mummy- to be refunded
A12: 46030 | B12: Percy -Cash | C12: =20000-'Dec 2025 Sales'!M3 -> 3700 | F12: Top up for feed
A13: 46048 | B13: T-bill | C13: 424000
A14: 46048 | B14: Percy -Cash | C14: 10000 | F14: Drinker lines
B18: Egg sales | E18: ='PMT Summary'!A3 -> 604093
B19: Broiler 1 Sales | E19: ='PMT Summary'!C32 -> 19320
B20: Christmas sale | E20: ='Dec 2025 Sales'!I98 -> 74130
B21: Outflows
B22: Imprest | D22: ='PMT Summary'!A13 -> 1332023.2
B23: Items from China | D23: =(2000*15.5)+(2000*15.5) -> 62000
B25: Other Expenses
B26: Domiabra fence | D26: =20000+20000 -> 40000
B27: Off Nsawam road Fence | D27: =15000+20000+30000+30000+25000 -> 120000
B28: Repayment to Mummy | D28: 30000 | F28: Ecobank
B29: Repayment to Percy | D29: =50000+10000+C12 -> 63700 | F29: Ecobank
D31: =SUM(D4:D29) -> 1647723.2 | E31: =SUM(E4:E28) -> 1892470.4

Sheet Sheet21
B1: All stock | C1: 80 Birds
A2: Production cost | B2: =SUMIF('Accountable Imprest '!C:C,"Broiler - Set B",'Accountable Imprest '!O:O) -> 47312 | C2: =C3/B3*B2 -> 16456.348
A3: Number of Birds | B3: 230 | C3: 80
A4: Production Unit cost | B4: =B2/B3 -> 205.70435 | C4: =C2/C3 -> 205.70435
A5: Selling Price | B5: =1.4*B4 -> 287.98609
A6: Mark up | B6: 0.4
A7: Eggs | B7: 40
A8: Dressing | B8: 12
A9: Bagging | B9: 3
A10: Delivery | B10: 500
A11: Delivery Unit | B11: =B10/C3 -> 6.25
A12: Selling Price | B12: Rev @185.46GH
A13: =B8+B7+B5+B11 -> 346.23609 | B13: =A13*80 -> 27698.887

Sheet Retro
A1: Retro
A2: Manure Disposal
A3: Sorting & Grading
A4: Staff
A5: Phone

Sheet 6 Months Budget-Layer Set 4
A1: Description | B1: Details | C1: Units | D1: Unit Cost | E1: Total | F1: Actual
A2: Day Old chicks | B2: Cost of bird | C2: 2000 | D2: =1.1*28 -> 30.8 | E2: =C2*D2 -> 61600 | F2: =(1200*24.5)+(800*25) -> 49400
A3: Feed
B4: Koudijis Galdus Magic Feed | C4: =6*4 -> 24 | D4: =1.1*445 -> 489.5 | E4: =C4*D4 -> 11748
B5: Koudijs Chick Starter | C5: =4*4 -> 16 | D5: =1.1*466 -> 512.6 | E5: =C5*D5 -> 8201.6
B6: Koudijs Layer Grower Mash | C6: =2*84 -> 168 | D6: =1.1*425 -> 467.5 | E6: =C6*D6 -> 78540
B7: Koudijs Developer Mash | C7: =2*86 -> 172 | D7: =1.1*415 -> 456.5 | E7: =C7*D7 -> 78518
B8: Koudijs Pre-Layer Mash | C8: 50 | D8: =1.1*410 -> 451 | E8: =C8*D8 -> 22550
B9: Koudijs Layer 1 Mash | C9: 80 | D9: =1.1*429 -> 471.9 | E9: =C9*D9 -> 37752
A11: Meds
B12: Glucovet | C12: =3*4 -> 12 | D12: =1.1*110 -> 121 | E12: =C12*D12 -> 1452
B13: Amprocure | C13: 2 | D13: =1.1*446 -> 490.6 | E13: =C13*D13 -> 981.2
B14: Penstrep | C14: =2*3 -> 6 | D14: =1.1*348 -> 382.8 | E14: =C14*D14 -> 2296.8
B15: Multi Amino M | C15: 4 | D15: =1.1*226 -> 248.6 | E15: =C15*D15 -> 994.4
B16: Vitamino | C16: 3 | D16: =1.1*270 -> 297 | E16: =C16*D16 -> 891
B17: Maridav Amprocox | C17: 2 | D17: =1.1*335 -> 368.5 | E17: =C17*D17 -> 737
B18: Amprocure | C18: 2 | D18: =1.1*426 -> 468.6 | E18: =C18*D18 -> 937.2
B19: Amprocox WS | C19: 2 | D19: =1.1*515 -> 566.5 | E19: =C19*D19 -> 1133
B20: Amprolium 300 1kg | C20: 2 | D20: =1.1*495 -> 544.5 | E20: =C20*D20 -> 1089
B21: Oxytetravet Aerosol | C21: 4 | D21: =1.1*90 -> 99 | E21: =C21*D21 -> 396
B22: Tetracolivit 1kg | C22: 4 | D22: =1.1*465 -> 511.5 | E22: =C22*D22 -> 2046
B23: Colvit 1kg | C23: 2 | D23: =1.1*175 -> 192.5 | E23: =C23*D23 -> 385
B24: Gluco-Vet C | C24: 4 | D24: =1.1*110 -> 121 | E24: =C24*D24 -> 484
B25: Nemovit WS | C25: 2 | D25: =1.1*330 -> 363 | E25: =C25*D25 -> 726
B26: Piperin | C26: 2 | D26: =1.1*463 -> 509.3 | E26: =C26*D26 -> 1018.6
A30: Vaccines
B31: 1st Newcastle Vaccine | C31: 4 | D31: =1.1*110 -> 121 | E31: =C31*D31 -> 484
B32: 1st Gumboro Vaccine | C32: 4 | D32: =1.1*150 -> 165 | E32: =C32*D32 -> 660
B33: 2nd Gumboro Vaccine | C33: 4 | D33: =1.1*160 -> 176 | E33: =C33*D33 -> 704
B34: Lasota Vaccine | C34: 4 | D34: =1.1*120 -> 132 | E34: =C34*D34 -> 528
B35: 2nd Newcastle Vaccination | C35: 2 | D35: =1.1*255 -> 280.5 | E35: =C35*D35 -> 561
B36: 1st Fowl Pox Vaccine | C36: 2 | D36: =1.1*390 -> 429 | E36: =C36*D36 -> 858
B37: Syringe for 3rd Newcastle Vacc. | C37: 20 | D37: =1.1*3 -> 3.3 | E37: =C37*D37 -> 66
B38: 3rd Newcastle Vaccine | C38: 2 | D38: =1.1*730 -> 803 | E38: =C38*D38 -> 1606
B39: Vet for Vaccination | C39: 1 | D39: 1000 | E39: =C39*D39 -> 1000
A41: Others
B42: Postmortem | C42: 1 | D42: 50 | E42: =C42*D42 -> 50
B43: Transportation | C43: 1 | D43: 1000 | E43: =C43*D43 -> 1000
B44: salt | C44: 1 | D44: 200 | E44: =C44*D44 -> 200
B45: Pin for Vaccination | C45: 1 | D45: 10 | E45: =C45*D45 -> 10
B46: Saw dust | C46: 1 | D46: 1000 | E46: =C46*D46 -> 1000
B47: Wages | C47: 6 | D47: 800 | E47: =C47*D47 -> 4800
A49: Total | E49: =SUM(E2:E47) -> 328003.8
A50: Total/month | E50: =(E49-E2)/6 -> 44400.633
